Workbook
Name ADRI: #REF!
Name ALEX_DELCLAUX: #REF!
Name ALVARO_NISTAL: #REF!
Name ANGEL: #REF!
Name ANNA: #REF!
Name ASTARLOA: #REF!
Name BALTHAZAR__VINTED: #REF!
Name BARALLOBRE: #REF!
Name BARTA: #REF!
Name BRUNO: #REF!
Name CAMACHO: #REF!
Name CANALES: #REF!
Name CANDELA: #REF!
Name CARLOTA: #REF!
Name CARMEN: #REF!
Name CASADO: #REF!
Name CASAPE: #REF!
Name CHIARRI: #REF!
Name CHORVO: #REF!
Name CRIS_ARTEAGA: #REF!
Name CUERVO: #REF!
Name DIEGO: #REF!
Name DIEGUITO: #REF!
Name DIRECTOR: #REF!
Name DOMINGUEZ: #REF!
Name FELIX: #REF!
Name FORMARIZ: #REF!
Name GA: #REF!
Name GABRIEL: #REF!
Name GENOVEVA: #REF!
Name IAGO: #REF!
Name IÑIGO: #REF!
Name JAIME_BUSTAMANTE: #REF!
Name JAIME_RAMIREZ: #REF!
Name JAIME_RICO: #REF!
Name JAIME_X: #REF!
Name JORDI: #REF!
Name JOSE: #REF!
Name JP: #REF!
Name JUANMA: #REF!
Name JUANPA: #REF!
Name JUANTO: #REF!
Name JUST.JEANNE__VINTED: #REF!
Name LAURA_PUIG: #REF!
Name LUIS_CANADA: #REF!
Name LYDIABELLET__VINTED: #REF!
Name MARIO_MIRON: #REF!
Name MARQUINA: #REF!
Name MONICA: #REF!
Name MUÑOZ: #REF!
Name NACHO_DE_BENITO: #REF!
Name NACHO_PEREZ: #REF!
Name NATHAN: #REF!
Name NICO_DIAMANTO: #REF!
Name NICO_RUIZ: #REF!
Name PEREZ: #REF!
Name PETER: #REF!
Name PUIG: #REF!
Name PUPI: #REF!
Name QUINTANA: #REF!

Sheet CLIENTES
A1: CLIENTES | E1: CLIENTE | F1: TALLA 2 | G1: TALLA | H1: UNIDADES | I1: INGRESO | J1: DROP
A2: AGO | D2: =1 -> 1 | E2: {='DROP 1'!B65:G65} -> JAIME MILL | F2: M | G2: 1 | H2: 3 | I2: 120 | J2: DROP 1 | L2: Etiquetas de fila | M2: Suma de INGRESO | O2: Etiquetas de fila | P2: Suma de UNIDADES
A3: ALEX DELCAUX | D3: =D2+1 -> 2 | E3: {='DROP 1'!B66:G66} -> PETER | F3: M | G3: 1 | H3: 2 | I3: 105 | J3: DROP 1 | L3: PETER | M3: 421 | O3: L | P3: 100
A4: ALEX GARCIA | D4: =D3+1 -> 3 | E4: {='DROP 1'!B67:G67} -> LUIS CANADA | F4: M | G4: 1 | H4: 2 | I4: 80 | J4: DROP 1 | L4: A33 X NO ART | M4: 70 | O4: M | P4: 85
A5: ALVARO GOMEZ | D5: =D4+1 -> 4 | E5: {='DROP 1'!B68:G68} -> JAIME BUSTAMANTE | F5: M | G5: 1 | H5: 3 | I5: 112 | J5: DROP 1 | L5: DROP 1 | M5: 105 | O5: M, L | P5: 13
A6: ALVARO NISTAL | D6: =D5+1 -> 5 | E6: {='DROP 1'!B69:G69} -> QUINTANA | F6: L | G6: 2 | H6: 1 | I6: 55 | J6: DROP 1 | L6: DROP 2 | M6: 34 | O6: Total general | P6: 198
A7: ALVARO PEREZ | D7: =D6+1 -> 6 | E7: {='DROP 1'!B70:G70} -> MUÑOZ | F7: L | G7: 2 | H7: 4 | I7: 232 | J7: DROP 1 | L7: DROP 3 | M7: 96
A8: AMIGO ANGEL | D8: =D7+1 -> 7 | E8: {='DROP 1'!B71:G71} -> PUIG AMIGO JACO | F8: M | G8: 1 | H8: 1 | I8: 30 | J8: DROP 1 | L8: DROP 4 | M8: 78 | O8: Etiquetas de fila | P8: Suma de UNIDADES
A9: ANA AMIGA JACO | D9: =D8+1 -> 8 | E9: {='DROP 1'!B72:G72} -> GA | F9: M | G9: 1 | H9: 1 | I9: 30 | J9: DROP 1 | L9: DROP 5 | M9: 0 | O9: PETER | P9: 12
A10: ANGEL AMIGO JACO | D10: =D9+1 -> 9 | E10: {='DROP 1'!B73:G73} -> NACHO PEREZ | F10: M | G10: 1 | H10: 1 | I10: 30 | J10: DROP 1 | L10: SUMMER DROP | M10: 38 | O10: JAIME BUSTAMANTE | P10: 12
A11: ASTARLOA | D11: =D10+1 -> 10 | E11: {='DROP 1'!B74:G74} -> CASAPE | F11: M | G11: 1 | H11: 1 | I11: 30 | J11: DROP 1 | L11: MUÑOZ | M11: 398 | O11: MUÑOZ | P11: 11
A12: BARALLOBRE | D12: =D11+1 -> 11 | E12: {='DROP 1'!B75:G75} -> JUANTO | F12: M | G12: 1 | H12: 1 | I12: 55 | J12: DROP 1 | L12: A33 X NO ART | M12: 35 | O12: JUANTO | P12: 8
A13: BARTA | D13: =D12+1 -> 12 | E13: {='DROP 1'!B76:G76} -> DIEGO AMIGO JACO | F13: M | G13: 1 | H13: 1 | I13: 30 | J13: DROP 1 | L13: DROP 1 | M13: 232 | O13: NICO RUIZ | P13: 7
A14: BRUNITO | D14: =D13+1 -> 13 | E14: {='DROP 1'!B77:G77} -> JAIME X | F14: M | G14: 1 | H14: 1 | I14: 30 | J14: DROP 1 | L14: DROP 2 | M14: 78 | O14: BARALLOBRE | P14: 7
A15: CAMACHO | D15: =D14+1 -> 14 | E15: {='DROP 1'!B78:G78} -> AMIGO ANGEL | F15: M | G15: 1 | H15: 1 | I15: 30 | J15: DROP 1 | L15: DROP 4 | M15: 34 | O15: VINTED | P15: 6
A16: CANALES | D16: =D15+1 -> 15 | E16: {='DROP 1'!B79:G79} -> GENOVEVA | F16: M | G16: 1 | H16: 1 | I16: 40 | J16: DROP 1 | L16: DROP 5 | M16: 0 | O16: CHORVO | P16: 6
A17: CANDELA | D17: =D16+1 -> 16 | E17: {='DROP 1'!B80:G80} -> CANDELA | F17: M | G17: 1 | H17: 1 | I17: 40 | J17: DROP 1 | L17: SUMMER DROP | M17: 19 | O17: NACHO PEREZ | P17: 6
A18: CANTERO | D18: =D17+1 -> 17 | E18: {='DROP 2'!B65:G65} -> ANGEL AMIGO JACO | F18: M, L | G18: 3 | H18: 2 | I18: 78 | J18: DROP 2 | L18: JAIME BUSTAMANTE | M18: 393 | O18: DOMINGUEZ | P18: 5
A19: CARLOTA DEL OLMO | D19: =D18+1 -> 18 | E19: {='DROP 2'!B66:G66} -> DIEGO AMIGO JACO | F19: L | G19: 2 | H19: 2 | I19: 63 | J19: DROP 2 | L19: A33 X NO ART | M19: 70 | O19: CASAPE | P19: 5
A20: CARMEN | D20: =D19+1 -> 19 | E20: {='DROP 2'!B67:G67} -> JUANMA | F20: M | G20: 1 | H20: 1 | I20: 29 | J20: DROP 2 | L20: DROP 1 | M20: 112 | O20: QUINTANA | P20: 5
A21: CASADO | D21: =D20+1 -> 20 | E21: {='DROP 2'!B68:G68} -> JUANTO | F21: M | G21: 1 | H21: 2 | I21: 63 | J21: DROP 2 | L21: DROP 2 | M21: 100 | O21: PUIG AMIGO JACO | P21: 5
A22: CASAPE | D22: =D21+1 -> 21 | E22: {='DROP 2'!B69:G69} -> JORGE PUIG | F22: M | G22: 1 | H22: 1 | I22: 49 | J22: DROP 2 | L22: DROP 3 | M22: 33 | O22: JUANMA | P22: 5
A23: CHIARRI | D23: =D22+1 -> 22 | E23: {='DROP 2'!B70:G70} -> NACHO PEREZ | F23: L | G23: 2 | H23: 1 | I23: 34 | J23: DROP 2 | L23: DROP 4 | M23: 78 | O23: BRUNITO | P23: 5
A24: CHORVO | D24: =D23+1 -> 23 | E24: {='DROP 2'!B71:G71} -> PETER | F24: M | G24: 1 | H24: 1 | I24: 34 | J24: DROP 2 | L24: JUANTO | M24: 257 | O24: JORGE PUIG | P24: 5
A25: CRIS ARTEAGA | D25: =D24+1 -> 24 | E25: {='DROP 2'!B72:G72} -> BARALLOBRE | F25: L | G25: 2 | H25: 1 | I25: 29 | J25: DROP 2 | L25: A33 X NO ART | M25: 35 | O25: LUIS CANADA | P25: 4
A26: CUERVO | D26: =D25+1 -> 25 | E26: {='DROP 2'!B73:G73} -> PUIG AMIGO JACO | F26: M | G26: 1 | H26: 2 | I26: 78 | J26: DROP 2 | L26: DROP 1 | M26: 55 | O26: IÑIGO | P26: 4
A27: DIEGO AMIGO JACO | D27: =D26+1 -> 26 | E27: {='DROP 2'!B74:G74} -> FORMARIZ | F27: M | G27: 1 | H27: 1 | I27: 49 | J27: DROP 2 | L27: DROP 2 | M27: 63 | O27: RUBINI | P27: 3
A28: DIEGUITO | D28: =D27+1 -> 27 | E28: {='DROP 2'!B75:G75} -> DOMINGUEZ | F28: L | G28: 2 | H28: 2 | I28: 63 | J28: DROP 2 | L28: DROP 5 | M28: 66 | O28: FORMARIZ | P28: 3
A29: DIRECTOR AMIGO JACO | D29: =D28+1 -> 28 | E29: {='DROP 2'!B76:G76} -> IÑIGO | F29: L | G29: 2 | H29: 1 | I29: 40 | J29: DROP 2 | L29: SUMMER DROP | M29: 38 | O29: IAGO AMIGO JACO | P29: 3
... A44: JOSE AMIGO JACO | D44: =D43+1 -> 43 | E44: {='DROP 2'!B91:G91} -> BARTA | F44: M | G44: 1 | H44: 1 | I44: 25 | J44: DROP 2 | L44: DROP 4 | M44: 77 | O44: AMIGO ANGEL | P44: 1
A45: JP | D45: =D44+1 -> 44 | E45: {='SUMMER DROP'!B65:G65} -> MUÑOZ | F45: L | G45: 2 | H45: 1 | I45: 19 | J45: SUMMER DROP | L45: SUMMER DROP | M45: 19 | O45: NACHO BENITO | P45: 1
A46: JUANMA | D46: =D45+1 -> 45 | E46: {='SUMMER DROP'!B66:G66} -> PETER | F46: L | G46: 2 | H46: 2 | I46: 38 | J46: SUMMER DROP | L46: CASAPE | M46: 169 | O46: ALVARO GOMEZ | P46: 1
A47: JUANTO | D47: =D46+1 -> 46 | E47: {='SUMMER DROP'!B67:G67} -> JUANMA | F47: L | G47: 2 | H47: 1 | I47: 19 | J47: SUMMER DROP | L47: DROP 1 | M47: 30 | O47: ALEX GARCIA | P47: 1
A48: LAURA PUIG | D48: =D47+1 -> 47 | E48: {='SUMMER DROP'!B68:G68} -> NICO RUIZ | F48: M | G48: 1 | H48: 2 | I48: 38 | J48: SUMMER DROP | L48: DROP 2 | M48: 29 | O48: ALEX DELCAUX | P48: 1
A49: LUCAS MARTINEZ | D49: =D48+1 -> 48 | E49: {='SUMMER DROP'!B69:G69} -> ASTARLOA | F49: L | G49: 2 | H49: 1 | I49: 19 | J49: SUMMER DROP | L49: DROP 4 | M49: 44 | O49: GABRIEL | P49: 1
A50: LUIS CANADA | D50: =D49+1 -> 49 | E50: {='SUMMER DROP'!B70:G70} -> RUBINI | F50: L | G50: 2 | H50: 1 | I50: 19 | J50: SUMMER DROP | L50: DROP 5 | M50: 66 | O50: JAIME RAMIREZ | P50: 1
A51: MARIO MIRON | D51: =D50+1 -> 50 | E51: {='SUMMER DROP'!B71:G71} -> PUIG AMIGO JACO | F51: M | G51: 1 | H51: 1 | I51: 19 | J51: SUMMER DROP | L51: LUIS CANADA | M51: 159 | O51: NATHAN | P51: 1
A52: MARQUINA | D52: =D51+1 -> 51 | E52: {='SUMMER DROP'!B72:G72} -> JUANTO | F52: M | G52: 1 | H52: 2 | I52: 38 | J52: SUMMER DROP | L52: A33 X NO ART | M52: 35 | O52: JAIME X | P52: 1
A53: MMEDRANO | D53: =D52+1 -> 52 | E53: {='SUMMER DROP'!B73:G73} -> NICO DIAMANTO | F53: M | G53: 1 | H53: 1 | I53: 19 | J53: SUMMER DROP | L53: DROP 1 | M53: 80 | O53: FELIX | P53: 1
A54: MONICA AMIGA JACO | D54: =D53+1 -> 53 | E54: {='SUMMER DROP'!B74:G74} -> DOMINGUEZ | F54: L | G54: 2 | H54: 1 | I54: 19 | J54: SUMMER DROP | L54: DROP 4 | M54: 44 | O54: JORGE CALVO | P54: 1
A55: MUÑOZ | D55: =D54+1 -> 54 | E55: {='SUMMER DROP'!B75:G75} -> CHORVO | F55: M | G55: 1 | H55: 1 | I55: 19 | J55: SUMMER DROP | L55: VINTED | M55: 156 | O55: VICTOR PUJOL | P55: 1
A56: NACHO BENITO | D56: =D55+1 -> 55 | E56: {='SUMMER DROP'!B76:G76} -> DIRECTOR AMIGO JACO | F56: M | G56: 1 | H56: 1 | I56: 19 | J56: SUMMER DROP | L56: DROP 2 | M56: 73 | O56: CANALES | P56: 1
... A64: QUINTANA | D64: =D63+1 -> 63 | E64: {='SUMMER DROP'!B84:G84} -> BRUNITO | F64: M | G64: 1 | H64: 1 | I64: 19 | J64: SUMMER DROP | L64: DROP 4 | M64: 33 | O64: RODRI AMIGO JACO | P64: 1
A65: RITXI AMIGO JACO | D65: =D64+1 -> 64 | E65: {='A33 X NO ART'!B65:G65} -> PETER | F65: L | G65: 2 | H65: 2 | I65: 70 | J65: A33 X NO ART | L65: DROP 5 | M65: 0 | O65: BARTA | P65: 1
A66: RODRI AMIGO JACO | D66: =D65+1 -> 65 | E66: {='A33 X NO ART'!B66:G66} -> JP | F66: L | G66: 2 | H66: 1 | I66: 35 | J66: A33 X NO ART | L66: SUMMER DROP | M66: 19 | O66: SAMUEL | P66: 1
A67: RUBINI | D67: =D66+1 -> 66 | E67: {='A33 X NO ART'!B67:G67} -> PUPI | F67: M | G67: 1 | H67: 1 | I67: 35 | J67: A33 X NO ART | L67: DOMINGUEZ | M67: 150 | O67: SESE | P67: 1
A68: SAMUEL | D68: =D67+1 -> 67 | E68: {='A33 X NO ART'!B68:G68} -> SESE | F68: L | G68: 2 | H68: 1 | I68: 35 | J68: A33 X NO ART | L68: A33 X NO ART | M68: 35 | O68: JP | P68: 1
A69: SANDRO ROCCI | D69: =D68+1 -> 68 | E69: {='A33 X NO ART'!B69:G69} -> LUIS CANADA | F69: M | G69: 1 | H69: 1 | I69: 35 | J69: A33 X NO ART | L69: DROP 2 | M69: 63 | O69: RITXI AMIGO JACO | P69: 1
A70: SEANFUL | D70: =D69+1 -> 69 | E70: {='A33 X NO ART'!B70:G70} -> MUÑOZ | F70: L | G70: 2 | H70: 1 | I70: 35 | J70: A33 X NO ART | L70: DROP 5 | M70: 33 | O70: CANDELA | P70: 1
A71: SESE | D71: =D70+1 -> 70 | E71: {='A33 X NO ART'!B71:G71} -> NACHO BENITO | F71: L | G71: 2 | H71: 1 | I71: 35 | J71: A33 X NO ART | L71: SUMMER DROP | M71: 19 | O71: CUERVO | P71: 1
A72: SUAREZ | D72: =D71+1 -> 71 | E72: {='A33 X NO ART'!B72:G72} -> NACHO PEREZ | F72: M | G72: 1 | H72: 1 | I72: 35 | J72: A33 X NO ART | L72: IÑIGO | M72: 147 | O72: CANTERO | P72: 1
A73: TITO | D73: =D72+1 -> 72 | E73: {='A33 X NO ART'!B73:G73} -> DOMINGUEZ | F73: M | G73: 1 | H73: 1 | I73: 35 | J73: A33 X NO ART | L73: DROP 2 | M73: 40 | O73: SANDRO ROCCI | P73: 1
A74: TOMAS ACHA | D74: =D73+1 -> 73 | E74: {='A33 X NO ART'!B74:G74} -> CHORVO | F74: L | G74: 2 | H74: 2 | I74: 70 | J74: A33 X NO ART | L74: DROP 3 | M74: 69 | O74: LAURA PUIG | P74: 1
A75: VICTOR PUJOL | D75: =D74+1 -> 74 | E75: {='A33 X NO ART'!B75:G75} -> CUERVO | F75: M | G75: 1 | H75: 1 | I75: 35 | J75: A33 X NO ART | L75: SUMMER DROP | M75: 38 | O75: SUAREZ | P75: 1
A76: VINTED | D76: =D75+1 -> 75 | E76: {='A33 X NO ART'!B76:G76} -> JUANTO | F76: M | G76: 1 | H76: 1 | I76: 35 | J76: A33 X NO ART | L76: TITO | M76: 142 | O76: LUCAS MARTINEZ | P76: 1
A77: WEITERS | D77: =D76+1 -> 76 | E77: {='A33 X NO ART'!B77:G77} -> ALVARO NISTAL | F77: M | G77: 1 | H77: 1 | I77: 35 | J77: A33 X NO ART | L77: DROP 2 | M77: 45 | O77: TOMAS ACHA | P77: 1
D78: =D77+1 -> 77 | E78: {='A33 X NO ART'!B78:G78} -> BARALLOBRE | F78: L | G78: 2 | H78: 2 | I78: 60 | J78: A33 X NO ART | L78: DROP 3 | M78: 63 | O78: CARLOTA DEL OLMO | P78: 1
D79: =D78+1 -> 78 | E79: {='A33 X NO ART'!B79:G79} -> GABRIEL | F79: M | G79: 1 | H79: 1 | I79: 35 | J79: A33 X NO ART | L79: DROP 4 | M79: 34 | O79: DIEGUITO | P79: 1
D80: =D79+1 -> 79 | E80: {='A33 X NO ART'!B80:G80} -> NATHAN | F80: M | G80: 1 | H80: 1 | I80: 35 | J80: A33 X NO ART | L80: JORGE PUIG | M80: 131 | O80: MARIO MIRON | P80: 1
D81: =D80+1 -> 80 | E81: {='A33 X NO ART'!B81:G81} -> JAIME BUSTAMANTE | F81: M, L | G81: 3 | H81: 2 | I81: 70 | J81: A33 X NO ART | L81: DROP 2 | M81: 49 | O81: DIRECTOR AMIGO JACO | P81: 1
D82: =D81+1 -> 81 | E82: {='A33 X NO ART'!B82:G82} -> JUANMA | F82: M | G82: 1 | H82: 1 | I82: 35 | J82: A33 X NO ART | L82: DROP 3 | M82: 63 | O82: MARQUINA | P82: 1
D83: =D82+1 -> 82 | E83: {='A33 X NO ART'!B83:G83} -> CRIS ARTEAGA | F83: L | G83: 2 | H83: 1 | I83: 35 | J83: A33 X NO ART | L83: DROP 5 | M83: 0 | O83: Total general | P83: 198
D84: =D83+1 -> 83 | E84: {='A33 X NO ART'!B84:G84} -> BRUNITO | F84: M | G84: 1 | H84: 1 | I84: 35 | J84: A33 X NO ART | L84: SUMMER DROP | M84: 19
D85: =D84+1 -> 84 | E85: {='A33 X NO ART'!B85:G85} -> CANALES | F85: M | G85: 1 | H85: 1 | I85: 0 | J85: A33 X NO ART | L85: PUIG AMIGO JACO | M85: 127
D86: =D85+1 -> 85 | E86: {='DROP 3'!B65:G65} -> CARMEN | F86: L | G86: 2 | H86: 1 | I86: 69 | J86: DROP 3 | L86: DROP 1 | M86: 30
D87: =D86+1 -> 86 | E87: {='DROP 3'!B66:G66} -> IÑIGO | F87: L | G87: 2 | H87: 1 | I87: 69 | J87: DROP 3 | L87: DROP 2 | M87: 78
D88: =D87+1 -> 87 | E88: {='DROP 3'!B67:G67} -> PETER | F88: L | G88: 2 | H88: 2 | I88: 96 | J88: DROP 3 | L88: DROP 5 | M88: 0
D89: =D88+1 -> 88 | E89: {='DROP 3'!B68:G68} -> JORGE PUIG | F89: M | G89: 1 | H89: 1 | I89: 63 | J89: DROP 3 | L89: SUMMER DROP | M89: 19
D90: =D89+1 -> 89 | E90: {='DROP 3'!B69:G69} -> ALEX DELCAUX | F90: L | G90: 2 | H90: 1 | I90: 33 | J90: DROP 3 | L90: JAIME MILL | M90: 120
D91: =D90+1 -> 90 | E91: {='DROP 3'!B70:G70} -> TITO | F91: L | G91: 2 | H91: 1 | I91: 63 | J91: DROP 3 | L91: DROP 1 | M91: 120
D92: =D91+1 -> 91 | E92: {='DROP 3'!B71:G71} -> IAGO AMIGO JACO | F92: M | G92: 1 | H92: 1 | I92: 33 | J92: DROP 3 | L92: BRUNITO | M92: 117
D93: =D92+1 -> 92 | E93: {='DROP 3'!B72:G72} -> BRUNITO | F93: M | G93: 1 | H93: 1 | I93: 63 | J93: DROP 3 | L93: A33 X NO ART | M93: 35
D94: =D93+1 -> 93 | E94: {='DROP 3'!B73:G73} -> SAMUEL | F94: M | G94: 1 | H94: 1 | I94: 30 | J94: DROP 3 | L94: DROP 3 | M94: 63
D95: =D94+1 -> 94 | E95: {='DROP 3'!B74:G74} -> VICTOR PUJOL | F95: M | G95: 1 | H95: 1 | I95: 33 | J95: DROP 3 | L95: DROP 4 | M95: 0
D96: =D95+1 -> 95 | E96: {='DROP 3'!B75:G75} -> CAMACHO | F96: M | G96: 1 | H96: 1 | I96: 33 | J96: DROP 3 | L96: SUMMER DROP | M96: 19
D97: =D96+1 -> 96 | E97: {='DROP 3'!B76:G76} -> VINTED | F97: L | G97: 2 | H97: 1 | I97: 26 | J97: DROP 3 | L97: FORMARIZ | M97: 116
D98: =D97+1 -> 97 | E98: {='DROP 3'!B77:G77} -> JAIME BUSTAMANTE | F98: L | G98: 2 | H98: 1 | I98: 33 | J98: DROP 3 | L98: DROP 2 | M98: 49
D99: =D98+1 -> 98 | E99: {='DROP 4'!B65:G65} -> JAIME RAMIREZ | F99: L | G99: 2 | H99: 1 | I99: 34 | J99: DROP 4 | L99: DROP 4 | M99: 34
D100: =D99+1 -> 99 | E100: {='DROP 4'!B66:G66} -> CASAPE | F100: L | G100: 2 | H100: 1 | I100: 44 | J100: DROP 4 | L100: DROP 5 | M100: 33
D101: =D100+1 -> 100 | E101: {='DROP 4'!B67:G67} -> IAGO AMIGO JACO | F101: M | G101: 1 | H101: 1 | I101: 44 | J101: DROP 4 | L101: QUINTANA | M101: 114
D102: =D101+1 -> 101 | E102: {='DROP 4'!B68:G68} -> LAURA PUIG | F102: L | G102: 2 | H102: 1 | I102: 44 | J102: DROP 4 | L102: DROP 1 | M102: 55
D103: =D102+1 -> 102 | E103: {='DROP 4'!B69:G69} -> PETER | F103: M, L | G103: 3 | H103: 2 | I103: 78 | J103: DROP 4 | L103: DROP 2 | M103: 25
D104: =D103+1 -> 103 | E104: {='DROP 4'!B70:G70} -> DIEGUITO | F104: M | G104: 1 | H104: 1 | I104: 44 | J104: DROP 4 | L104: DROP 4 | M104: 34
D105: =D104+1 -> 104 | E105: {='DROP 4'!B71:G71} -> WEITERS | F105: L | G105: 2 | H105: 1 | I105: 34 | J105: DROP 4 | L105: DROP 5 | M105: 0
D106: =D105+1 -> 105 | E106: {='DROP 4'!B72:G72} -> NICO RUIZ | F106: M | G106: 1 | H106: 2 | I106: 76 | J106: DROP 4 | L106: JUANMA | M106: 113
D107: =D106+1 -> 106 | E107: {='DROP 4'!B73:G73} -> FELIX | F107: L | G107: 2 | H107: 1 | I107: 34 | J107: DROP 4 | L107: A33 X NO ART | M107: 35
D108: =D107+1 -> 107 | E108: {='DROP 4'!B74:G74} -> TITO | F108: L | G108: 2 | H108: 1 | I108: 34 | J108: DROP 4 | L108: DROP 2 | M108: 29
D109: =D108+1 -> 108 | E109: {='DROP 4'!B75:G75} -> FORMARIZ | F109: M | G109: 1 | H109: 1 | I109: 34 | J109: DROP 4 | L109: DROP 4 | M109: 30
D110: =D109+1 -> 109 | E110: {='DROP 4'!B76:G76} -> CASADO | F110: L | G110: 2 | H110: 1 | I110: 34 | J110: DROP 4 | L110: DROP 5 | M110: 0
... D130: =D129+1 -> 129 | E130: {='DROP 4'!B96:G96} -> ALVARO PEREZ | F130: L | G130: 2 | H130: 2 | I130: 0 | J130: DROP 4 | L130: DROP 4 | M130: 0
D131: =D130+1 -> 130 | E131: {='DROP 5'!B65:G65} -> DOMINGUEZ | F131: L | G131: 2 | H131: 1 | I131: 33 | J131: DROP 5 | L131: ALVARO NISTAL | M131: 74
D132: =D131+1 -> 131 | E132: {='DROP 5'!B66:G66} -> BARALLOBRE | F132: L | G132: 2 | H132: 1 | I132: 33 | J132: DROP 5 | L132: A33 X NO ART | M132: 35
D133: =D132+1 -> 132 | E133: {='DROP 5'!B67:G67} -> TOMAS ACHA | F133: L | G133: 2 | H133: 1 | I133: 33 | J133: DROP 5 | L133: DROP 2 | M133: 39
D134: =D133+1 -> 133 | E134: {='DROP 5'!B68:G68} -> FORMARIZ | F134: M | G134: 1 | H134: 1 | I134: 33 | J134: DROP 5 | L134: PUPI | M134: 69
D135: =D134+1 -> 134 | E135: {='DROP 5'!B69:G69} -> CASAPE | F135: L | G135: 2 | H135: 2 | I135: 66 | J135: DROP 5 | L135: A33 X NO ART | M135: 35
D136: =D135+1 -> 135 | E136: {='DROP 5'!B70:G70} -> JUANTO | F136: M | G136: 1 | H136: 2 | I136: 66 | J136: DROP 5 | L136: DROP 4 | M136: 34
D137: =D136+1 -> 136 | E137: {='DROP 5'!B71:G71} -> VINTED | F137: M | G137: 1 | H137: 1 | I137: 33 | J137: DROP 5 | L137: CARMEN | M137: 69
D138: =D137+1 -> 137 | E138: {='DROP 5'!B72:G72} -> NICO RUIZ | F138: L | G138: 2 | H138: 2 | I138: 66 | J138: DROP 5 | L138: DROP 3 | M138: 69
D139: =D138+1 -> 138 | E139: {='DROP 5'!B73:G73} -> CAMACHO | F139: L | G139: 2 | H139: 1 | I139: 0 | J139: DROP 5 | L139: CAMACHO | M139: 67
D140: =D139+1 -> 139 | E140: {='DROP 5'!B74:G74} -> CANTERO | F140: L | G140: 2 | H140: 1 | I140: 0 | J140: DROP 5 | L140: DROP 3 | M140: 33
...

Sheet A33 (NEW)
B2: INVERSION | H2: INGRESOS | P2: GASTOS | AA2: COSTES GENERALES | AB2: €/UND | AC2: UNIDADES | AD2: IVA | AE2: € PER UND
H3: DROP | I3: DROP ANTERIOR | J3: PRESUPUESTO | K3: INGRESOS | L3: %VAR D/A | M3: %PPTO | P3: DROP | Q3: DROP ANTERIOR | R3: PRESUPUESTO | S3: GASTOS | T3: %VAR D/A | U3: %PPTO | AA3: Packaging | AB3: 148.63 | AC3: 100 | AE3: =IFERROR(AB3/AC3,"-") -> 1.4863
H4: 1 | I4: 0 | J4: ='D1'!C8 -> 1015 | K4: ='D1'!D8 -> 0 | L4: =IFERROR(IF(I4<0,-(K4/I4-1),K4/I4-1),"-") -> - | M4: =IFERROR(1+(K4-J4)/ABS(J4),"-") -> 0 | N4: =IF(M4>=1,3,IF(M4>=0.95,2,1)) -> 1 | P4: 1 | Q4: 0 | R4: ='D1'!C14 -> -824.1647 | S4: ='D1'!D14 -> -781.062 | T4: =IFERROR(IF(Q4>0,-(S4/Q4-1),S4/Q4-1),"-") -> - | U4: =IFERROR(1+(S4-R4)/ABS(R4),"-") -> 1.0522986 | V4: =IF(U4>=1,3,IF(U4>=0.95,2,1)) -> 3 | AA4: Etiquetas | AB4: 94.4 | AC4: 100 | AE4: =IFERROR(AB4/AC4,"-") -> 0.944
B5: BENEFICIO | H5: 2 | I5: =K4 -> 0 | L5: =IFERROR(IF(I5<0,-(K5/I5-1),K5/I5-1),"-") -> - | M5: =IFERROR(1+(K5-J5)/ABS(J5),"-") -> - | N5: =IF(M5>=1,3,IF(M5>=0.95,2,1)) -> 3 | P5: 2 | Q5: =S4 -> -781.062 | T5: =IFERROR(IF(Q5>0,-(S5/Q5-1),S5/Q5-1),"-") -> -1 | U5: =IFERROR(1+(S5-R5)/ABS(R5),"-") -> - | V5: =IF(U5>=1,3,IF(U5>=0.95,2,1)) -> 3 | AA5: ='A33'!$S$5 -> 0 | AC5: =#REF! -> #REF! | AD5: =IFERROR(((AB5*AC5)*0.21)/AC5,"-") -> - | AE5: =IFERROR(AB5/AC5,"-") -> -
H6: 3 | I6: =K5 -> 0 | L6: =IFERROR(IF(I6<0,-(K6/I6-1),K6/I6-1),"-") -> - | M6: =IFERROR(1+(K6-J6)/ABS(J6),"-") -> - | N6: =IF(M6>=1,3,IF(M6>=0.95,2,1)) -> 3 | P6: 3 | Q6: =S5 -> 0 | T6: =IFERROR(IF(Q6>0,-(S6/Q6-1),S6/Q6-1),"-") -> - | U6: =IFERROR(1+(S6-R6)/ABS(R6),"-") -> - | V6: =IF(U6>=1,3,IF(U6>=0.95,2,1)) -> 3 | AA6: ='A33'!$S$6 -> 0 | AC6: =#REF! -> #REF! | AD6: =IFERROR(((AB6*AC6)*0.21)/AC6,"-") -> - | AE6: =IFERROR(AB6/AC6,"-") -> -
H7: 4 | I7: =K6 -> 0 | L7: =IFERROR(IF(I7<0,-(K7/I7-1),K7/I7-1),"-") -> - | M7: =IFERROR(1+(K7-J7)/ABS(J7),"-") -> - | N7: =IF(M7>=1,3,IF(M7>=0.95,2,1)) -> 3 | P7: 4 | Q7: =S6 -> 0 | T7: =IFERROR(IF(Q7>0,-(S7/Q7-1),S7/Q7-1),"-") -> - | U7: =IFERROR(1+(S7-R7)/ABS(R7),"-") -> - | V7: =IF(U7>=1,3,IF(U7>=0.95,2,1)) -> 3 | AD7: =IFERROR(((AB7*AC7)*0.21)/AC7,"-") -> - | AE7: =IFERROR(AB7/AC7,"-") -> -
B8: COR | E8: =R27 -> 0.81198493 | H8: 5 | I8: =K7 -> 0 | L8: =IFERROR(IF(I8<0,-(K8/I8-1),K8/I8-1),"-") -> - | M8: =IFERROR(1+(K8-J8)/ABS(J8),"-") -> - | N8: =IF(M8>=1,3,IF(M8>=0.95,2,1)) -> 3 | P8: 5 | Q8: =S7 -> 0 | T8: =IFERROR(IF(Q8>0,-(S8/Q8-1),S8/Q8-1),"-") -> - | U8: =IFERROR(1+(S8-R8)/ABS(R8),"-") -> - | V8: =IF(U8>=1,3,IF(U8>=0.95,2,1)) -> 3 | AD8: =IFERROR(((AB8*AC8)*0.21)/AC8,"-") -> - | AE8: =IFERROR(AB8/AC8,"-") -> -
H9: 6 | I9: =K8 -> 0 | L9: =IFERROR(IF(I9<0,-(K9/I9-1),K9/I9-1),"-") -> - | M9: =IFERROR(1+(K9-J9)/ABS(J9),"-") -> - | N9: =IF(M9>=1,3,IF(M9>=0.95,2,1)) -> 3 | P9: 6 | Q9: =S8 -> 0 | T9: =IFERROR(IF(Q9>0,-(S9/Q9-1),S9/Q9-1),"-") -> - | U9: =IFERROR(1+(S9-R9)/ABS(R9),"-") -> - | V9: =IF(U9>=1,3,IF(U9>=0.95,2,1)) -> 3 | AA9: SERIGRAFIA TOTAL | AC9: =SUM(AC3:AC8) -> #REF!
H10: 7 | I10: =K9 -> 0 | L10: =IFERROR(IF(I10<0,-(K10/I10-1),K10/I10-1),"-") -> - | M10: =IFERROR(1+(K10-J10)/ABS(J10),"-") -> - | N10: =IF(M10>=1,3,IF(M10>=0.95,2,1)) -> 3 | P10: 7 | Q10: =S9 -> 0 | T10: =IFERROR(IF(Q10>0,-(S10/Q10-1),S10/Q10-1),"-") -> - | U10: =IFERROR(1+(S10-R10)/ABS(R10),"-") -> - | V10: =IF(U10>=1,3,IF(U10>=0.95,2,1)) -> 3
H11: 8 | I11: =K10 -> 0 | L11: =IFERROR(IF(I11<0,-(K11/I11-1),K11/I11-1),"-") -> - | M11: =IFERROR(1+(K11-J11)/ABS(J11),"-") -> - | N11: =IF(M11>=1,3,IF(M11>=0.95,2,1)) -> 3 | P11: 8 | Q11: =S10 -> 0 | T11: =IFERROR(IF(Q11>0,-(S11/Q11-1),S11/Q11-1),"-") -> - | U11: =IFERROR(1+(S11-R11)/ABS(R11),"-") -> - | V11: =IF(U11>=1,3,IF(U11>=0.95,2,1)) -> 3
H13: TOTAL | J13: =SUM(J4:J11) -> 1015 | K13: =SUM(K4:K11) -> 0 | M13: =IFERROR(1+(K13-J13)/ABS(J13),"-") -> 0 | N13: =IF(M13>=1,3,IF(M13>=0.95,2,1)) -> 1 | P13: TOTAL | R13: =SUM(R4:R11) -> -824.1647 | S13: =SUM(S4:S11) -> -781.062 | U13: =IFERROR(1+(S13-R13)/ABS(R13),"-") -> 1.0522986 | V13: =IF(U13>=1,3,IF(U13>=0.95,2,1)) -> 3
H16: BENEFICIO | P16: COR%
H17: DROP | I17: DROP ANTERIOR | J17: PRESUPUESTO | K17: BENEFICIO | L17: %VAR D/A | M17: %PPTO | P17: DROP | Q17: DROP ANTERIOR | R17: PRESUPUESTO | S17: COR% | T17: %VAR D/A | U17: %PPTO
H18: 1 | I18: 0 | J18: ='D1'!C17 -> 190.8353 | K18: ='D1'!D17 -> -781.062 | L18: =IFERROR(IF(AND(I18<0,K18>0),-(K18/I18-1),IF(AND(I18>0,K18<0),K18/I18-1,IF(AND(I18<0,K18<0),-(K18/I18-1),K18/I18-1))),"-") -> - | M18: =IFERROR(1+(K18-J18)/ABS(J18),"-") -> -4.0928591 | N18: =IF(M18>=1,3,IF(M18>=0.95,2,1)) -> 1 | P18: 1 | Q18: 0 | R18: ='D1'!C22 -> 0.81198493 | S18: ='D1'!D22 -> - | T18: =IFERROR(CONCATENATE(FIXED(100*(S18-Q18),1),"p.p."),"n.a.") -> n.a. | U18: =IFERROR(CONCATENATE(FIXED(100*(S18-R18),1),"p.p."),"n.a.") -> n.a. | V18: =IFERROR(IF(S18<R18,3,IF(U18>R18,1,2)),"-") -> 1 | W18: =ABS(R4/J4)-R18 -> 0 | X18: =ABS(S4/K4)-S18 -> #DIV/0!
H19: 2 | I19: =K18 -> -781.062 | L19: =IFERROR(IF(AND(I19<0,K19>0),-(K19/I19-1),IF(AND(I19>0,K19<0),K19/I19-1,IF(AND(I19<0,K19<0),-(K19/I19-1),K19/I19-1))),"-") -> -1 | M19: =IFERROR(1+(K19-J19)/ABS(J19),"-") -> - | N19: =IF(M19>=1,3,IF(M19>=0.95,2,1)) -> 3 | P19: 2 | Q19: =S18 -> - | T19: =IFERROR(CONCATENATE(FIXED(100*(S19-Q19),1),"p.p."),"n.a.") -> n.a. | U19: =IFERROR(CONCATENATE(FIXED(100*(S19-R19),1),"p.p."),"n.a.") -> 0,0p.p. | V19: =IFERROR(IF(S19<R19,3,IF(U19>R19,1,2)),"-") -> 1 | W19: =ABS(R5/J5)-R19 -> #DIV/0! | X19: =ABS(S5/K5)-S19 -> #DIV/0!
H20: 3 | I20: =K19 -> 0 | L20: =IFERROR(IF(AND(I20<0,K20>0),-(K20/I20-1),IF(AND(I20>0,K20<0),K20/I20-1,IF(AND(I20<0,K20<0),-(K20/I20-1),K20/I20-1))),"-") -> - | M20: =IFERROR(1+(K20-J20)/ABS(J20),"-") -> - | N20: =IF(M20>=1,3,IF(M20>=0.95,2,1)) -> 3 | P20: 3 | Q20: =S19 -> 0 | T20: =IFERROR(CONCATENATE(FIXED(100*(S20-Q20),1),"p.p."),"n.a.") -> 0,0p.p. | U20: =IFERROR(CONCATENATE(FIXED(100*(S20-R20),1),"p.p."),"n.a.") -> 0,0p.p. | V20: =IFERROR(IF(S20<R20,3,IF(U20>R20,1,2)),"-") -> 1 | W20: =ABS(R6/J6)-R20 -> #DIV/0! | X20: =ABS(S6/K6)-S20 -> #DIV/0!
H21: 4 | I21: =K20 -> 0 | L21: =IFERROR(IF(AND(I21<0,K21>0),-(K21/I21-1),IF(AND(I21>0,K21<0),K21/I21-1,IF(AND(I21<0,K21<0),-(K21/I21-1),K21/I21-1))),"-") -> - | M21: =IFERROR(1+(K21-J21)/ABS(J21),"-") -> - | N21: =IF(M21>=1,3,IF(M21>=0.95,2,1)) -> 3 | P21: 4 | Q21: =S20 -> 0 | T21: =IFERROR(CONCATENATE(FIXED(100*(S21-Q21),1),"p.p."),"n.a.") -> 0,0p.p. | U21: =IFERROR(CONCATENATE(FIXED(100*(S21-R21),1),"p.p."),"n.a.") -> 0,0p.p. | V21: =IFERROR(IF(S21<R21,3,IF(U21>R21,1,2)),"-") -> 1 | W21: =ABS(R7/J7)-R21 -> #DIV/0! | X21: =ABS(S7/K7)-S21 -> #DIV/0!
H22: 5 | I22: =K21 -> 0 | L22: =IFERROR(IF(AND(I22<0,K22>0),-(K22/I22-1),IF(AND(I22>0,K22<0),K22/I22-1,IF(AND(I22<0,K22<0),-(K22/I22-1),K22/I22-1))),"-") -> - | M22: =IFERROR(1+(K22-J22)/ABS(J22),"-") -> - | N22: =IF(M22>=1,3,IF(M22>=0.95,2,1)) -> 3 | P22: 5 | Q22: =S21 -> 0 | T22: =IFERROR(CONCATENATE(FIXED(100*(S22-Q22),1),"p.p."),"n.a.") -> 0,0p.p. | U22: =IFERROR(CONCATENATE(FIXED(100*(S22-R22),1),"p.p."),"n.a.") -> 0,0p.p. | V22: =IFERROR(IF(S22<R22,3,IF(U22>R22,1,2)),"-") -> 1 | W22: =ABS(R8/J8)-R22 -> #DIV/0! | X22: =ABS(S8/K8)-S22 -> #DIV/0!
H23: 6 | I23: =K22 -> 0 | L23: =IFERROR(IF(AND(I23<0,K23>0),-(K23/I23-1),IF(AND(I23>0,K23<0),K23/I23-1,IF(AND(I23<0,K23<0),-(K23/I23-1),K23/I23-1))),"-") -> - | M23: =IFERROR(1+(K23-J23)/ABS(J23),"-") -> - | N23: =IF(M23>=1,3,IF(M23>=0.95,2,1)) -> 3 | P23: 6 | Q23: =S22 -> 0 | T23: =IFERROR(CONCATENATE(FIXED(100*(S23-Q23),1),"p.p."),"n.a.") -> 0,0p.p. | U23: =IFERROR(CONCATENATE(FIXED(100*(S23-R23),1),"p.p."),"n.a.") -> 0,0p.p. | V23: =IFERROR(IF(S23<R23,3,IF(U23>R23,1,2)),"-") -> 1 | W23: =ABS(R9/J9)-R23 -> #DIV/0! | X23: =ABS(S9/K9)-S23 -> #DIV/0!
H24: 7 | I24: =K23 -> 0 | L24: =IFERROR(IF(AND(I24<0,K24>0),-(K24/I24-1),IF(AND(I24>0,K24<0),K24/I24-1,IF(AND(I24<0,K24<0),-(K24/I24-1),K24/I24-1))),"-") -> - | M24: =IFERROR(1+(K24-J24)/ABS(J24),"-") -> - | N24: =IF(M24>=1,3,IF(M24>=0.95,2,1)) -> 3 | P24: 7 | Q24: =S23 -> 0 | T24: =IFERROR(CONCATENATE(FIXED(100*(S24-Q24),1),"p.p."),"n.a.") -> 0,0p.p. | U24: =IFERROR(CONCATENATE(FIXED(100*(S24-R24),1),"p.p."),"n.a.") -> 0,0p.p. | V24: =IFERROR(IF(S24<R24,3,IF(U24>R24,1,2)),"-") -> 1 | W24: =ABS(R10/J10)-R24 -> #DIV/0! | X24: =ABS(S10/K10)-S24 -> #DIV/0!
H25: 8 | I25: =K24 -> 0 | L25: =IFERROR(IF(AND(I25<0,K25>0),-(K25/I25-1),IF(AND(I25>0,K25<0),K25/I25-1,IF(AND(I25<0,K25<0),-(K25/I25-1),K25/I25-1))),"-") -> - | M25: =IFERROR(1+(K25-J25)/ABS(J25),"-") -> - | N25: =IF(M25>=1,3,IF(M25>=0.95,2,1)) -> 3 | P25: 8 | Q25: =S24 -> 0 | T25: =IFERROR(CONCATENATE(FIXED(100*(S25-Q25),1),"p.p."),"n.a.") -> 0,0p.p. | U25: =IFERROR(CONCATENATE(FIXED(100*(S25-R25),1),"p.p."),"n.a.") -> 0,0p.p. | V25: =IFERROR(IF(S25<R25,3,IF(U25>R25,1,2)),"-") -> 1 | W25: =ABS(R11/J11)-R25 -> #DIV/0! | X25: =ABS(S11/K11)-S25 -> #DIV/0!
H27: TOTAL | J27: =SUM(J18:J25) -> 190.8353 | K27: =SUM(K18:K25) -> -781.062 | M27: =IFERROR(1+(K27-J27)/ABS(J27),"-") -> -4.0928591 | N27: =IF(M27>=1,3,IF(M27>=0.95,2,1)) -> 1 | P27: TOTAL | R27: =ABS(R13/J13) -> 0.81198493 | S27: =ABS(S13/K13) -> #DIV/0! | U27: =IFERROR(CONCATENATE(FIXED(100*(S27-R27),1),"p.p."),"n.a.") -> n.a. | V27: =IFERROR(IF(S27<R27,3,IF(U27>R27,1,2)),"-") -> - | W27: =ABS(R13/J13)-R27 -> 0 | X27: =ABS(S13/K13)-S27 -> #DIV/0!
H30: UNIDADES
H31: DROP | I31: DROP ANTERIOR | J31: PRESUPUESTO | K31: UNIDADES | L31: %VAR D/A | M31: %PPTO
H32: 1 | I32: 0 | J32: ='D1'!AH9 -> 29 | K32: ='D1'!O27 -> 0 | L32: =IFERROR(IF(AND(I32<0,K32>0),-(K32/I32-1),IF(AND(I32>0,K32<0),K32/I32-1,IF(AND(I32<0,K32<0),-(K32/I32-1),K32/I32-1))),"-") -> - | M32: =IFERROR(1+(K32-J32)/ABS(J32),"-") -> 0 | N32: =IF(M32>=1,3,IF(M32>=0.95,2,1)) -> 1
H33: 2 | I33: =K32 -> 0 | L33: =IFERROR(IF(AND(I33<0,K33>0),-(K33/I33-1),IF(AND(I33>0,K33<0),K33/I33-1,IF(AND(I33<0,K33<0),-(K33/I33-1),K33/I33-1))),"-") -> - | M33: =IFERROR(1+(K33-J33)/ABS(J33),"-") -> - | N33: =IF(M33>=1,3,IF(M33>=0.95,2,1)) -> 3
H34: 3 | I34: =K33 -> 0 | L34: =IFERROR(IF(AND(I34<0,K34>0),-(K34/I34-1),IF(AND(I34>0,K34<0),K34/I34-1,IF(AND(I34<0,K34<0),-(K34/I34-1),K34/I34-1))),"-") -> - | M34: =IFERROR(1+(K34-J34)/ABS(J34),"-") -> - | N34: =IF(M34>=1,3,IF(M34>=0.95,2,1)) -> 3
H35: 4 | I35: =K34 -> 0 | L35: =IFERROR(IF(AND(I35<0,K35>0),-(K35/I35-1),IF(AND(I35>0,K35<0),K35/I35-1,IF(AND(I35<0,K35<0),-(K35/I35-1),K35/I35-1))),"-") -> - | M35: =IFERROR(1+(K35-J35)/ABS(J35),"-") -> - | N35: =IF(M35>=1,3,IF(M35>=0.95,2,1)) -> 3
H36: 5 | I36: =K35 -> 0 | L36: =IFERROR(IF(AND(I36<0,K36>0),-(K36/I36-1),IF(AND(I36>0,K36<0),K36/I36-1,IF(AND(I36<0,K36<0),-(K36/I36-1),K36/I36-1))),"-") -> - | M36: =IFERROR(1+(K36-J36)/ABS(J36),"-") -> - | N36: =IF(M36>=1,3,IF(M36>=0.95,2,1)) -> 3
H37: 6 | I37: =K36 -> 0 | L37: =IFERROR(IF(AND(I37<0,K37>0),-(K37/I37-1),IF(AND(I37>0,K37<0),K37/I37-1,IF(AND(I37<0,K37<0),-(K37/I37-1),K37/I37-1))),"-") -> - | M37: =IFERROR(1+(K37-J37)/ABS(J37),"-") -> - | N37: =IF(M37>=1,3,IF(M37>=0.95,2,1)) -> 3
H38: 7 | I38: =K37 -> 0 | L38: =IFERROR(IF(AND(I38<0,K38>0),-(K38/I38-1),IF(AND(I38>0,K38<0),K38/I38-1,IF(AND(I38<0,K38<0),-(K38/I38-1),K38/I38-1))),"-") -> - | M38: =IFERROR(1+(K38-J38)/ABS(J38),"-") -> - | N38: =IF(M38>=1,3,IF(M38>=0.95,2,1)) -> 3
H39: 8 | I39: =K38 -> 0 | L39: =IFERROR(IF(AND(I39<0,K39>0),-(K39/I39-1),IF(AND(I39>0,K39<0),K39/I39-1,IF(AND(I39<0,K39<0),-(K39/I39-1),K39/I39-1))),"-") -> - | M39: =IFERROR(1+(K39-J39)/ABS(J39),"-") -> - | N39: =IF(M39>=1,3,IF(M39>=0.95,2,1)) -> 3
H41: TOTAL | J41: =SUM(J32:J39) -> 29 | K41: =SUM(K32:K39) -> 0 | M41: =IFERROR(1+(K41-J41)/ABS(J41),"-") -> 0 | N41: =IF(M41>=1,3,IF(M41>=0.95,2,1)) -> 1

Sheet A33
B2: INGRESOS | J2: GASTOS
B3: DROP | C3: DROP ANTERIOR | D3: PRESUPUESTO | E3: INGRESOS | F3: %VAR D/A | G3: %PPTO | J3: DROP | K3: DROP ANTERIOR | L3: PRESUPUESTO | M3: GASTOS | N3: %VAR D/A | O3: %PPTO
B4: 1 | C4: 0 | D4: ='DROP 1'!C6 -> 1130 | E4: ='DROP 1'!D6 -> 1049 | F4: =IFERROR(IF(C4<0,-(E4/C4-1),E4/C4-1),"-") -> - | G4: =IFERROR(1+(E4-D4)/ABS(D4),"-") -> 0.92831858 | H4: =IF(G4>=1,3,IF(G4>=0.95,2,1)) -> 1 | J4: 1 | K4: 0 | L4: ='DROP 1'!C14 -> -838.1 | M4: ='DROP 1'!D14 -> -838.1 | N4: =IFERROR(IF(K4>0,-(M4/K4-1),M4/K4-1),"-") -> - | O4: =IFERROR(1+(M4-L4)/ABS(L4),"-") -> 1 | P4: =IF(O4>=1,3,IF(O4>=0.95,2,1)) -> 3
B5: 2 | C5: =E4 -> 1049 | D5: ='DROP 2'!C8 -> 1318 | E5: ='DROP 2'!D8 -> 1304 | F5: =IFERROR(IF(C5<0,-(E5/C5-1),E5/C5-1),"-") -> 0.24308866 | G5: =IFERROR(1+(E5-D5)/ABS(D5),"-") -> 0.98937785 | H5: =IF(G5>=1,3,IF(G5>=0.95,2,1)) -> 2 | J5: 2 | K5: =M4 -> -838.1 | L5: ='DROP 2'!C14 -> -1261.695 | M5: ='DROP 2'!D14 -> -1261.695 | N5: =IFERROR(IF(K5>0,-(M5/K5-1),M5/K5-1),"-") -> 0.50542298 | O5: =IFERROR(1+(M5-L5)/ABS(L5),"-") -> 1 | P5: =IF(O5>=1,3,IF(O5>=0.95,2,1)) -> 3
B6: SUMMER DROP | C6: =E5 -> 1304 | D6: ='SUMMER DROP'!C8 -> 494 | E6: ='SUMMER DROP'!D8 -> 494 | F6: =IFERROR(IF(C6<0,-(E6/C6-1),E6/C6-1),"-") -> -0.62116564 | G6: =IFERROR(1+(E6-D6)/ABS(D6),"-") -> 1 | H6: =IF(G6>=1,3,IF(G6>=0.95,2,1)) -> 3 | J6: SUMMER DROP | K6: =M5 -> -1261.695 | L6: ='SUMMER DROP'!C14 -> -211.17 | M6: ='SUMMER DROP'!D14 -> -211.17 | N6: =IFERROR(IF(K6>0,-(M6/K6-1),M6/K6-1),"-") -> -0.83262991 | O6: =IFERROR(1+(M6-L6)/ABS(L6),"-") -> 1 | P6: =IF(O6>=1,3,IF(O6>=0.95,2,1)) -> 3
B7: A33 X NO ART | C7: =E6 -> 494 | D7: ='A33 X NO ART'!C8 -> 875 | E7: ='A33 X NO ART'!D8 -> 830 | F7: =IFERROR(IF(C7<0,-(E7/C7-1),E7/C7-1),"-") -> 0.68016194 | G7: =IFERROR(1+(E7-D7)/ABS(D7),"-") -> 0.94857143 | H7: =IF(G7>=1,3,IF(G7>=0.95,2,1)) -> 1 | J7: A33 X NO ART | K7: =M6 -> -211.17 | L7: ='A33 X NO ART'!C14 -> -790.83 | M7: ='A33 X NO ART'!D14 -> -790.83 | N7: =IFERROR(IF(K7>0,-(M7/K7-1),M7/K7-1),"-") -> 2.7449922 | O7: =IFERROR(1+(M7-L7)/ABS(L7),"-") -> 1 | P7: =IF(O7>=1,3,IF(O7>=0.95,2,1)) -> 3
B8: 3 | C8: =E7 -> 830 | D8: ='DROP 3'!C8 -> 1014 | E8: ='DROP 3'!D8 -> 644 | F8: =IFERROR(IF(C8<0,-(E8/C8-1),E8/C8-1),"-") -> -0.22409639 | G8: =IFERROR(1+(E8-D8)/ABS(D8),"-") -> 0.63510848 | H8: =IF(G8>=1,3,IF(G8>=0.95,2,1)) -> 1 | J8: 3 | K8: =M7 -> -790.83 | L8: ='DROP 3'!C14 -> -948.71 | M8: ='DROP 3'!D14 -> -948.71 | N8: =IFERROR(IF(K8>0,-(M8/K8-1),M8/K8-1),"-") -> 0.19963835 | O8: =IFERROR(1+(M8-L8)/ABS(L8),"-") -> 1 | P8: =IF(O8>=1,3,IF(O8>=0.95,2,1)) -> 3
B9: 4 | C9: =E8 -> 644 | D9: ='DROP 4'!C8 -> 1476 | E9: ='DROP 4'!D8 -> 1267 | F9: =IFERROR(IF(C9<0,-(E9/C9-1),E9/C9-1),"-") -> 0.9673913 | G9: =IFERROR(1+(E9-D9)/ABS(D9),"-") -> 0.85840108 | H9: =IF(G9>=1,3,IF(G9>=0.95,2,1)) -> 1 | J9: 4 | K9: =M8 -> -948.71 | L9: ='DROP 4'!C14 -> -1318.04 | M9: ='DROP 4'!D14 -> -1318.04 | N9: =IFERROR(IF(K9>0,-(M9/K9-1),M9/K9-1),"-") -> 0.38929705 | O9: =IFERROR(1+(M9-L9)/ABS(L9),"-") -> 1 | P9: =IF(O9>=1,3,IF(O9>=0.95,2,1)) -> 3
B10: 5 | C10: =E9 -> 1267 | D10: ='DROP 5'!C8 -> 1221 | E10: ='DROP 5'!D8 -> 363 | F10: =IFERROR(IF(C10<0,-(E10/C10-1),E10/C10-1),"-") -> -0.71349645 | G10: =IFERROR(1+(E10-D10)/ABS(D10),"-") -> 0.2972973 | H10: =IF(G10>=1,3,IF(G10>=0.95,2,1)) -> 1 | J10: 5 | K10: =M9 -> -1318.04 | L10: ='DROP 5'!C14 -> -942.27 | M10: ='DROP 5'!D14 -> -942.27 | N10: =IFERROR(IF(K10>0,-(M10/K10-1),M10/K10-1),"-") -> -0.28509757 | O10: =IFERROR(1+(M10-L10)/ABS(L10),"-") -> 1 | P10: =IF(O10>=1,3,IF(O10>=0.95,2,1)) -> 3
B11: 6 | C11: =E10 -> 363 | F11: =IFERROR(IF(C11<0,-(E11/C11-1),E11/C11-1),"-") -> -1 | G11: =IFERROR(1+(E11-D11)/ABS(D11),"-") -> - | H11: =IF(G11>=1,3,IF(G11>=0.95,2,1)) -> 3 | J11: 6 | K11: =M10 -> -942.27 | N11: =IFERROR(IF(K11>0,-(M11/K11-1),M11/K11-1),"-") -> -1 | O11: =IFERROR(1+(M11-L11)/ABS(L11),"-") -> - | P11: =IF(O11>=1,3,IF(O11>=0.95,2,1)) -> 3
B13: TOTAL | D13: =SUM(D4:D11) -> 7528 | E13: =SUM(E4:E11) -> 5951 | G13: =IFERROR(1+(E13-D13)/ABS(D13),"-") -> 0.79051541 | H13: =IF(G13>=1,3,IF(G13>=0.95,2,1)) -> 1 | J13: TOTAL | L13: =SUM(L4:L11) -> -6310.815 | M13: =SUM(M4:M11) -> -6310.815 | O13: =IFERROR(1+(M13-L13)/ABS(L13),"-") -> 1 | P13: =IF(O13>=1,3,IF(O13>=0.95,2,1)) -> 3
B16: BENEFICIO | J16: COR%
B17: DROP | C17: DROP ANTERIOR | D17: PRESUPUESTO | E17: BENEFICIO | F17: %VAR D/A | G17: %PPTO | J17: DROP | K17: DROP ANTERIOR | L17: PRESUPUESTO | M17: COR% | N17: %VAR D/A | O17: %PPTO
B18: 1 | C18: 0 | D18: ='DROP 1'!C17 -> 291.9 | E18: ='DROP 1'!D17 -> 210.9 | F18: =IFERROR(IF(AND(C18<0,E18>0),-(E18/C18-1),IF(AND(C18>0,E18<0),E18/C18-1,IF(AND(C18<0,E18<0),-(E18/C18-1),E18/C18-1))),"-") -> - | G18: =IFERROR(1+(E18-D18)/ABS(D18),"-") -> 0.72250771 | H18: =IF(G18>=1,3,IF(G18>=0.95,2,1)) -> 1 | J18: 1 | K18: 0 | L18: ='DROP 1'!C20 -> 0.74168142 | M18: ='DROP 1'!D20 -> 0.79895138 | N18: =IFERROR(CONCATENATE(FIXED(100*(M18-K18),1),"p.p."),"n.a.") -> 79,9p.p. | O18: =IFERROR(CONCATENATE(FIXED(100*(M18-L18),1),"p.p."),"n.a.") -> 5,7p.p. | P18: =IFERROR(IF(M18<L18,3,IF(O18>L18,1,2)),"-") -> 1 | Q18: =ABS(L4/D4)-L18 -> 0 | R18: =ABS(M4/E4)-M18 -> 0
B19: 2 | C19: =E18 -> 210.9 | D19: ='DROP 2'!C17 -> 56.305 | E19: ='DROP 2'!D17 -> 42.305 | F19: =IFERROR(IF(AND(C19<0,E19>0),-(E19/C19-1),IF(AND(C19>0,E19<0),E19/C19-1,IF(AND(C19<0,E19<0),-(E19/C19-1),E19/C19-1))),"-") -> -0.7994073 | G19: =IFERROR(1+(E19-D19)/ABS(D19),"-") -> 0.75135423 | H19: =IF(G19>=1,3,IF(G19>=0.95,2,1)) -> 1 | J19: 2 | K19: =M18 -> 0.79895138 | L19: ='DROP 2'!C20 -> 0.95727997 | M19: ='DROP 2'!D20 -> 0.96755752 | N19: =IFERROR(CONCATENATE(FIXED(100*(M19-K19),1),"p.p."),"n.a.") -> 16,9p.p. | O19: =IFERROR(CONCATENATE(FIXED(100*(M19-L19),1),"p.p."),"n.a.") -> 1,0p.p. | P19: =IFERROR(IF(M19<L19,3,IF(O19>L19,1,2)),"-") -> 1 | Q19: =ABS(L5/D5)-L19 -> 0 | R19: =ABS(M5/E5)-M19 -> 0
B20: SUMMER DROP | C20: =E19 -> 42.305 | D20: ='SUMMER DROP'!C17 -> 282.83 | E20: ='SUMMER DROP'!D17 -> 282.83 | F20: =IFERROR(IF(AND(C20<0,E20>0),-(E20/C20-1),IF(AND(C20>0,E20<0),E20/C20-1,IF(AND(C20<0,E20<0),-(E20/C20-1),E20/C20-1))),"-") -> 5.6854982 | G20: =IFERROR(1+(E20-D20)/ABS(D20),"-") -> 1 | H20: =IF(G20>=1,3,IF(G20>=0.95,2,1)) -> 3 | J20: SUMMER DROP | K20: =M19 -> 0.96755752 | L20: ='SUMMER DROP'!C20 -> 0.42746964 | M20: ='SUMMER DROP'!D20 -> 0.42746964 | N20: =IFERROR(CONCATENATE(FIXED(100*(M20-K20),1),"p.p."),"n.a.") -> -54,0p.p. | O20: =IFERROR(CONCATENATE(FIXED(100*(M20-L20),1),"p.p."),"n.a.") -> 0,0p.p. | P20: =IFERROR(IF(M20<L20,3,IF(O20>L20,1,2)),"-") -> 1 | Q20: =ABS(L6/D6)-L20 -> 0 | R20: =ABS(M6/E6)-M20 -> 0
B21: A33 X NO ART | C21: =E20 -> 282.83 | D21: ='A33 X NO ART'!C17 -> 84.17 | E21: ='A33 X NO ART'!D17 -> 39.17 | F21: =IFERROR(IF(AND(C21<0,E21>0),-(E21/C21-1),IF(AND(C21>0,E21<0),E21/C21-1,IF(AND(C21<0,E21<0),-(E21/C21-1),E21/C21-1))),"-") -> -0.86150691 | G21: =IFERROR(1+(E21-D21)/ABS(D21),"-") -> 0.46536771 | H21: =IF(G21>=1,3,IF(G21>=0.95,2,1)) -> 1 | J21: A33 X NO ART | K21: =M20 -> 0.42746964 | L21: ='A33 X NO ART'!C20 -> 0.90380571 | M21: ='A33 X NO ART'!D20 -> 0.95280723 | N21: =IFERROR(CONCATENATE(FIXED(100*(M21-K21),1),"p.p."),"n.a.") -> 52,5p.p. | O21: =IFERROR(CONCATENATE(FIXED(100*(M21-L21),1),"p.p."),"n.a.") -> 4,9p.p. | P21: =IFERROR(IF(M21<L21,3,IF(O21>L21,1,2)),"-") -> 1 | Q21: =ABS(L7/D7)-L21 -> 0 | R21: =ABS(M7/E7)-M21 -> 0
B22: 3 | C22: =E21 -> 39.17 | D22: ='DROP 3'!C17 -> 65.29 | E22: ='DROP 3'!D17 -> -304.71 | F22: =IFERROR(IF(AND(C22<0,E22>0),-(E22/C22-1),IF(AND(C22>0,E22<0),E22/C22-1,IF(AND(C22<0,E22<0),-(E22/C22-1),E22/C22-1))),"-") -> -8.7791677 | G22: =IFERROR(1+(E22-D22)/ABS(D22),"-") -> -4.667024 | H22: =IF(G22>=1,3,IF(G22>=0.95,2,1)) -> 1 | J22: 3 | K22: =M21 -> 0.95280723 | L22: ='DROP 3'!C20 -> 0.93561144 | M22: ='DROP 3'!D20 -> 1.4731522 | N22: =IFERROR(CONCATENATE(FIXED(100*(M22-K22),1),"p.p."),"n.a.") -> 52,0p.p. | O22: =IFERROR(CONCATENATE(FIXED(100*(M22-L22),1),"p.p."),"n.a.") -> 53,8p.p. | P22: =IFERROR(IF(M22<L22,3,IF(O22>L22,1,2)),"-") -> 1 | Q22: =ABS(L8/D8)-L22 -> 0 | R22: =ABS(M8/E8)-M22 -> 0
B23: 4 | C23: =E22 -> -304.71 | D23: ='DROP 4'!C17 -> 157.96 | E23: ='DROP 4'!D17 -> -51.04 | F23: =IFERROR(IF(AND(C23<0,E23>0),-(E23/C23-1),IF(AND(C23>0,E23<0),E23/C23-1,IF(AND(C23<0,E23<0),-(E23/C23-1),E23/C23-1))),"-") -> 0.83249647 | G23: =IFERROR(1+(E23-D23)/ABS(D23),"-") -> -0.32311978 | H23: =IF(G23>=1,3,IF(G23>=0.95,2,1)) -> 1 | J23: 4 | K23: =M22 -> 1.4731522 | L23: ='DROP 4'!C20 -> 0.89298103 | M23: ='DROP 4'!D20 -> 1.0402841 | N23: =IFERROR(CONCATENATE(FIXED(100*(M23-K23),1),"p.p."),"n.a.") -> -43,3p.p. | O23: =IFERROR(CONCATENATE(FIXED(100*(M23-L23),1),"p.p."),"n.a.") -> 14,7p.p. | P23: =IFERROR(IF(M23<L23,3,IF(O23>L23,1,2)),"-") -> 1 | Q23: =ABS(L9/D9)-L23 -> 0 | R23: =ABS(M9/E9)-M23 -> 0
B24: 5 | C24: =E23 -> -51.04 | D24: ='DROP 5'!C17 -> 278.73 | E24: ='DROP 5'!D17 -> -579.27 | F24: =IFERROR(IF(AND(C24<0,E24>0),-(E24/C24-1),IF(AND(C24>0,E24<0),E24/C24-1,IF(AND(C24<0,E24<0),-(E24/C24-1),E24/C24-1))),"-") -> -10.349334 | G24: =IFERROR(1+(E24-D24)/ABS(D24),"-") -> -2.0782478 | H24: =IF(G24>=1,3,IF(G24>=0.95,2,1)) -> 1 | J24: 5 | K24: =M23 -> 1.0402841 | L24: ='DROP 5'!C20 -> 0.7717199 | M24: ='DROP 5'!D20 -> 2.5957851 | N24: =IFERROR(CONCATENATE(FIXED(100*(M24-K24),1),"p.p."),"n.a.") -> 155,6p.p. | O24: =IFERROR(CONCATENATE(FIXED(100*(M24-L24),1),"p.p."),"n.a.") -> 182,4p.p. | P24: =IFERROR(IF(M24<L24,3,IF(O24>L24,1,2)),"-") -> 1 | Q24: =ABS(L10/D10)-L24 -> 0 | R24: =ABS(M10/E10)-M24 -> 0
B25: 6 | C25: =E24 -> -579.27 | F25: =IFERROR(IF(AND(C25<0,E25>0),-(E25/C25-1),IF(AND(C25>0,E25<0),E25/C25-1,IF(AND(C25<0,E25<0),-(E25/C25-1),E25/C25-1))),"-") -> -1 | G25: =IFERROR(1+(E25-D25)/ABS(D25),"-") -> - | H25: =IF(G25>=1,3,IF(G25>=0.95,2,1)) -> 3 | J25: 6 | K25: =M24 -> 2.5957851 | N25: =IFERROR(CONCATENATE(FIXED(100*(M25-K25),1),"p.p."),"n.a.") -> -259,6p.p. | O25: =IFERROR(CONCATENATE(FIXED(100*(M25-L25),1),"p.p."),"n.a.") -> 0,0p.p. | P25: =IFERROR(IF(M25<L25,3,IF(O25>L25,1,2)),"-") -> 1 | Q25: =ABS(L11/D11)-L25 -> #DIV/0! | R25: =ABS(M11/E11)-M25 -> #DIV/0!
B27: TOTAL | D27: =SUM(D18:D25) -> 1217.185 | E27: =SUM(E18:E25) -> -359.815 | G27: =IFERROR(1+(E27-D27)/ABS(D27),"-") -> -0.29561242 | H27: =IF(G27>=1,3,IF(G27>=0.95,2,1)) -> 1 | J27: TOTAL | L27: =ABS(L13/D13) -> 0.8383123 | M27: =ABS(M13/E13) -> 1.0604629 | O27: =IFERROR(CONCATENATE(FIXED(100*(M27-L27),1),"p.p."),"n.a.") -> 22,2p.p. | P27: =IFERROR(IF(M27<L27,3,IF(O27>L27,1,2)),"-") -> 1 | Q27: =ABS(L13/D13)-L27 -> 0 | R27: =ABS(M13/E13)-M27 -> 0
B30: UNIDADES
B31: DROP | C31: DROP ANTERIOR | D31: PRESUPUESTO | E31: UNIDADES | F31: %VAR D/A | G31: %PPTO
B32: 1 | C32: 0 | D32: ='DROP 1'!T9 -> 26 | E32: ='DROP 1'!K24 -> 25 | F32: =IFERROR(IF(AND(C32<0,E32>0),-(E32/C32-1),IF(AND(C32>0,E32<0),E32/C32-1,IF(AND(C32<0,E32<0),-(E32/C32-1),E32/C32-1))),"-") -> - | G32: =IFERROR(1+(E32-D32)/ABS(D32),"-") -> 0.96153846 | H32: =IF(G32>=1,3,IF(G32>=0.95,2,1)) -> 2
B33: 2 | C33: =E32 -> 25 | D33: ='DROP 2'!T9+'DROP 2'!T18 -> 38 | E33: ='DROP 2'!K24 -> 38 | F33: =IFERROR(IF(AND(C33<0,E33>0),-(E33/C33-1),IF(AND(C33>0,E33<0),E33/C33-1,IF(AND(C33<0,E33<0),-(E33/C33-1),E33/C33-1))),"-") -> 0.52 | G33: =IFERROR(1+(E33-D33)/ABS(D33),"-") -> 1 | H33: =IF(G33>=1,3,IF(G33>=0.95,2,1)) -> 3
B34: SUMMER DROP | C34: =E33 -> 38 | D34: ='SUMMER DROP'!T9 -> 26 | E34: ='SUMMER DROP'!K24 -> 26 | F34: =IFERROR(IF(AND(C34<0,E34>0),-(E34/C34-1),IF(AND(C34>0,E34<0),E34/C34-1,IF(AND(C34<0,E34<0),-(E34/C34-1),E34/C34-1))),"-") -> -0.31578947 | G34: =IFERROR(1+(E34-D34)/ABS(D34),"-") -> 1 | H34: =IF(G34>=1,3,IF(G34>=0.95,2,1)) -> 3
B35: A33 X NO ART | C35: =E34 -> 26 | D35: ='A33 X NO ART'!T9 -> 25 | E35: ='A33 X NO ART'!K24 -> 25 | F35: =IFERROR(IF(AND(C35<0,E35>0),-(E35/C35-1),IF(AND(C35>0,E35<0),E35/C35-1,IF(AND(C35<0,E35<0),-(E35/C35-1),E35/C35-1))),"-") -> -0.038461538 | G35: =IFERROR(1+(E35-D35)/ABS(D35),"-") -> 1 | H35: =IF(G35>=1,3,IF(G35>=0.95,2,1)) -> 3
B36: 3 | C36: =E35 -> 25 | D36: ='DROP 3'!T9 -> 22 | E36: ='DROP 3'!K24 -> 14 | F36: =IFERROR(IF(AND(C36<0,E36>0),-(E36/C36-1),IF(AND(C36>0,E36<0),E36/C36-1,IF(AND(C36<0,E36<0),-(E36/C36-1),E36/C36-1))),"-") -> -0.44 | G36: =IFERROR(1+(E36-D36)/ABS(D36),"-") -> 0.63636364 | H36: =IF(G36>=1,3,IF(G36>=0.95,2,1)) -> 1
B37: 4 | C37: =E36 -> 14 | D37: ='DROP 4'!T9 -> 39 | E37: ='DROP 4'!K24 -> 39 | F37: =IFERROR(IF(AND(C37<0,E37>0),-(E37/C37-1),IF(AND(C37>0,E37<0),E37/C37-1,IF(AND(C37<0,E37<0),-(E37/C37-1),E37/C37-1))),"-") -> 1.7857143 | G37: =IFERROR(1+(E37-D37)/ABS(D37),"-") -> 1 | H37: =IF(G37>=1,3,IF(G37>=0.95,2,1)) -> 3
B38: 5 | C38: =E37 -> 39 | D38: ='DROP 5'!T9 -> 37 | E38: ='DROP 5'!K24 -> 27 | F38: =IFERROR(IF(AND(C38<0,E38>0),-(E38/C38-1),IF(AND(C38>0,E38<0),E38/C38-1,IF(AND(C38<0,E38<0),-(E38/C38-1),E38/C38-1))),"-") -> -0.30769231 | G38: =IFERROR(1+(E38-D38)/ABS(D38),"-") -> 0.72972973 | H38: =IF(G38>=1,3,IF(G38>=0.95,2,1)) -> 1
B39: 6 | C39: =E38 -> 27 | F39: =IFERROR(IF(AND(C39<0,E39>0),-(E39/C39-1),IF(AND(C39>0,E39<0),E39/C39-1,IF(AND(C39<0,E39<0),-(E39/C39-1),E39/C39-1))),"-") -> -1 | G39: =IFERROR(1+(E39-D39)/ABS(D39),"-") -> - | H39: =IF(G39>=1,3,IF(G39>=0.95,2,1)) -> 3
B41: TOTAL | D41: =SUM(D32:D39) -> 213 | E41: =SUM(E32:E39) -> 194 | G41: =IFERROR(1+(E41-D41)/ABS(D41),"-") -> 0.91079812 | H41: =IF(G41>=1,3,IF(G41>=0.95,2,1)) -> 1

Sheet BASE
B2: DROP X | S2: BLANKS 1 | T2: UND€ | U2: M | V2: L | W2: XL | X2: UNIDADES | Y2: EXTRA | Z2: € PER UND | AA2: TOTAL | AC2: INGRESOS FINALES | AD2: PRECIO | AE2: M | AF2: L | AG2: XL | AH2: UNIDADES | AI2: TOTAL
X3: =SUM(U3:W3) -> 0 | Y3: =IFERROR($AA$12/$X$9,"-") -> - | Z3: =IFERROR(T3+Y3,"-") -> - | AA3: =IFERROR(X3*Z3,"-") -> - | AC3: =$S$3 -> 0 | AD3: =T40 -> 0 | AE3: =U40-U49 -> 0 | AF3: =V40-V49 -> 0 | AG3: =W40-W49 -> 0 | AH3: =SUM(AE3:AG3) -> 0 | AI3: =IFERROR(AD3*AH3,"-") -> 0
X4: =SUM(U4:W4) -> 0 | Y4: =IFERROR($AA$12/$X$9,"-") -> - | Z4: =IFERROR(T4+Y4,"-") -> - | AA4: =IFERROR(X4*Z4,"-") -> - | AC4: =$S$4 -> 0 | AD4: =T41 -> 0 | AE4: =U41-U50 -> 0 | AF4: =V41-V50 -> 0 | AG4: =W41-W50 -> 0 | AH4: =SUM(AE4:AG4) -> 0 | AI4: =IFERROR(AD4*AH4,"-") -> 0
C5: PPTO | D5: REAL | X5: =SUM(U5:W5) -> 0 | Y5: =IFERROR($AA$12/$X$9,"-") -> - | Z5: =IFERROR(T5+Y5,"-") -> - | AA5: =IFERROR(X5*Z5,"-") -> - | AC5: =$S$5 -> 0 | AD5: =T42 -> 0 | AE5: =U42-U51 -> 0 | AF5: =V42-V51 -> 0 | AG5: =W42-W51 -> 0 | AH5: =SUM(AE5:AG5) -> 0 | AI5: =IFERROR(AD5*AH5,"-") -> 0
B6: INGRESOS | C6: =AI9 -> 0 | D6: =SUM(P27:$P$61) -> 0 | X6: =SUM(U6:W6) -> 0 | Y6: =IFERROR($AA$12/$X$9,"-") -> - | Z6: =IFERROR(T6+Y6,"-") -> - | AA6: =IFERROR(X6*Z6,"-") -> - | AC6: =$S$6 -> 0 | AD6: =T43 -> 0 | AE6: =U43-U52 -> 0 | AF6: =V43-V52 -> 0 | AG6: =W43-W52 -> 0 | AH6: =SUM(AE6:AG6) -> 0 | AI6: =IFERROR(AD6*AH6,"-") -> 0
B7: Otros ingresos | C7: 0 | X7: =SUM(U7:W7) -> 0 | Y7: =IFERROR($AA$12/$X$9,"-") -> - | Z7: =IFERROR(T7+Y7,"-") -> - | AA7: =IFERROR(X7*Z7,"-") -> - | AE7: =U44-U53 -> 0 | AF7: =V44-V53 -> 0 | AG7: =W44-W53 -> 0 | AH7: =SUM(AE7:AG7) -> 0 | AI7: =IFERROR(AD7*AH7,"-") -> 0
B8: TOTAL INGRESOS | C8: =SUM(C6:C7) -> 0 | D8: =SUM(D6:D7) -> 0 | X8: =SUM(U8:W8) -> 0 | Y8: =IFERROR($AA$12/$X$9,"-") -> - | Z8: =IFERROR(T8+Y8,"-") -> - | AA8: =IFERROR(X8*Z8,"-") -> - | AE8: =U45-U54 -> 0 | AF8: =V45-V54 -> 0 | AG8: =W45-W54 -> 0 | AH8: =SUM(AE8:AG8) -> 0 | AI8: =IFERROR(AD8*AH8,"-") -> 0
B9: Gasto Blanks 1 | C9: =-$Z$28 -> 0 | D9: =C9 -> 0 | S9: TOTAL | X9: =SUM(X3:X8) -> 0 | AA9: =SUM(AA3:AA8) -> 0 | AC9: INGRESOS TOTALES FINALES | AH9: =SUM(AH3:AH8) -> 0 | AI9: =SUM(AI3:AI8) -> 0
B10: Gasto Serigrafia | C10: =-$X$37 -> 0 | D10: =C10 -> 0 | S10: Envio
B11: Otros gastos | S11: Otros gastos
S12: TOTAL EXTRAS | AA12: =SUM(AA10:AA11) -> 0
S13: BLANKS TOTAL | AA13: =AA9 -> 0
B14: TOTAL GASTOS | C14: =SUM(C9:C13) -> 0 | D14: =SUM(D9:D13) -> 0 | AA14: =T3*X3+T4*X4+T5*X5+T6*X6+T7*X7+T8*X8+AA12-AA13 -> 0
S15: BLANKS 2 | T15: UND€ | U15: M | V15: L | W15: XL | X15: UNIDADES | Y15: EXTRA | Z15: € PER UND | AA15: TOTAL
X16: =SUM(U16:W16) -> 0 | Y16: =IFERROR($AA$12/$X$9,"-") -> - | Z16: =IFERROR(T16+Y16,"-") -> - | AA16: =IFERROR(X16*Z16,"-") -> -
B17: BENEFICIO | C17: =C8+C14 -> 0 | D17: =D8+D14 -> 0 | X17: =SUM(U17:W17) -> 0 | Y17: =IFERROR($AA$12/$X$9,"-") -> - | Z17: =IFERROR(T17+Y17,"-") -> - | AA17: =IFERROR(X17*Z17,"-") -> -
X18: =SUM(U18:W18) -> 0 | Y18: =IFERROR($AA$12/$X$9,"-") -> - | Z18: =IFERROR(T18+Y18,"-") -> - | AA18: =IFERROR(X18*Z18,"-") -> -
B19: RATIO DE BLANKS | C19: =IFERROR(ABS($C$9/$C$8),"-") -> - | D19: =IFERROR(ABS($D$10/$D$8),"-") -> - | X19: =SUM(U19:W19) -> 0 | Y19: =IFERROR($AA$12/$X$9,"-") -> - | Z19: =IFERROR(T19+Y19,"-") -> - | AA19: =IFERROR(X19*Z19,"-") -> -
B20: COR% | C20: =IFERROR(ABS($C$14/$C$8),"-") -> - | D20: =IFERROR(ABS($D$14/$D$8),"-") -> - | X20: =SUM(U20:W20) -> 0 | Y20: =IFERROR($AA$12/$X$9,"-") -> - | Z20: =IFERROR(T20+Y20,"-") -> - | AA20: =IFERROR(X20*Z20,"-") -> -
X21: =SUM(U21:W21) -> 0 | Y21: =IFERROR($AA$12/$X$9,"-") -> - | Z21: =IFERROR(T21+Y21,"-") -> - | AA21: =IFERROR(X21*Z21,"-") -> -
C22: =$S$3 -> 0 | F22: =$S$4 -> 0 | I22: =$S$5 -> 0 | L22: =$S$6 -> 0 | S22: TOTAL | X22: =SUM(X16:X21) -> 0 | AA22: =SUM(AA16:AA21) -> 0
C23: M | D23: L | E23: XL | F23: M | G23: L | H23: XL | I23: M | J23: L | K23: XL | L23: M | M23: L | N23: XL | O23: TOTAL | S23: Envio
B24: SOLD | C24: =SUM(C27:C61) -> 0 | D24: =SUM(D27:D61) -> 0 | E24: =SUM(E27:E61) -> 0 | F24: =SUM(F27:F61) -> 0 | G24: =SUM(G27:G61) -> 0 | H24: =SUM(H27:H61) -> 0 | I24: =SUM(I27:I61) -> 0 | J24: =SUM(J27:J61) -> 0 | ... N24: =SUM(N27:N61) -> 0 | O24: =SUM(C24:N24) -> 0 | P24: =O24-SUM(O27:O61) -> 0 | S24: Otros gastos
B25: STOCK | C25: =AE3-C24 -> 0 | D25: =AF3-D24 -> 0 | E25: =AG3-E24 -> 0 | F25: =AE4-F24 -> 0 | G25: =AF4-G24 -> 0 | H25: =AG4-H24 -> 0 | I25: =AE5-I24 -> 0 | J25: =AF5-J24 -> 0 | K25: =AG5-K24 -> 0 | L25: =AE6-L24 -> 0 | M25: =AF6-M24 -> 0 | N25: =AG6-N24 -> 0 | O25: =SUM(C25:N25) -> 0 | S25: TOTAL EXTRAS | AA25: =SUM(AA23:AA24) -> 0
B26: NOMBRE | O26: UNIDADES | P26: INGRESO | Q26: FECHA | S26: BLANKS TOTAL | AA26: =-AA22 -> 0
A27: 1 | O27: =SUM(C27:N27) -> 0 | P27: =IFERROR(((C27+D27+E27)*$AD$3)+((F27+G27+H27)*$AD$4)+((I27+J27+K27)*$AD$5)+((L27+M27+N27)*$AD$6),"-") -> 0 | Z27: =T16*X16+T17*X17+T18*X18+T19*X19+T20*X20+T21*X21+AA25+AA26 -> 0
A28: 2 | O28: =SUM(C28:N28) -> 0 | P28: =IFERROR(((C28+D28+E28)*$AD$3)+((F28+G28+H28)*$AD$4)+((I28+J28+K28)*$AD$5)+((L28+M28+N28)*$AD$6),"-") -> 0 | S28: COSTE TOTAL BLANKS | Z28: =AA13+AA26 -> 0
A29: 3 | O29: =SUM(C29:N29) -> 0 | P29: =IFERROR(((C29+D29+E29)*$AD$3)+((F29+G29+H29)*$AD$4)+((I29+J29+K29)*$AD$5)+((L29+M29+N29)*$AD$6),"-") -> 0
A30: =A29+1 -> 4 | O30: =SUM(C30:N30) -> 0 | P30: =IFERROR(((C30+D30+E30)*$AD$3)+((F30+G30+H30)*$AD$4)+((I30+J30+K30)*$AD$5)+((L30+M30+N30)*$AD$6),"-") -> 0 | S30: SERIGRAFIA | T30: €/UND | U30: UNIDADES | V30: IVA | W30: € PER UND | X30: TOTAL
A31: =A30+1 -> 5 | O31: =SUM(C31:N31) -> 0 | P31: =IFERROR(((C31+D31+E31)*$AD$3)+((F31+G31+H31)*$AD$4)+((I31+J31+K31)*$AD$5)+((L31+M31+N31)*$AD$6),"-") -> 0 | S31: =$S$3 -> 0 | U31: =X3 -> 0 | V31: =IFERROR(((T31*U31)*0.21)/U31,"-") -> - | W31: =IFERROR(T31+V31,"-") -> - | X31: =IFERROR(U31*W31,"-") -> -
A32: =A31+1 -> 6 | O32: =SUM(C32:N32) -> 0 | P32: =IFERROR(((C32+D32+E32)*$AD$3)+((F32+G32+H32)*$AD$4)+((I32+J32+K32)*$AD$5)+((L32+M32+N32)*$AD$6),"-") -> 0 | S32: =$S$4 -> 0 | U32: =X4 -> 0 | V32: =IFERROR(((T32*U32)*0.21)/U32,"-") -> - | W32: =IFERROR(T32+V32,"-") -> - | X32: =IFERROR(U32*W32,"-") -> -
A33: =A32+1 -> 7 | O33: =SUM(C33:N33) -> 0 | P33: =IFERROR(((C33+D33+E33)*$AD$3)+((F33+G33+H33)*$AD$4)+((I33+J33+K33)*$AD$5)+((L33+M33+N33)*$AD$6),"-") -> 0 | S33: =$S$5 -> 0 | U33: =X5 -> 0 | V33: =IFERROR(((T33*U33)*0.21)/U33,"-") -> - | W33: =IFERROR(T33+V33,"-") -> - | X33: =IFERROR(U33*W33,"-") -> -
A34: =A33+1 -> 8 | O34: =SUM(C34:N34) -> 0 | P34: =IFERROR(((C34+D34+E34)*$AD$3)+((F34+G34+H34)*$AD$4)+((I34+J34+K34)*$AD$5)+((L34+M34+N34)*$AD$6),"-") -> 0 | S34: =$S$6 -> 0 | U34: =X6 -> 0 | V34: =IFERROR(((T34*U34)*0.21)/U34,"-") -> - | W34: =IFERROR(T34+V34,"-") -> - | X34: =IFERROR(U34*W34,"-") -> -
A35: =A34+1 -> 9 | O35: =SUM(C35:N35) -> 0 | P35: =IFERROR(((C35+D35+E35)*$AD$3)+((F35+G35+H35)*$AD$4)+((I35+J35+K35)*$AD$5)+((L35+M35+N35)*$AD$6),"-") -> 0 | V35: =IFERROR(((T35*U35)*0.21)/U35,"-") -> - | W35: =IFERROR(T35+V35,"-") -> - | X35: =IFERROR(U35*W35,"-") -> -
A36: =A35+1 -> 10 | O36: =SUM(C36:N36) -> 0 | P36: =IFERROR(((C36+D36+E36)*$AD$3)+((F36+G36+H36)*$AD$4)+((I36+J36+K36)*$AD$5)+((L36+M36+N36)*$AD$6),"-") -> 0 | V36: =IFERROR(((T36*U36)*0.21)/U36,"-") -> - | W36: =IFERROR(T36+V36,"-") -> - | X36: =IFERROR(U36*W36,"-") -> -
A37: =A36+1 -> 11 | O37: =SUM(C37:N37) -> 0 | P37: =IFERROR(((C37+D37+E37)*$AD$3)+((F37+G37+H37)*$AD$4)+((I37+J37+K37)*$AD$5)+((L37+M37+N37)*$AD$6),"-") -> 0 | S37: SERIGRAFIA TOTAL | U37: =SUM(U31:U36) -> 0 | X37: =SUM(X31:X36) -> 0
A38: =A37+1 -> 12 | O38: =SUM(C38:N38) -> 0 | P38: =IFERROR(((C38+D38+E38)*$AD$3)+((F38+G38+H38)*$AD$4)+((I38+J38+K38)*$AD$5)+((L38+M38+N38)*$AD$6),"-") -> 0
A39: =A38+1 -> 13 | O39: =SUM(C39:N39) -> 0 | P39: =IFERROR(((C39+D39+E39)*$AD$3)+((F39+G39+H39)*$AD$4)+((I39+J39+K39)*$AD$5)+((L39+M39+N39)*$AD$6),"-") -> 0 | S39: INGRESOS | T39: PRECIO | U39: M | V39: L | W39: XL | X39: UNIDADES | Y39: TOTAL
A40: =A39+1 -> 14 | O40: =SUM(C40:N40) -> 0 | P40: =IFERROR(((C40+D40+E40)*$AD$3)+((F40+G40+H40)*$AD$4)+((I40+J40+K40)*$AD$5)+((L40+M40+N40)*$AD$6),"-") -> 0 | S40: =$S$3 -> 0 | T40: =T66 -> 0 | U40: =U3 -> 0 | V40: =V3 -> 0 | W40: =W3 -> 0 | X40: =SUM(U40:W40) -> 0 | Y40: =IFERROR(T40*X40,"-") -> 0
A41: =A40+1 -> 15 | O41: =SUM(C41:N41) -> 0 | P41: =IFERROR(((C41+D41+E41)*$AD$3)+((F41+G41+H41)*$AD$4)+((I41+J41+K41)*$AD$5)+((L41+M41+N41)*$AD$6),"-") -> 0 | S41: =$S$4 -> 0 | T41: =T67 -> 0 | U41: =U4 -> 0 | V41: =V4 -> 0 | W41: =W4 -> 0 | X41: =SUM(U41:W41) -> 0 | Y41: =IFERROR(T41*X41,"-") -> 0
A42: =A41+1 -> 16 | O42: =SUM(C42:N42) -> 0 | P42: =IFERROR(((C42+D42+E42)*$AD$3)+((F42+G42+H42)*$AD$4)+((I42+J42+K42)*$AD$5)+((L42+M42+N42)*$AD$6),"-") -> 0 | S42: =$S$5 -> 0 | T42: =T68 -> 0 | U42: =U5 -> 0 | V42: =V5 -> 0 | W42: =W5 -> 0 | X42: =SUM(U42:W42) -> 0 | Y42: =IFERROR(T42*X42,"-") -> 0
A43: =A42+1 -> 17 | O43: =SUM(C43:N43) -> 0 | P43: =IFERROR(((C43+D43+E43)*$AD$3)+((F43+G43+H43)*$AD$4)+((I43+J43+K43)*$AD$5)+((L43+M43+N43)*$AD$6),"-") -> 0 | S43: =$S$6 -> 0 | T43: =T69 -> 0 | U43: =U6 -> 0 | V43: =V6 -> 0 | W43: =W6 -> 0 | X43: =SUM(U43:W43) -> 0 | Y43: =IFERROR(T43*X43,"-") -> 0
A44: =A43+1 -> 18 | O44: =SUM(C44:N44) -> 0 | P44: =IFERROR(((C44+D44+E44)*$AD$3)+((F44+G44+H44)*$AD$4)+((I44+J44+K44)*$AD$5)+((L44+M44+N44)*$AD$6),"-") -> 0 | U44: =U7 -> 0 | V44: =V7 -> 0 | W44: =W7 -> 0 | X44: =SUM(U44:W44) -> 0 | Y44: =IFERROR(T44*X44,"-") -> 0
A45: =A44+1 -> 19 | O45: =SUM(C45:N45) -> 0 | P45: =IFERROR(((C45+D45+E45)*$AD$3)+((F45+G45+H45)*$AD$4)+((I45+J45+K45)*$AD$5)+((L45+M45+N45)*$AD$6),"-") -> 0 | U45: =U8 -> 0 | V45: =V8 -> 0 | W45: =W8 -> 0 | X45: =SUM(U45:W45) -> 0 | Y45: =IFERROR(T45*X45,"-") -> 0
A46: =A45+1 -> 20 | O46: =SUM(C46:N46) -> 0 | P46: =IFERROR(((C46+D46+E46)*$AD$3)+((F46+G46+H46)*$AD$4)+((I46+J46+K46)*$AD$5)+((L46+M46+N46)*$AD$6),"-") -> 0 | S46: INGRESOS TOTALES | X46: =SUM(X40:X45) -> 0 | Y46: =SUM(Y40:Y45) -> 0
A47: =A46+1 -> 21 | O47: =SUM(C47:N47) -> 0 | P47: =IFERROR(((C47+D47+E47)*$AD$3)+((F47+G47+H47)*$AD$4)+((I47+J47+K47)*$AD$5)+((L47+M47+N47)*$AD$6),"-") -> 0
A48: =A47+1 -> 22 | O48: =SUM(C48:N48) -> 0 | P48: =IFERROR(((C48+D48+E48)*$AD$3)+((F48+G48+H48)*$AD$4)+((I48+J48+K48)*$AD$5)+((L48+M48+N48)*$AD$6),"-") -> 0 | S48: GON JACO | T48: COSTE | U48: M | V48: L | W48: XL | X48: UNIDADES | Y48: TOTAL
A49: =A48+1 -> 23 | O49: =SUM(C49:N49) -> 0 | P49: =IFERROR(((C49+D49+E49)*$AD$3)+((F49+G49+H49)*$AD$4)+((I49+J49+K49)*$AD$5)+((L49+M49+N49)*$AD$6),"-") -> 0 | S49: =$S$3 -> 0 | T49: =U66 -> 0 | X49: =SUM(U49:W49) -> 0 | Y49: =IFERROR(T49*X49,"-") -> 0
A50: =A49+1 -> 24 | O50: =SUM(C50:N50) -> 0 | P50: =IFERROR(((C50+D50+E50)*$AD$3)+((F50+G50+H50)*$AD$4)+((I50+J50+K50)*$AD$5)+((L50+M50+N50)*$AD$6),"-") -> 0 | S50: =$S$4 -> 0 | T50: =U67 -> 0 | X50: =SUM(U50:W50) -> 0 | Y50: =IFERROR(T50*X50,"-") -> 0
A51: =A50+1 -> 25 | O51: =SUM(C51:N51) -> 0 | P51: =IFERROR(((C51+D51+E51)*$AD$3)+((F51+G51+H51)*$AD$4)+((I51+J51+K51)*$AD$5)+((L51+M51+N51)*$AD$6),"-") -> 0 | S51: =$S$5 -> 0 | T51: =U68 -> 0 | X51: =SUM(U51:W51) -> 0 | Y51: =IFERROR(T51*X51,"-") -> 0
A52: =A51+1 -> 26 | O52: =SUM(C52:N52) -> 0 | P52: =IFERROR(((C52+D52+E52)*$AD$3)+((F52+G52+H52)*$AD$4)+((I52+J52+K52)*$AD$5)+((L52+M52+N52)*$AD$6),"-") -> 0 | S52: =$S$6 -> 0 | T52: =U69 -> 0 | X52: =SUM(U52:W52) -> 0 | Y52: =IFERROR(T52*X52,"-") -> 0
A53: =A52+1 -> 27 | O53: =SUM(C53:N53) -> 0 | P53: =IFERROR(((C53+D53+E53)*$AD$3)+((F53+G53+H53)*$AD$4)+((I53+J53+K53)*$AD$5)+((L53+M53+N53)*$AD$6),"-") -> 0 | X53: =SUM(U53:W53) -> 0 | Y53: =IFERROR(T53*X53,"-") -> 0
A54: =A53+1 -> 28 | O54: =SUM(C54:N54) -> 0 | P54: =IFERROR(((C54+D54+E54)*$AD$3)+((F54+G54+H54)*$AD$4)+((I54+J54+K54)*$AD$5)+((L54+M54+N54)*$AD$6),"-") -> 0 | X54: =SUM(U54:W54) -> 0 | Y54: =IFERROR(T54*X54,"-") -> 0
A55: =A54+1 -> 29 | O55: =SUM(C55:N55) -> 0 | P55: =IFERROR(((C55+D55+E55)*$AD$3)+((F55+G55+H55)*$AD$4)+((I55+J55+K55)*$AD$5)+((L55+M55+N55)*$AD$6),"-") -> 0 | S55: COSTE TOTAL | X55: =SUM(X49:X54) -> 0 | Y55: =SUM(Y49:Y54) -> 0
A56: =A55+1 -> 30 | O56: =SUM(C56:N56) -> 0 | P56: =IFERROR(((C56+D56+E56)*$AD$3)+((F56+G56+H56)*$AD$4)+((I56+J56+K56)*$AD$5)+((L56+M56+N56)*$AD$6),"-") -> 0
A57: =A56+1 -> 31 | O57: =SUM(C57:N57) -> 0 | P57: =IFERROR(((C57+D57+E57)*$AD$3)+((F57+G57+H57)*$AD$4)+((I57+J57+K57)*$AD$5)+((L57+M57+N57)*$AD$6),"-") -> 0 | S57: COSTE POR UND | T57: BLANKS | U57: SERIGRAFIA | V57: EXTRA | W57: TOTAL
A58: =A57+1 -> 32 | O58: =SUM(C58:N58) -> 0 | P58: =IFERROR(((C58+D58+E58)*$AD$3)+((F58+G58+H58)*$AD$4)+((I58+J58+K58)*$AD$5)+((L58+M58+N58)*$AD$6),"-") -> 0 | S58: =$S$3 -> 0 | T58: =Z3 -> - | U58: =W31 -> - | W58: =SUM(T58:V58) -> 0
A59: =A58+1 -> 33 | O59: =SUM(C59:N59) -> 0 | P59: =IFERROR(((C59+D59+E59)*$AD$3)+((F59+G59+H59)*$AD$4)+((I59+J59+K59)*$AD$5)+((L59+M59+N59)*$AD$6),"-") -> 0 | S59: =$S$4 -> 0 | T59: =Z4 -> - | U59: =W32 -> - | W59: =SUM(T59:V59) -> 0
A60: =A59+1 -> 34 | O60: =SUM(C60:N60) -> 0 | P60: =IFERROR(((C60+D60+E60)*$AD$3)+((F60+G60+H60)*$AD$4)+((I60+J60+K60)*$AD$5)+((L60+M60+N60)*$AD$6),"-") -> 0 | S60: =$S$5 -> 0 | T60: =Z5 -> - | U60: =W33 -> - | W60: =SUM(T60:V60) -> 0
A61: =A60+1 -> 35 | O61: =SUM(C61:N61) -> 0 | P61: =IFERROR(((C61+D61+E61)*$AD$3)+((F61+G61+H61)*$AD$4)+((I61+J61+K61)*$AD$5)+((L61+M61+N61)*$AD$6),"-") -> 0 | S61: =$S$6 -> 0 | T61: =Z6 -> - | U61: =W34 -> - | W61: =SUM(T61:V61) -> 0
W62: =SUM(T62:V62) -> 0
W63: =SUM(T63:V63) -> 0
A65: 1 | B65: =B27 -> 0 | C65: =_xlfn.TEXTJOIN(", ",TRUE, IF(OR(C27>0,F27>0,I27>0,L27>0),"M",""), IF(OR(D27>0,G27>0,J27>0,M27>0),"L",""), IF(OR(E27>0,H27>0,K27>0,N27>0),"XL","") ) | D65: =IF(C65="M",1,IF(C65="L",2,IF(C65="XL",3))) -> FALSE | E65: =O27 -> 0 | F65: =P27 -> 0 | G65: =$B$2 -> DROP X | S65: BENEFICIO POR UND | T65: PRECIO | U65: COSTE | V65: BENEFICIO | W65: MARGEN
A66: 2 | B66: =B28 -> 0 | C66: =_xlfn.TEXTJOIN(", ",TRUE, IF(OR(C28>0,F28>0,I28>0,L28>0),"M",""), IF(OR(D28>0,G28>0,J28>0,M28>0),"L",""), IF(OR(E28>0,H28>0,K28>0,N28>0),"XL","") ) | D66: =IF(C66="M",1,IF(C66="L",2,IF(C66="XL",3))) -> FALSE | E66: =O28 -> 0 | F66: =P28 -> 0 | G66: =$B$2 -> DROP X | S66: =$S$3 -> 0 | U66: =-W58 -> 0 | V66: =SUM(T66:U66) -> 0 | W66: =V66/T66 -> #DIV/0!
A67: 3 | B67: =B29 -> 0 | C67: =_xlfn.TEXTJOIN(", ",TRUE, IF(OR(C29>0,F29>0,I29>0,L29>0),"M",""), IF(OR(D29>0,G29>0,J29>0,M29>0),"L",""), IF(OR(E29>0,H29>0,K29>0,N29>0),"XL","") ) | D67: =IF(C67="M",1,IF(C67="L",2,IF(C67="XL",3))) -> FALSE | E67: =O29 -> 0 | F67: =P29 -> 0 | G67: =$B$2 -> DROP X | S67: =$S$4 -> 0 | U67: =-W59 -> 0 | V67: =SUM(T67:U67) -> 0 | W67: =V67/T67 -> #DIV/0!
A68: =A67+1 -> 4 | B68: =B30 -> 0 | C68: =_xlfn.TEXTJOIN(", ",TRUE, IF(OR(C30>0,F30>0,I30>0,L30>0),"M",""), IF(OR(D30>0,G30>0,J30>0,M30>0),"L",""), IF(OR(E30>0,H30>0,K30>0,N30>0),"XL","") ) | D68: =IF(C68="M",1,IF(C68="L",2,IF(C68="XL",3))) -> FALSE | E68: =O30 -> 0 | F68: =P30 -> 0 | G68: =$B$2 -> DROP X | S68: =$S$5 -> 0 | U68: =-W60 -> 0 | V68: =SUM(T68:U68) -> 0 | W68: =V68/T68 -> #DIV/0!
A69: =A68+1 -> 5 | B69: =B31 -> 0 | C69: =_xlfn.TEXTJOIN(", ",TRUE, IF(OR(C31>0,F31>0,I31>0,L31>0),"M",""), IF(OR(D31>0,G31>0,J31>0,M31>0),"L",""), IF(OR(E31>0,H31>0,K31>0,N31>0),"XL","") ) | D69: =IF(C69="M",1,IF(C69="L",2,IF(C69="XL",3))) -> FALSE | E69: =O31 -> 0 | F69: =P31 -> 0 | G69: =$B$2 -> DROP X | S69: =$S$6 -> 0 | U69: =-W61 -> 0 | V69: =SUM(T69:U69) -> 0 | W69: =V69/T69 -> #DIV/0!
A70: =A69+1 -> 6 | B70: =B32 -> 0 | C70: =_xlfn.TEXTJOIN(", ",TRUE, IF(OR(C32>0,F32>0,I32>0,L32>0),"M",""), IF(OR(D32>0,G32>0,J32>0,M32>0),"L",""), IF(OR(E32>0,H32>0,K32>0,N32>0),"XL","") ) | D70: =IF(C70="M",1,IF(C70="L",2,IF(C70="XL",3))) -> FALSE | E70: =O32 -> 0 | F70: =P32 -> 0 | G70: =$B$2 -> DROP X
A71: =A70+1 -> 7 | B71: =B33 -> 0 | C71: =_xlfn.TEXTJOIN(", ",TRUE, IF(OR(C33>0,F33>0,I33>0,L33>0),"M",""), IF(OR(D33>0,G33>0,J33>0,M33>0),"L",""), IF(OR(E33>0,H33>0,K33>0,N33>0),"XL","") ) | D71: =IF(C71="M",1,IF(C71="L",2,IF(C71="XL",3))) -> FALSE | E71: =O33 -> 0 | F71: =P33 -> 0 | G71: =$B$2 -> DROP X
A72: =A71+1 -> 8 | B72: =B34 -> 0 | C72: =_xlfn.TEXTJOIN(", ",TRUE, IF(OR(C34>0,F34>0,I34>0,L34>0),"M",""), IF(OR(D34>0,G34>0,J34>0,M34>0),"L",""), IF(OR(E34>0,H34>0,K34>0,N34>0),"XL","") ) | D72: =IF(C72="M",1,IF(C72="L",2,IF(C72="XL",3))) -> FALSE | E72: =O34 -> 0 | F72: =P34 -> 0 | G72: =$B$2 -> DROP X
A73: =A72+1 -> 9 | B73: =B35 -> 0 | C73: =_xlfn.TEXTJOIN(", ",TRUE, IF(OR(C35>0,F35>0,I35>0,L35>0),"M",""), IF(OR(D35>0,G35>0,J35>0,M35>0),"L",""), IF(OR(E35>0,H35>0,K35>0,N35>0),"XL","") ) | D73: =IF(C73="M",1,IF(C73="L",2,IF(C73="XL",3))) -> FALSE | E73: =O35 -> 0 | F73: =P35 -> 0 | G73: =$B$2 -> DROP X
A74: =A73+1 -> 10 | B74: =B36 -> 0 | C74: =_xlfn.TEXTJOIN(", ",TRUE, IF(OR(C36>0,F36>0,I36>0,L36>0),"M",""), IF(OR(D36>0,G36>0,J36>0,M36>0),"L",""), IF(OR(E36>0,H36>0,K36>0,N36>0),"XL","") ) | D74: =IF(C74="M",1,IF(C74="L",2,IF(C74="XL",3))) -> FALSE | E74: =O36 -> 0 | F74: =P36 -> 0 | G74: =$B$2 -> DROP X
A75: =A74+1 -> 11 | B75: =B37 -> 0 | C75: =_xlfn.TEXTJOIN(", ",TRUE, IF(OR(C37>0,F37>0,I37>0,L37>0),"M",""), IF(OR(D37>0,G37>0,J37>0,M37>0),"L",""), IF(OR(E37>0,H37>0,K37>0,N37>0),"XL","") ) | D75: =IF(C75="M",1,IF(C75="L",2,IF(C75="XL",3))) -> FALSE | E75: =O37 -> 0 | F75: =P37 -> 0 | G75: =$B$2 -> DROP X
A76: =A75+1 -> 12 | B76: =B38 -> 0 | C76: =_xlfn.TEXTJOIN(", ",TRUE, IF(OR(C38>0,F38>0,I38>0,L38>0),"M",""), IF(OR(D38>0,G38>0,J38>0,M38>0),"L",""), IF(OR(E38>0,H38>0,K38>0,N38>0),"XL","") ) | D76: =IF(C76="M",1,IF(C76="L",2,IF(C76="XL",3))) -> FALSE | E76: =O38 -> 0 | F76: =P38 -> 0 | G76: =$B$2 -> DROP X
A77: =A76+1 -> 13 | B77: =B39 -> 0 | C77: =_xlfn.TEXTJOIN(", ",TRUE, IF(OR(C39>0,F39>0,I39>0,L39>0),"M",""), IF(OR(D39>0,G39>0,J39>0,M39>0),"L",""), IF(OR(E39>0,H39>0,K39>0,N39>0),"XL","") ) | D77: =IF(C77="M",1,IF(C77="L",2,IF(C77="XL",3))) -> FALSE | E77: =O39 -> 0 | F77: =P39 -> 0 | G77: =$B$2 -> DROP X
A78: =A77+1 -> 14 | B78: =B40 -> 0 | C78: =_xlfn.TEXTJOIN(", ",TRUE, IF(OR(C40>0,F40>0,I40>0,L40>0),"M",""), IF(OR(D40>0,G40>0,J40>0,M40>0),"L",""), IF(OR(E40>0,H40>0,K40>0,N40>0),"XL","") ) | D78: =IF(C78="M",1,IF(C78="L",2,IF(C78="XL",3))) -> FALSE | E78: =O40 -> 0 | F78: =P40 -> 0 | G78: =$B$2 -> DROP X
A79: =A78+1 -> 15 | B79: =B41 -> 0 | C79: =_xlfn.TEXTJOIN(", ",TRUE, IF(OR(C41>0,F41>0,I41>0,L41>0),"M",""), IF(OR(D41>0,G41>0,J41>0,M41>0),"L",""), IF(OR(E41>0,H41>0,K41>0,N41>0),"XL","") ) | D79: =IF(C79="M",1,IF(C79="L",2,IF(C79="XL",3))) -> FALSE | E79: =O41 -> 0 | F79: =P41 -> 0 | G79: =$B$2 -> DROP X
A80: =A79+1 -> 16 | B80: =B42 -> 0 | C80: =_xlfn.TEXTJOIN(", ",TRUE, IF(OR(C42>0,F42>0,I42>0,L42>0),"M",""), IF(OR(D42>0,G42>0,J42>0,M42>0),"L",""), IF(OR(E42>0,H42>0,K42>0,N42>0),"XL","") ) | D80: =IF(C80="M",1,IF(C80="L",2,IF(C80="XL",3))) -> FALSE | E80: =O42 -> 0 | F80: =P42 -> 0 | G80: =$B$2 -> DROP X
A81: =A80+1 -> 17 | B81: =B43 -> 0 | C81: =_xlfn.TEXTJOIN(", ",TRUE, IF(OR(C43>0,F43>0,I43>0,L43>0),"M",""), IF(OR(D43>0,G43>0,J43>0,M43>0),"L",""), IF(OR(E43>0,H43>0,K43>0,N43>0),"XL","") ) | D81: =IF(C81="M",1,IF(C81="L",2,IF(C81="XL",3))) -> FALSE | E81: =O43 -> 0 | F81: =P43 -> 0 | G81: =$B$2 -> DROP X
... A99: =A98+1 -> 35 | B99: =B61 -> 0 | C99: =_xlfn.TEXTJOIN(", ",TRUE, IF(OR(C61>0,F61>0,I61>0,L61>0),"M",""), IF(OR(D61>0,G61>0,J61>0,M61>0),"L",""), IF(OR(E61>0,H61>0,K61>0,N61>0),"XL","") ) | D99: =IF(C99="M",1,IF(C99="L",2,IF(C99="XL",3))) -> FALSE | E99: =O61 -> 0 | F99: =P61 -> 0 | G99: =$B$2 -> DROP X

Sheet REVOLUT
H2: A33 | J2: DROP 1 | N2: DROP 2 | R2: SUMMER DROP | V2: A33 X NO ART | Z2: DROP 3 | AD2: DROP 4 | AH2: DROP 5
G3: DROP 1 | H3: =L14 -> 1039.41
A4: TOPUP | B4: Current | C4: 44338.993 | D4: A33: 1 SUDAPA GRIS D1 (PETER) | E4: 55 | G4: DROP 2 | H4: =P34 -> 297.92 | J4: 44338.993 | K4: A33: 1 SUDAPA GRIS D1 (PETER) | L4: 55 | N4: =C12 -> 44467.677 | O4: COMPRA RUE PORTER | P4: =E12 -> -780.23 | R4: 44690.781 | S4: COMPRA WORDANS PRUEBA | T4: =E45 -> -9.84 | V4: =C64 -> 44819.083 | W4: COMPRA RUE PORTER | X4: =E64 -> -405.11 | Z4: =C37 -> 44620.86 | AA4: COMPRA RUE PORTER | AB4: =E37 -> -433.02 | AD4: =C77 -> 44872.176 | AE4: COMPRA PRUEBA STUDIOS TC | AF4: =E77 -> -89.68 | AH4: =C114 -> 45260 | AI4: =D114 -> COMPRA STUDIOS TC | AJ4: =E114 -> -713.58
A5: TOPUP | B5: Current | C5: 44341.712 | D5: A33: 1 CAMI MADRID D1 (LUISAN) | E5: 30 | G5: SUMMER DROP | H5: =T20 -> 282.83 | J5: 44341.712 | K5: A33: 1 CAMI MADRID D1 (LUISAN) | L5: 30 | N5: =C13 -> 44467.683 | O5: COMPRA RUE PORTER | P5: =E13 -> -107.2 | R5: 44699.84 | S5: COMPRA WORDANS | T5: =E46 -> -108.16 | V5: =C65 -> 44842.782 | W5: TASAS RUE PORTER | X5: =E65 -> -173.3 | Z5: =C40 -> 44630.828 | AA5: COMPRA MOOJI MOOJI | AB5: =E40 -> -423.53 | AD5: =C80 -> 44887.169 | AE5: DEVOLUCION A STUDIOS TC | AF5: =E80 -> -17.64 | AH5: =C116 -> 45323 | AI5: =D116 -> SERIGRAFIA | AJ5: =E116 -> -228.69
A6: TOPUP | B6: Current | C6: 44392.816 | D6: A33: 1 SUDAPA Y 1 CAMI (JAIME BUST) | E6: 80 | G6: A33 X NO ART | H6: =X20 -> 39.22 | J6: 44392.816 | K6: A33: 1 SUDAPA Y 1 CAMI (JAIME BUST) | L6: 80 | N6: =C14 -> 44471.086 | O6: COMPRA DORTEX | P6: =E14 -> -49.01 | R6: 44706.836 | S6: SERIGRAFIA | T6: =E47 -> -93.17 | V6: =C70 -> 44868.085 | W6: A33: 1 BALACLAVA L Y SKULL L (PETER) | X6: =E70 -> 70 | Z6: =C41 -> 44658.211 | AA6: TASAS MOOJI MOOJI (PAGADO POR MAMA) | AB6: =E41 -> -109.14 | AD6: =C82 -> 44898.375 | AE6: REEMBOLSO DE STUDIOS TC | AF6: =E82 -> 89.68 | AH6: 45372 | AI6: =D119 -> A33: GRAF L Y BRAILE L (DOMINGUEZ) | AJ6: =E119 -> 66
A7: TOPUP | B7: Current | C7: 44399.158 | D7: A33: CAMI VERDE Y BLANCA Y SUDAPA (JAIME$) Y SUDAPA (LUISAN) | E7: 170 | G7: DROP 3 | H7: =AB29 -> -315.56 | J7: 44399.158 | K7: A33: CAMI VERDE Y BLANCA Y SUDAPA (JAIME$) Y SUDAPA (LUISAN) | L7: 170 | N7: =C16 -> 44477.03 | O7: AÑADE DINERO PARA SERIGRAFIA | P7: =E16 -> 178.87 | R7: 44718.755 | S7: A33: 3 SAND XL (JUANMA, MUÑOZ Y PETER) 1 RUSA XL (PETER) | T7: =E49 -> 38 | V7: =C71 -> 44868.092 | W7: A33: 1 BALACLAVA L (JP) | X7: =E71 -> 35.34 | Z7: =C44 -> 44688.992 | AA7: DEVOLUCION RUE PORTER | AB7: =E44 -> 455.17 | AD7: =C90 -> 45034.161 | AE7: COMPRA WEEKDAY | AF7: =E90 -> -108 | AJ7: =I90 -> 0
A8: TOPUP | B8: Current | C8: 44400.061 | D8: A33: SUDAPA (QUINTANA) | E8: 55 | G8: DROP 4 | H8: =AF33 -> -170.55 | J8: 44400.061 | K8: A33: SUDAPA (QUINTANA) | L8: 55 | N8: =C17 -> 44477.036 | O8: SERIGRAFIA | P8: =E17 -> -246.24 | R8: 44718.99 | S8: A33: 1 RUSA XL (PETER) | T8: =E50 -> 38 | V8: =C72 -> 44868.735 | W8: A33: 2 BALACLAVA M (PUPI, LUIS CAN) SKULL XL (SESE) | X8: =E72 -> 105 | Z8: =C66 -> 44848.097 | AA8: SERIGRAFIA | AB8: =E66 -> -29.04 | AD8: =C91 -> 45034.738 | AE8: A33: CREW N L (CASAPE), CAMI XL (JAIME RAMIEZ) | AF8: =E91 -> 78 | AJ8: =I91 -> 0
A9: TOPUP | B9: Current | C9: 44403.834 | D9: A33: SUDAPA GRIS (GENO) | E9: 40.41 | H9: =SUM(H3:H8) -> 1173.27 | J9: 44403.834 | K9: A33: SUDAPA GRIS (GENO) | L9: 40.41 | N9: =C18 -> 44502.812 | O9: APPLE PAY | P9: =E18 -> 40 | R9: 44726.266 | S9: A33: 1 SAND L y 1 RUSA L (Nico) | T9: =E52 -> 38 | V9: =C73 -> 44870.278 | W9: A33: 2 BALACLAVA L (Muñoz) | X9: =E73 -> 35 | Z9: =C67 -> 44848.89 | AA9: COMPRA CAMISETAS FUTBOL | AB9: =E67 -> -387 | AD9: =C92 -> 45035.637 | AE9: COMPRA VELOUR GARMETS | AF9: =E92 -> -634.99 | AJ9: =I92 -> 0
A10: TOPUP | B10: Current | C10: 44410.081 | D10: A33: 3 SUDAPAS 1 CAMI BLANCA (MUÑOZ) Y SUDAPA GRIS (AMIGA GENO) | E10: 272 | J10: 44410.081 | K10: A33: 3 SUDAPAS 1 CAMI BLANCA (MUÑOZ) Y SUDAPA GRIS (AMIGA GENO) | L10: 272 | N10: =C19 -> 44503.724 | O10: COMPRA PEGATINAS | P10: =E19 -> -26.33 | R10: 44728.932 | S10: A33: 1 RUSA XL (ASTARLOA) | T10: =E53 -> 19 | V10: =C74 -> 44871.174 | W10: A33: 1 BALACLAVA M (Dominguez), 2 SKULL ML (N.Per y N.Ben) | X10: =E74 -> 105 | Z10: =C68 -> 44863.065 | AA10: A33: MOOJI L (CARMEN) | AB10: =E68 -> 69 | AD10: =C93 -> 45035.702 | AE10: COMPRA STUDIOS TC | AF10: =E93 -> -357.25 | AJ10: =I93 -> 0
A11: TOPUP | B11: Current | C11: 44454.166 | D11: A33: 1 SUDAPA, 3 CAMIS BLANCAS, 3 CAMIS VERDES (AMIGOS JACO) | E11: 255 | J11: 44454.166 | K11: A33: 1 SUDAPA, 3 CAMIS BLANCAS, 3 CAMIS VERDES (AMIGOS JACO) | L11: 255 | N11: =C20 -> 44514.179 | O11: A33: CAMI TIRO L Y CAMI PIVA L (DOMINGEZ) | P11: =E20 -> 63 | R11: 44729.223 | S11: A33: 1 MANOS XL (RUBINI) | T11: =E54 -> 19 | V11: =C75 -> 44871.175 | W11: A33: 1 BALACLAVA L (C.Chorvo), 2 SKULL ML (C.chorv y cuervo) | X11: =E75 -> 105 | Z11: =C69 -> 44868.085 | AA11: A33: FUTBOL XL (PETER) | AB11: =E69 -> 36 | AD11: =C96 -> 45043.269 | AE11: A33: CREW N M, CAMI L (PETER) | AF11: =E96 -> 78 | AJ11: =I96 -> 0
A12: CARD_PAYMENT | B12: Current | C12: 44467.677 | D12: COMPRA RUE PORTER | E12: -780.23 | J12: 44472.893 | K12: A33: 1 SUDAPA TIRO D1 (PETER) | L12: 50 | N12: =C21 -> 44515.68 | O12: A33: CAMI TIRO M (PETER) | P12: =E21 -> 34.37 | R12: 44730.408 | S12: A33: 3 RUSAS L Y 1 XL (PUIG,JUANTO,BRABUS,DOMING), 1 MANOS L (JUANTO) | T12: =E55 -> 95 | V12: =C76 -> 44871.284 | W12: SERIGRAFIA | X12: =E76 -> -212.71 | Z12: =C84 -> 44938.718 | AA12: A33: REVOLUTION L (IÑIGO) | AB12: =E84 -> 69 | AD12: =C97 -> 45043.27 | AE12: A33: CREW M L (LAURA), CREW N M (IAGO) | AF12: =E97 -> 88 | AJ12: =I97 -> 0
A13: CARD_PAYMENT | B13: Current | C13: 44467.683 | D13: COMPRA RUE PORTER | E13: -107.2 | J13: 44626.071 | K13: A33: 1 SUDAPA CARA D1 (AMIGO JAIME) | L13: 32 | N13: =C22 -> 44516.098 | O13: A33: EFECTIVO Y OTRO | P13: =E22 -> 187 | R13: 44730.87 | S13: A33: 1 MANOS L (CHORBO) | T13: =E56 -> 19 | V13: =C78 -> 44875.727 | W13: A33: 1 BALACLAVA M (Nistal), 2 SKULL ML (Juanto, Barallobre) | X13: =E78 -> 105 | Z13: =C86 -> 44982.198 | AA13: A33: FUTBOL XL (ALEX DELCLAUX) | AB13: =E86 -> 33 | AD13: =C98 -> 45043.659 | AE13: SERIGRAFIA | AF13: =E98 -> -217.8 | AJ13: =I98 -> 0
A14: CARD_PAYMENT | B14: Current | C14: 44471.086 | D14: COMPRA DORTEX | E14: -49.01 | L14: =SUM(L4:L13) -> 1039.41 | N14: =C23 -> 44516.168 | O14: A33: OTRO | P14: =E23 -> 63 | R14: 44734.16 | S14: A33: 1 RUSA L (DIRECTOR) | T14: =E57 -> 19 | V14: =C79 -> 44876.766 | W14: A33: 1 BALACLAVA M (GABRIEL) | X14: =E79 -> 35 | Z14: =C87 -> 44994.152 | AA14: A33: FUTBOL XL (IAGO) REVOLUTION L (TITO) | AB14: =E87 -> 96 | AD14: =C100 -> 45066.87 | AE14: A33: 2 CREW N M (nico y juli), CAMI ML (Nico y weister) | AF14: =E100 -> 154 | AJ14: =I100 -> 0
A15: TOPUP | B15: Current | C15: 44472.893 | D15: A33: 1 SUDAPA TIRO D1 (PETER) | E15: 50 | N15: =C24 -> 44517.234 | O15: A33: SUDAPA M, CAMI MARRON M (PUIG) | P15: =E24 -> 78 | R15: 44734.714 | S15: A33: 1 RUSA L (NACHO), RUSA XL MANOS XL (JOSE) | T15: =E58 -> 57 | V15: =C81 -> 44887.212 | W15: A33: 1 BALACLAVA M (nathan) | X15: =E81 -> 35 | Z15: =C88 -> 44994.157 | AA15: A33: REVOLUTION M (BRUNO) | AB15: =E88 -> 63 | AD15: =C101 -> 45067.205 | AE15: A33: 4 CAMI 3L 1M (FELIX, TITO, CASADO Y FORMAS) | AF15: =E101 -> 136 | AJ15: =I101 -> 0
A16: TOPUP | B16: Current | C16: 44477.03 | D16: AÑADE DINERO PARA SERIGRAFIA | E16: 178.87 | N16: =C25 -> 44527.932 | O16: A33: OTRO | P16: =E25 -> 78 | R16: 44736.823 | S16: A33: 1 RUSA L Y XL (CASADO Y BARALLOBRE), MANOS L Y XL (IAGO Y BARALLOBRE) | T16: =E59 -> 76 | V16: =C83 -> 44899.092 | W16: A33: 2 BALACLAVA M y L (Zorrila y Dani cris arte) | X16: =E83 -> 70 | Z16: =C95 -> 45043.264 | AA16: A33: 2 REVOLUTION M Y L (JORDI Y PETER) | AB16: =E95 -> 123 | AD16: =C102 -> 45067.212 | AE16: A33: 2 CAMI L(PUPI y rubini) y SUDAPA M L (RUBAS) | AF16: =E102 -> 112 | AJ16: =I102 -> 0
A17: TRANSFER | B17: Current | C17: 44477.036 | D17: SERIGRAFIA | E17: -246.24 | N17: =C26 -> 44536.097 | O17: A33: SUDAPA M (FORMARIZ) | P17: =E26 -> 49 | R17: 44743.054 | S17: A33: 1 MANOS L (JORDI) | T17: =E60 -> 19 | V17: =C85 -> 44938.72 | W17: A33: 1 BALACLAVA L (JAIME), SKULL M (JAIME) | X17: =E85 -> 70 | Z17: =C99 -> 45063.18 | AA17: A33: 1 FUTBOL L (SAMUEL) | AB17: =E99 -> 30 | AD17: =C103 -> 45079.027 | AE17: A33: 2 CAMI L(MONICA Y CAMA) y SUDAPA M M (ANNA) | AF17: =E103 -> 112.01 | AJ17: =I103 -> 0
A18: TOPUP | B18: Current | C18: 44502.812 | D18: APPLE PAY | E18: 40 | N18: =C27 -> 44537.173 | O18: A33: SUDAPA L (STRIPE) | P18: =E27 -> 52.7 | R18: 44783.086 | S18: A33: 1 MANOS XL Y RUSA XL (IÑIGO) | T18: =E61 -> 38 | V18: =C89 -> 44994.157 | W18: A33: 1 BALACLAVA M (BRUNO) | X18: =E89 -> 35 | Z18: =C106 -> 45101.156 | AA18: A33: 1 FUTBOL L (VICTOR) | AB18: =E106 -> 33 | AD18: =C104 -> 45091.817 | AE18: A33: 2 CAMI XL(MUÑOZ) y SUDAPA N M (CHIARRI) | AF18: =E104 -> 78.12 | AJ18: =I104 -> 0
A19: CARD_PAYMENT | B19: Current | C19: 44503.724 | D19: COMPRA PEGATINAS | E19: -26.33 | N19: =C28 -> 44540.681 | O19: A33: CAMI MARRON L (MUÑOZ) | P19: =E28 -> 29 | R19: 44783.285 | S19: A33: 1 MANOS L (BRUNO) | T19: =E62 -> 19 | V19: =C94 -> 45041.09 | W19: A33: 1 BALACLAVA L (BARALLOBRE) | X19: =E94 -> 25 | Z19: =C109 -> 45105.731 | AA19: A33: 1 FUTBOL L (VINTED) | AB19: =E109 -> 33 | AD19: =C105 -> 45098.102 | AE19: A33: CAMI L (QUINTANA) | AF19: =E105 -> 34 | AJ19: =I105 -> 0
A20: TOPUP | B20: Current | C20: 44514.179 | D20: A33: CAMI TIRO L Y CAMI PIVA L (DOMINGEZ) | E20: 63 | N20: =C29 -> 44545.051 | O20: A33: SUDAPA L (STRIPE) | P20: =E29 -> 54.3 | T20: =SUM(T4:T19) -> 282.83 | X20: =SUM(X4:X19) -> 39.22 | Z20: 45251 | AA20: A33: FUTBOL XL (VINTED) | AB20: =E113 -> 26 | AD20: =C107 -> 45101.156 | AE20: A33: SUDAPA N M (luisan) | AF20: =E107 -> 44 | AJ20: =I107 -> 0
A21: TOPUP | B21: Current | C21: 44515.68 | D21: A33: CAMI TIRO M (PETER) | E21: 34.37 | N21: =C30 -> 44548.915 | O21: A33: CAMI TIRO L (RODRI) | P21: =E30 -> 34 | AB21: 0 | AD21: =C108 -> 45105.731 | AE21: A33: CAMI L (JUANMA) | AF21: =E108 -> 30 | AJ21: =I108 -> 0
A22: TOPUP | B22: Current | C22: 44516.098 | D22: A33: EFECTIVO Y OTRO | E22: 187 | N22: =C31 -> 44549.115 | O22: A33: 1 SUDAPA OJOS L (TITO) | P22: =E31 -> 45 | AB22: 0 | AD22: =C110 -> 45133.818 | AE22: A33: CAMI M y XL (NACHO.P Y MARQUINA) | AF22: =E110 -> 66 | AJ22: =I110 -> 0
A23: TOPUP | B23: Current | C23: 44516.168 | D23: A33: OTRO | E23: 63 | N23: =C32 -> 44550.201 | O23: A33: SUDAPA L (ALVARO NISTAL) | P23: =E32 -> 39 | AB23: 0 | AD23: =C111 -> 45240.911 | AE23: A33: CAMI M y sudapa M (CHORVO) | AF23: =E111 -> 78 | AJ23: =I111 -> 0
A24: TOPUP | B24: Current | C24: 44517.234 | D24: A33: SUDAPA M, CAMI MARRON M (PUIG) | E24: 78 | N24: =C33 -> 44551.387 | O24: A33: SUDAPA L (MARIO MIRON) | P24: =E33 -> 49 | AB24: 0 | AD24: =C112 -> 45244.929 | AE24: A33: CAMI L (BARALLOBRE) | AF24: =E112 -> 33 | AJ24: =I112 -> 0
A25: TOPUP | B25: Current | C25: 44527.932 | D25: A33: OTRO | E25: 78 | N25: =C34 -> 44557.358 | O25: A33: SUDAPA M (CHIARRI) | P25: =E34 -> 39 | AB25: 0 | AD25: 45260 | AE25: A33: SUDAPA L M (RITXI) | AF25: =E115 -> 44 | AJ25: =I115 -> 0
A26: TOPUP | B26: Current | C26: 44536.097 | D26: A33: SUDAPA M (FORMARIZ) | E26: 49 | N26: =C35 -> 44561.25 | O26: A33: SUDAPA M (AMIGO MUÑOZ) | P26: =E35 -> 49 | AB26: 0 | AF26: 0 | AJ26: 0
A27: TOPUP | B27: Current | C27: 44537.173 | D27: A33: SUDAPA L (STRIPE) | E27: 52.7 | N27: =C36 -> 44620.858 | O27: A33: VINTED | P27: =E36 -> 73 | AB27: 0 | AF27: 0 | AJ27: 0
A28: TOPUP | B28: Current | C28: 44540.681 | D28: A33: CAMI MARRON L (MUÑOZ) | E28: 29 | N28: =C39 -> 44626.071 | O28: A33: 2 CAMI TIRO M Y L, 2 CAMI PIVA M (JAIME Y AMIGO) | P28: =E39 -> 100.02 | AB28: 0 | AF28: 0 | AJ28: 0
A29: TOPUP | B29: Current | C29: 44545.051 | D29: A33: SUDAPA L (STRIPE) | E29: 54.3 | N29: =C42 -> 44658.724 | O29: A33: SUDAPA OJOS L (IÑIGO) | P29: =E42 -> 40.67 | AB29: =SUM(AB4:AB28) -> -315.56 | AF29: 0 | AJ29: 0
A30: TOPUP | B30: Current | C30: 44548.915 | D30: A33: CAMI TIRO L (RODRI) | E30: 34 | N30: =C43 -> 44677.237 | O30: A33: CAMI TIRO M (NICO) | P30: =E43 -> 25 | AF30: 0 | AJ30: 0
A31: TOPUP | B31: Current | C31: 44549.115 | D31: A33: 1 SUDAPA OJOS L (TITO) | E31: 45 | N31: =C48 -> 44716.206 | O31: A33: CAMI TIRO M (BARTA) | P31: =E48 -> 25 | AF31: 0 | AJ31: 0
A32: TOPUP | B32: Current | C32: 44550.201 | D32: A33: SUDAPA L (ALVARO NISTAL) | E32: 39 | N32: =C51 -> 44722.86 | O32: A33: CAMI TIRO L (QUINTANA) | P32: =E51 -> 25 | AF32: 0 | AJ32: 0
A33: TOPUP | B33: Current | C33: 44551.387 | D33: A33: SUDAPA L (MARIO MIRON) | E33: 49 | N33: =C63 -> 44783.285 | O33: A33: CAMI MARRON L , CAMI TIRO M (CASAPE, SANZ = DEUDA JACO) | P33: =E63 -> 56 | AF33: =SUM(AF4:AF32) -> -170.55 | AJ33: =SUM(AJ4:AJ32) -> -876.27
A34: TOPUP | B34: Current | C34: 44557.358 | D34: A33: SUDAPA M (CHIARRI) | E34: 39 | P34: =SUM(P4:P33) -> 297.92
A35: TOPUP | B35: Current | C35: 44561.25 | D35: A33: SUDAPA M (AMIGO MUÑOZ) | E35: 49
A36: TOPUP | B36: Current | C36: 44620.858 | D36: A33: VINTED | E36: 73
A37: CARD_PAYMENT | B37: Current | C37: 44620.86 | D37: COMPRA RUE PORTER | E37: -433.02
A38: TOPUP | B38: Current | C38: 44626.071 | D38: A33: 1 SUDAPA CARA D1 (AMIGO JAIME) | E38: 32
A39: TOPUP | B39: Current | C39: 44626.071 | D39: A33: 2 CAMI TIRO M Y L, 2 CAMI PIVA M (JAIME Y AMIGO) | E39: 100.02
A40: CARD_PAYMENT | B40: Current | C40: 44630.828 | D40: COMPRA MOOJI MOOJI | E40: -423.53
A41: TRANSFER | B41: Current | C41: 44658.211 | D41: TASAS MOOJI MOOJI (PAGADO POR MAMA) | E41: -109.14
A42: TOPUP | B42: Current | C42: 44658.724 | D42: A33: SUDAPA OJOS L (IÑIGO) | E42: 40.67
A43: TOPUP | B43: Current | C43: 44677.237 | D43: A33: CAMI TIRO M (NICO) | E43: 25
A44: EXCHANGE | B44: Current | C44: 44688.992 | D44: DEVOLUCION RUE PORTER | E44: 455.17
A45: CARD_PAYMENT | B45: Current | C45: 44690.781 | D45: COMPRA WORDANS PRUEBA | E45: -9.84
A46: CARD_PAYMENT | B46: Current | C46: 44699.84 | D46: COMPRA WORDANS | E46: -108.16
... A62: TOPUP | B62: Current | C62: 44783.285 | D62: A33: 1 MANOS L (BRUNO) | E62: 19
A63: TOPUP | B63: Current | C63: 44783.285 | D63: A33: CAMI MARRON L , CAMI TIRO M (CASAPE, SANZ = DEUDA JACO) | E63: =75-19 -> 56
A64: TRANSFER | B64: Current | C64: 44819.083 | D64: COMPRA RUE PORTER | E64: -405.11
A65: TRANSFER | B65: Current | C65: 44842.782 | D65: TASAS RUE PORTER | E65: -173.3
A66: TRANSFER | B66: Current | C66: 44848.097 | D66: SERIGRAFIA | E66: -29.04
A67: CARD_PAYMENT | B67: Current | C67: 44848.89 | D67: COMPRA CAMISETAS FUTBOL | E67: -387
A68: TOPUP | B68: Current | C68: 44863.065 | D68: A33: MOOJI L (CARMEN) | E68: 69
A69: TOPUP | B69: Current | C69: 44868.085 | D69: A33: FUTBOL XL (PETER) | E69: =36 -> 36
A70: TOPUP | B70: Current | C70: 44868.085 | D70: A33: 1 BALACLAVA L Y SKULL L (PETER) | E70: =35*2 -> 70
A71: TOPUP | B71: Current | C71: 44868.092 | D71: A33: 1 BALACLAVA L (JP) | E71: 35.34
A72: TOPUP | B72: Current | C72: 44868.735 | D72: A33: 2 BALACLAVA M (PUPI, LUIS CAN) SKULL XL (SESE) | E72: 105
A73: TOPUP | B73: Current | C73: 44870.278 | D73: A33: 2 BALACLAVA L (Muñoz) | E73: 35
A74: TOPUP | B74: Current | C74: 44871.174 | D74: A33: 1 BALACLAVA M (Dominguez), 2 SKULL ML (N.Per y N.Ben) | E74: 105
A75: TOPUP | B75: Current | C75: 44871.175 | D75: A33: 1 BALACLAVA L (C.Chorvo), 2 SKULL ML (C.chorv y cuervo) | E75: 105
A76: TRANSFER | B76: Current | C76: 44871.284 | D76: SERIGRAFIA | E76: -212.71
A77: CARD_PAYMENT | B77: Current | C77: 44872.176 | D77: COMPRA PRUEBA STUDIOS TC | E77: -89.68
A78: TOPUP | B78: Current | C78: 44875.727 | D78: A33: 1 BALACLAVA M (Nistal), 2 SKULL ML (Juanto, Barallobre) | E78: 105
A79: TOPUP | B79: Current | C79: 44876.766 | D79: A33: 1 BALACLAVA M (GABRIEL) | E79: 35
A80: CARD_PAYMENT | B80: Current | C80: 44887.169 | D80: DEVOLUCION A STUDIOS TC | E80: -17.64
A81: TOPUP | B81: Current | C81: 44887.212 | D81: A33: 1 BALACLAVA M (nathan) | E81: 35
A82: CARD_REFUND | B82: Current | C82: 44898.375 | D82: REEMBOLSO DE STUDIOS TC | E82: 89.68
... A88: TOPUP | B88: Current | C88: 44994.157 | D88: A33: REVOLUTION M (BRUNO) | E88: 63
A89: TOPUP | B89: Current | C89: 44994.157 | D89: A33: 1 BALACLAVA M (BRUNO) | E89: =98-63 -> 35
A90: CARD_PAYMENT | B90: Current | C90: 45034.161 | D90: COMPRA WEEKDAY | E90: -108
A91: TOPUP | B91: Current | C91: 45034.738 | D91: A33: CREW N L (CASAPE), CAMI XL (JAIME RAMIEZ) | E91: 78
A92: CARD_PAYMENT | B92: Current | C92: 45035.637 | D92: COMPRA VELOUR GARMETS | E92: -634.99
A93: CARD_PAYMENT | B93: Current | C93: 45035.702 | D93: COMPRA STUDIOS TC | E93: -357.25
A94: TOPUP | B94: Current | C94: 45041.09 | D94: A33: 1 BALACLAVA L (BARALLOBRE) | E94: 25
A95: TOPUP | B95: Current | C95: 45043.264 | D95: A33: 2 REVOLUTION M Y L (JORDI Y PETER) | E95: 123
A96: TOPUP | B96: Current | C96: 45043.269 | D96: A33: CREW N M, CAMI L (PETER) | E96: 78
A97: TOPUP | B97: Current | C97: 45043.27 | D97: A33: CREW M L (LAURA), CREW N M (IAGO) | E97: 88
A98: TRANSFER | B98: Current | C98: 45043.659 | D98: SERIGRAFIA | E98: -217.8
A99: TOPUP | B99: Current | C99: 45063.18 | D99: A33: 1 FUTBOL L (SAMUEL) | E99: 30
A100: TOPUP | B100: Current | C100: 45066.87 | D100: A33: 2 CREW N M (nico y juli), CAMI ML (Nico y weister) | E100: 154
A101: TOPUP | B101: Current | C101: 45067.205 | D101: A33: 4 CAMI 3L 1M (FELIX, TITO, CASADO Y FORMAS) | E101: 136
... A106: TOPUP | B106: Current | C106: 45101.156 | D106: A33: 1 FUTBOL L (VICTOR) | E106: 33
A107: TOPUP | B107: Current | C107: 45101.156 | D107: A33: SUDAPA N M (luisan) | E107: =77-33 -> 44
A108: TOPUP | B108: Current | C108: 45105.731 | D108: A33: CAMI L (JUANMA) | E108: =63-33 -> 30
A109: TOPUP | B109: Current | C109: 45105.731 | D109: A33: 1 FUTBOL L (VINTED) | E109: 33
A110: TOPUP | B110: Current | C110: 45133.818 | D110: A33: CAMI M y XL (NACHO.P Y MARQUINA) | E110: 66
A111: TOPUP | B111: Current | C111: 45240.911 | D111: A33: CAMI M y sudapa M (CHORVO) | E111: 78
A112: TOPUP | B112: Current | C112: 45244.929 | D112: A33: CAMI L (BARALLOBRE) | E112: 33
A113: TOPUP | B113: Current | C113: 45251 | D113: A33: FUTBOL XL (VINTED) | E113: 26
A114: CARD_PAYMENT | B114: Current | C114: 45260 | D114: COMPRA STUDIOS TC | E114: -713.58
A115: TOPUP | B115: Current | C115: 45260 | D115: A33: SUDAPA L M (RITXI) | E115: 44
A116: TRANSFER | B116: Current | C116: 45323 | D116: SERIGRAFIA | E116: -228.69
A117: TOPUP | B117: Current | C117: 45349 | D117: A33: 1 FUTBOL XL (JAIME BUSTAMANTE) | E117: 33
A118: TOPUP | B118: Current | C118: 45349 | D118: A33: CAMI XL y sudapa NEGRA XL (JAIME BUSTAMANTE) | E118: 78
A119: TOPUP | B119: Current | C119: 45372 | D119: A33: GRAF L Y BRAILE L (DOMINGUEZ) | E119: 66
E120: =SUM(E4:E119) -> 408

Sheet DROP 1
B2: DROP 1 | P2: INGRESOS FINALES | Q2: PRECIO | R2: M | S2: L | T2: UNIDADES | U2: TOTAL | Y2: INGRESOS | Z2: PRECIO | AA2: M | AB2: L | AC2: UNIDADES | AD2: TOTAL
P3: =$P$27 -> MIRILLA | Q3: =Z3 -> 55 | R3: =AA3-AA12 -> 7 | S3: =AB3-AB12 -> 2 | T3: =SUM(R3:S3) -> 9 | U3: =IFERROR(Q3*T3,"-") -> 495 | Y3: =$P$27 -> MIRILLA | Z3: =Z35 -> 55 | AA3: =R27 -> 8 | AB3: =S27 -> 2 | AC3: =SUM(AA3:AB3) -> 10 | AD3: =IFERROR(Z3*AC3,"-") -> 550
P4: =$P$28 -> CARA | Q4: =Z4 -> 55 | R4: =AA4-AA13 -> 5 | S4: =AB4-AB13 -> 0 | T4: =SUM(R4:S4) -> 5 | U4: =IFERROR(Q4*T4,"-") -> 275 | Y4: =$P$28 -> CARA | Z4: =Z36 -> 55 | AA4: =R28 -> 6 | AB4: =S28 -> 0 | AC4: =SUM(AA4:AB4) -> 6 | AD4: =IFERROR(Z4*AC4,"-") -> 330
C5: PPTO | D5: REAL | P5: =$P$29 -> AIRLINE | Q5: =Z5 -> 30 | R5: =AA5-AA14 -> 6 | S5: =AB5-AB14 -> 0 | T5: =SUM(R5:S5) -> 6 | U5: =IFERROR(Q5*T5,"-") -> 180 | Y5: =$P$29 -> AIRLINE | Z5: =Z37 -> 30 | AA5: =R29 -> 8 | AB5: =S29 -> 0 | AC5: =SUM(AA5:AB5) -> 8 | AD5: =IFERROR(Z5*AC5,"-") -> 240
B6: INGRESOS | C6: =U9 -> 1130 | D6: =SUM(L27:$L$61) -> 1049 | P6: =$P$30 -> MADRID | Q6: =Z6 -> 30 | R6: =AA6-AA15 -> 6 | S6: =AB6-AB15 -> 0 | T6: =SUM(R6:S6) -> 6 | U6: =IFERROR(Q6*T6,"-") -> 180 | Y6: =$P$30 -> MADRID | Z6: =Z38 -> 30 | AA6: =R30 -> 8 | AB6: =S30 -> 0 | AC6: =SUM(AA6:AB6) -> 8 | AD6: =IFERROR(Z6*AC6,"-") -> 240
B7: Otros ingresos | C7: 0 | R7: =AA7-AA16 -> 0 | S7: =AB7-AB16 -> 0 | T7: =SUM(R7:S7) -> 0 | U7: =IFERROR(Q7*T7,"-") -> 0 | AA7: =R31 -> 0 | AB7: =S31 -> 0 | AC7: =SUM(AA7:AB7) -> 0 | AD7: =IFERROR(Z7*AC7,"-") -> 0
B8: TOTAL INGRESOS | C8: =SUM(C6:C7) -> 1130 | D8: =SUM(D6:D7) -> 1049 | R8: =AA8-AA17 -> 0 | S8: =AB8-AB17 -> 0 | T8: =SUM(R8:S8) -> 0 | U8: =IFERROR(Q8*T8,"-") -> 0 | AA8: =R32 -> 0 | AB8: =S32 -> 0 | AC8: =SUM(AA8:AB8) -> 0 | AD8: =IFERROR(Z8*AC8,"-") -> 0
B9: Gasto Blanks 1 | C9: =$W$52 -> -655.48 | D9: =C9 -> -655.48 | P9: INGRESOS TOTALES FINALES | T9: =SUM(T3:T8) -> 26 | U9: =SUM(U3:U8) -> 1130 | Y9: INGRESOS TOTALES | AC9: =SUM(AC3:AC8) -> 32 | AD9: =SUM(AD3:AD8) -> 1360
B10: Gasto Serigrafia | C10: =$U$61 -> -116.16 | D10: =C10 -> -116.16
B11: Etiquetas | C11: =-66.46 -> -66.46 | D11: =C11 -> -66.46 | Y11: GON JACO | Z11: COSTE | AA11: M | AB11: L | AC11: UNIDADES | AD11: TOTAL
B12: Otros gastos | Y12: =$P$27 -> MIRILLA | Z12: =AA35 -> -34.7825 | AA12: 1 | AC12: =SUM(AA12:AB12) -> 1 | AD12: =IFERROR(Z12*AC12,"-") -> -34.7825
Y13: =$P$28 -> CARA | Z13: =AA36 -> -33.0825 | AA13: 1 | AC13: =SUM(AA13:AB13) -> 1 | AD13: =IFERROR(Z13*AC13,"-") -> -33.0825
B14: TOTAL GASTOS | C14: =SUM(C9:C13) -> -838.1 | D14: =SUM(D9:D13) -> -838.1 | Y14: =$P$29 -> AIRLINE | Z14: =AA37 -> -14.0825 | AA14: 2 | AC14: =SUM(AA14:AB14) -> 2 | AD14: =IFERROR(Z14*AC14,"-") -> -28.165
Y15: =$P$30 -> MADRID | Z15: =AA38 -> -14.0825 | AA15: 2 | AC15: =SUM(AA15:AB15) -> 2 | AD15: =IFERROR(Z15*AC15,"-") -> -28.165
AC16: =SUM(AA16:AB16) -> 0 | AD16: =IFERROR(Z16*AC16,"-") -> 0
B17: BENEFICIO | C17: =C8+C14 -> 291.9 | D17: =D8+D14 -> 210.9 | AC17: =SUM(AA17:AB17) -> 0 | AD17: =IFERROR(Z17*AC17,"-") -> 0
Y18: COSTE TOTAL | AC18: =SUM(AC12:AC17) -> 6 | AD18: =SUM(AD12:AD17) -> -124.195
B19: RATIO DE BLANKS | C19: =IFERROR(ABS($C$9/$C$8),"-") -> 0.5800708 | D19: =IFERROR(ABS($D$10/$D$8),"-") -> 0.11073403
B20: COR% | C20: =IFERROR(ABS($C$14/$C$8),"-") -> 0.74168142 | D20: =IFERROR(ABS($D$14/$D$8),"-") -> 0.79895138
C22: =$P$27 -> MIRILLA | E22: =$P$28 -> CARA | G22: =$P$29 -> AIRLINE | I22: =$P$30 -> MADRID
C23: M | D23: L | E23: M | F23: L | G23: M | H23: L | I23: M | J23: L | K23: TOTAL
B24: SOLD | C24: =SUM(C27:C61) -> 7 | D24: =SUM(D27:D61) -> 2 | E24: =SUM(E27:E61) -> 4 | F24: =SUM(F27:F61) -> 0 | G24: =SUM(G27:G61) -> 6 | H24: =SUM(H27:H61) -> 0 | I24: =SUM(I27:I61) -> 6 | J24: =SUM(J27:J61) -> 0 | K24: =SUM(C24:J24) -> 25 | L24: =K24-SUM(K27:K61) -> 0
B25: STOCK | C25: =R3-C24 -> 0 | D25: =S3-D24 -> 0 | E25: =R4-E24 -> 1 | F25: =S4-F24 -> 0 | G25: =R5-G24 -> 0 | H25: =S5-H24 -> 0 | I25: =R6-I24 -> 0 | J25: =S6-J24 -> 0 | K25: =SUM(C25:J25) -> 1
B26: NOMBRE | K26: UNIDADES | L26: INGRESO | M26: FECHA | P26: BLANKS 1 | Q26: UND€ | R26: M | S26: L | T26: UNIDADES | U26: EXTRA | V26: € PER UND | W26: TOTAL | Y26: COSTE POR UND | Z26: BLANKS | AA26: SERIGRAFIA | AB26: EXTRA | AC26: TOTAL
A27: 1 | B27: JAIME MILL | C27: 1 | D27: 0 | E27: 0 | F27: 0 | G27: 1 | H27: 0 | I27: 1 | J27: 0 | K27: =SUM(C27:J27) -> 3 | L27: =IFERROR(((C27+D27)*$Q$3)+((E27+F27)*$Q$4)+((G27+H27)*$Q$5)+((I27+J27)*$Q$6),"-")+5 -> 120 | P27: MIRILLA | Q27: 27.5 | R27: 8 | S27: 2 | T27: =R27+S27 -> 10 | U27: =IFERROR($W$36/$T$33,"-") -> 3.0475 | V27: =IFERROR(Q27+U27,"-") -> 30.5475 | W27: =IFERROR(T27*V27,"-") -> 305.475 | Y27: =$P$27 -> MIRILLA | Z27: =V27 -> 30.5475 | AA27: =T55 -> 4.235 | AC27: =SUM(Z27:AB27) -> 34.7825
A28: 2 | B28: PETER | C28: 1 | E28: 1 | K28: =SUM(C28:J28) -> 2 | L28: =IFERROR(((C28+D28)*$Q$3)+((E28+F28)*$Q$4)+((G28+H28)*$Q$5)+((I28+J28)*$Q$6),"-")-5 -> 105 | P28: CARA | Q28: 25.8 | R28: 6 | T28: =R28+S28 -> 6 | U28: =IFERROR($W$36/$T$33,"-") -> 3.0475 | V28: =IFERROR(Q28+U28,"-") -> 28.8475 | W28: =IFERROR(T28*V28,"-") -> 173.085 | Y28: =$P$28 -> CARA | Z28: =V28 -> 28.8475 | AA28: =T56 -> 4.235 | AC28: =SUM(Z28:AB28) -> 33.0825
A29: 3 | B29: LUIS CANADA | C29: 1 | I29: 1 | K29: =SUM(C29:J29) -> 2 | L29: =IFERROR(((C29+D29)*$Q$3)+((E29+F29)*$Q$4)+((G29+H29)*$Q$5)+((I29+J29)*$Q$6),"-")-5 -> 80 | P29: AIRLINE | Q29: 8.01 | R29: 8 | T29: =R29+S29 -> 8 | U29: =IFERROR($W$36/$T$33,"-") -> 3.0475 | V29: =IFERROR(Q29+U29,"-") -> 11.0575 | W29: =IFERROR(T29*V29,"-") -> 88.46 | Y29: =$P$29 -> AIRLINE | Z29: =V29 -> 11.0575 | AA29: =T57 -> 3.025 | AC29: =SUM(Z29:AB29) -> 14.0825
A30: =A29+1 -> 4 | B30: JAIME BUSTAMANTE | C30: 1 | E30: 1 | G30: 1 | K30: =SUM(C30:J30) -> 3 | L30: =IFERROR(((C30+D30)*$Q$3)+((E30+F30)*$Q$4)+((G30+H30)*$Q$5)+((I30+J30)*$Q$6),"-")-28 -> 112 | P30: MADRID | Q30: 8.01 | R30: 8 | T30: =R30+S30 -> 8 | U30: =IFERROR($W$36/$T$33,"-") -> 3.0475 | V30: =IFERROR(Q30+U30,"-") -> 11.0575 | W30: =IFERROR(T30*V30,"-") -> 88.46 | Y30: =$P$30 -> MADRID | Z30: =V30 -> 11.0575 | AA30: =T58 -> 3.025 | AC30: =SUM(Z30:AB30) -> 14.0825
A31: =A30+1 -> 5 | B31: QUINTANA | D31: 1 | K31: =SUM(C31:J31) -> 1 | L31: =IFERROR(((C31+D31)*$Q$3)+((E31+F31)*$Q$4)+((G31+H31)*$Q$5)+((I31+J31)*$Q$6),"-") -> 55 | T31: =R31+S31 -> 0 | V31: =IFERROR(Q31+U31,"-") -> 0 | W31: =IFERROR(T31*V31,"-") -> 0 | AC31: =SUM(Z31:AB31) -> 0
A32: =A31+1 -> 6 | B32: MUÑOZ | C32: 2 | D32: 1 | G32: 1 | K32: =SUM(C32:J32) -> 4 | L32: =IFERROR(((C32+D32)*$Q$3)+((E32+F32)*$Q$4)+((G32+H32)*$Q$5)+((I32+J32)*$Q$6),"-")+37 -> 232 | T32: =R32+S32 -> 0 | V32: =IFERROR(Q32+U32,"-") -> 0 | W32: =IFERROR(T32*V32,"-") -> 0 | AC32: =SUM(Z32:AB32) -> 0
A33: =A32+1 -> 7 | B33: PUIG AMIGO JACO | I33: 1 | K33: =SUM(C33:J33) -> 1 | L33: =IFERROR(((C33+D33)*$Q$3)+((E33+F33)*$Q$4)+((G33+H33)*$Q$5)+((I33+J33)*$Q$6),"-") -> 30 | P33: TOTAL | T33: =SUM(T27:T32) -> 32 | W33: =SUM(W27:W32) -> 655.48
A34: =A33+1 -> 8 | B34: GA | I34: 1 | K34: =SUM(C34:J34) -> 1 | L34: =IFERROR(((C34+D34)*$Q$3)+((E34+F34)*$Q$4)+((G34+H34)*$Q$5)+((I34+J34)*$Q$6),"-") -> 30 | P34: Envio | W34: 97.52 | Y34: BENEFICIO POR UND | Z34: PRECIO | AA34: COSTE | AB34: BENEFICIO | AC34: MARGEN
A35: =A34+1 -> 9 | B35: NACHO PEREZ | G35: 1 | K35: =SUM(C35:J35) -> 1 | L35: =IFERROR(((C35+D35)*$Q$3)+((E35+F35)*$Q$4)+((G35+H35)*$Q$5)+((I35+J35)*$Q$6),"-") -> 30 | P35: Otros gastos | W35: 0 | Y35: =$P$27 -> MIRILLA | Z35: 55 | AA35: =-AC27 -> -34.7825 | AB35: =SUM(Z35:AA35) -> 20.2175 | AC35: =AB35/Z35 -> 0.36759091
A36: =A35+1 -> 10 | B36: CASAPE | G36: 1 | K36: =SUM(C36:J36) -> 1 | L36: =IFERROR(((C36+D36)*$Q$3)+((E36+F36)*$Q$4)+((G36+H36)*$Q$5)+((I36+J36)*$Q$6),"-") -> 30 | P36: TOTAL EXTRAS | W36: =SUM(W34:W35) -> 97.52 | Y36: =$P$28 -> CARA | Z36: 55 | AA36: =-AC28 -> -33.0825 | AB36: =SUM(Z36:AA36) -> 21.9175 | AC36: =AB36/Z36 -> 0.3985
A37: =A36+1 -> 11 | B37: JUANTO | C37: 1 | K37: =SUM(C37:J37) -> 1 | L37: =IFERROR(((C37+D37)*$Q$3)+((E37+F37)*$Q$4)+((G37+H37)*$Q$5)+((I37+J37)*$Q$6),"-") -> 55 | P37: BLANKS TOTAL | W37: =-W33 -> -655.48 | Y37: =$P$29 -> AIRLINE | Z37: 30 | AA37: =-AC29 -> -14.0825 | AB37: =SUM(Z37:AA37) -> 15.9175 | AC37: =AB37/Z37 -> 0.53058333
A38: =A37+1 -> 12 | B38: DIEGO AMIGO JACO | G38: 1 | K38: =SUM(C38:J38) -> 1 | L38: =IFERROR(((C38+D38)*$Q$3)+((E38+F38)*$Q$4)+((G38+H38)*$Q$5)+((I38+J38)*$Q$6),"-") -> 30 | W38: =Q27*T27+Q28*T28+Q29*T29+Q30*T30+Q31*T31+Q32*T32+W36+W37 -> 0 | Y38: =$P$30 -> MADRID | Z38: 30 | AA38: =-AC30 -> -14.0825 | AB38: =SUM(Z38:AA38) -> 15.9175 | AC38: =AB38/Z38 -> 0.53058333
A39: =A38+1 -> 13 | B39: JAIME X | I39: 1 | K39: =SUM(C39:J39) -> 1 | L39: =IFERROR(((C39+D39)*$Q$3)+((E39+F39)*$Q$4)+((G39+H39)*$Q$5)+((I39+J39)*$Q$6),"-") -> 30 | P39: BLANKS 2 | Q39: UND€ | R39: M | S39: L | T39: UNIDADES | U39: EXTRA | V39: € PER UND | W39: TOTAL
A40: =A39+1 -> 14 | B40: AMIGO ANGEL | I40: 1 | K40: =SUM(C40:J40) -> 1 | L40: =IFERROR(((C40+D40)*$Q$3)+((E40+F40)*$Q$4)+((G40+H40)*$Q$5)+((I40+J40)*$Q$6),"-") -> 30 | T40: =SUM(R40:S40) -> 0 | U40: =IFERROR($W$49/$T$46,"-") -> - | V40: =IFERROR(Q40+U40,"-") -> - | W40: =IFERROR(T40*V40,"-") -> -
A41: =A40+1 -> 15 | B41: GENOVEVA | E41: 1 | K41: =SUM(C41:J41) -> 1 | L41: =IFERROR(((C41+D41)*$Q$3)+((E41+F41)*$Q$4)+((G41+H41)*$Q$5)+((I41+J41)*$Q$6),"-")-15 -> 40 | T41: =SUM(R41:S41) -> 0 | U41: =IFERROR($W$49/$T$46,"-") -> - | V41: =IFERROR(Q41+U41,"-") -> - | W41: =IFERROR(T41*V41,"-") -> -
A42: =A41+1 -> 16 | B42: CANDELA | E42: 1 | K42: =SUM(C42:J42) -> 1 | L42: =IFERROR(((C42+D42)*$Q$3)+((E42+F42)*$Q$4)+((G42+H42)*$Q$5)+((I42+J42)*$Q$6),"-")-15 -> 40 | T42: =SUM(R42:S42) -> 0 | U42: =IFERROR($W$49/$T$46,"-") -> - | V42: =IFERROR(Q42+U42,"-") -> - | W42: =IFERROR(T42*V42,"-") -> -
A43: =A42+1 -> 17 | K43: =SUM(C43:J43) -> 0 | L43: =IFERROR(((C43+D43)*$Q$3)+((E43+F43)*$Q$4)+((G43+H43)*$Q$5)+((I43+J43)*$Q$6),"-") -> 0 | T43: =SUM(R43:S43) -> 0 | U43: =IFERROR($W$49/$T$46,"-") -> - | V43: =IFERROR(Q43+U43,"-") -> - | W43: =IFERROR(T43*V43,"-") -> -
A44: =A43+1 -> 18 | K44: =SUM(C44:J44) -> 0 | L44: =IFERROR(((C44+D44)*$Q$3)+((E44+F44)*$Q$4)+((G44+H44)*$Q$5)+((I44+J44)*$Q$6),"-") -> 0 | T44: =SUM(R44:S44) -> 0 | V44: =IFERROR(Q44+U44,"-") -> 0 | W44: =IFERROR(T44*V44,"-") -> 0
A45: =A44+1 -> 19 | K45: =SUM(C45:J45) -> 0 | L45: =IFERROR(((C45+D45)*$Q$3)+((E45+F45)*$Q$4)+((G45+H45)*$Q$5)+((I45+J45)*$Q$6),"-") -> 0 | T45: =SUM(R45:S45) -> 0 | V45: =IFERROR(Q45+U45,"-") -> 0 | W45: =IFERROR(T45*V45,"-") -> 0
A46: =A45+1 -> 20 | K46: =SUM(C46:J46) -> 0 | L46: =IFERROR(((C46+D46)*$Q$3)+((E46+F46)*$Q$4)+((G46+H46)*$Q$5)+((I46+J46)*$Q$6),"-") -> 0 | P46: TOTAL | T46: =SUM(T40:T45) -> 0 | W46: =SUM(W40:W45) -> 0
A47: =A46+1 -> 21 | K47: =SUM(C47:J47) -> 0 | L47: =IFERROR(((C47+D47)*$Q$3)+((E47+F47)*$Q$4)+((G47+H47)*$Q$5)+((I47+J47)*$Q$6),"-") -> 0 | P47: Envio
A48: =A47+1 -> 22 | K48: =SUM(C48:J48) -> 0 | L48: =IFERROR(((C48+D48)*$Q$3)+((E48+F48)*$Q$4)+((G48+H48)*$Q$5)+((I48+J48)*$Q$6),"-") -> 0 | P48: Otros gastos
A49: =A48+1 -> 23 | K49: =SUM(C49:J49) -> 0 | L49: =IFERROR(((C49+D49)*$Q$3)+((E49+F49)*$Q$4)+((G49+H49)*$Q$5)+((I49+J49)*$Q$6),"-") -> 0 | P49: TOTAL EXTRAS | W49: =SUM(W47:W48) -> 0
A50: =A49+1 -> 24 | K50: =SUM(C50:J50) -> 0 | L50: =IFERROR(((C50+D50)*$Q$3)+((E50+F50)*$Q$4)+((G50+H50)*$Q$5)+((I50+J50)*$Q$6),"-") -> 0 | P50: BLANKS TOTAL | W50: =-W46 -> 0
A51: =A50+1 -> 25 | K51: =SUM(C51:J51) -> 0 | L51: =IFERROR(((C51+D51)*$Q$3)+((E51+F51)*$Q$4)+((G51+H51)*$Q$5)+((I51+J51)*$Q$6),"-") -> 0 | W51: =Q40*T40+Q41*T41+Q42*T42+Q43*T43+Q44*T44+Q45*T45+W49+W50 -> 0
A52: =A51+1 -> 26 | K52: =SUM(C52:J52) -> 0 | L52: =IFERROR(((C52+D52)*$Q$3)+((E52+F52)*$Q$4)+((G52+H52)*$Q$5)+((I52+J52)*$Q$6),"-") -> 0 | P52: COSTE TOTAL BLANKS | W52: =W37+W50 -> -655.48
A53: =A52+1 -> 27 | K53: =SUM(C53:J53) -> 0 | L53: =IFERROR(((C53+D53)*$Q$3)+((E53+F53)*$Q$4)+((G53+H53)*$Q$5)+((I53+J53)*$Q$6),"-") -> 0
A54: =A53+1 -> 28 | K54: =SUM(C54:J54) -> 0 | L54: =IFERROR(((C54+D54)*$Q$3)+((E54+F54)*$Q$4)+((G54+H54)*$Q$5)+((I54+J54)*$Q$6),"-") -> 0 | P54: SERIGRAFIA | Q54: €/UND | R54: UNIDADES | S54: IVA | T54: € PER UND | U54: TOTAL
A55: =A54+1 -> 29 | K55: =SUM(C55:J55) -> 0 | L55: =IFERROR(((C55+D55)*$Q$3)+((E55+F55)*$Q$4)+((G55+H55)*$Q$5)+((I55+J55)*$Q$6),"-") -> 0 | P55: =$P$27 -> MIRILLA | Q55: 3.5 | R55: =T27 -> 10 | S55: =IFERROR(((Q55*R55)*0.21)/R55,"-") -> 0.735 | T55: =IFERROR(Q55+S55,"-") -> 4.235 | U55: =IFERROR(R55*T55,"-") -> 42.35
A56: =A55+1 -> 30 | K56: =SUM(C56:J56) -> 0 | L56: =IFERROR(((C56+D56)*$Q$3)+((E56+F56)*$Q$4)+((G56+H56)*$Q$5)+((I56+J56)*$Q$6),"-") -> 0 | P56: =$P$28 -> CARA | Q56: 3.5 | R56: =T28 -> 6 | S56: =IFERROR(((Q56*R56)*0.21)/R56,"-") -> 0.735 | T56: =IFERROR(Q56+S56,"-") -> 4.235 | U56: =IFERROR(R56*T56,"-") -> 25.41
A57: =A56+1 -> 31 | K57: =SUM(C57:J57) -> 0 | L57: =IFERROR(((C57+D57)*$Q$3)+((E57+F57)*$Q$4)+((G57+H57)*$Q$5)+((I57+J57)*$Q$6),"-") -> 0 | P57: =$P$29 -> AIRLINE | Q57: 2.5 | R57: =T29 -> 8 | S57: =IFERROR(((Q57*R57)*0.21)/R57,"-") -> 0.525 | T57: =IFERROR(Q57+S57,"-") -> 3.025 | U57: =IFERROR(R57*T57,"-") -> 24.2
A58: =A57+1 -> 32 | K58: =SUM(C58:J58) -> 0 | L58: =IFERROR(((C58+D58)*$Q$3)+((E58+F58)*$Q$4)+((G58+H58)*$Q$5)+((I58+J58)*$Q$6),"-") -> 0 | P58: =$P$30 -> MADRID | Q58: 2.5 | R58: =T30 -> 8 | S58: =IFERROR(((Q58*R58)*0.21)/R58,"-") -> 0.525 | T58: =IFERROR(Q58+S58,"-") -> 3.025 | U58: =IFERROR(R58*T58,"-") -> 24.2
A59: =A58+1 -> 33 | K59: =SUM(C59:J59) -> 0 | L59: =IFERROR(((C59+D59)*$Q$3)+((E59+F59)*$Q$4)+((G59+H59)*$Q$5)+((I59+J59)*$Q$6),"-") -> 0 | S59: =IFERROR(((Q59*R59)*0.21)/R59,"-") -> - | T59: =IFERROR(Q59+S59,"-") -> - | U59: =IFERROR(R59*T59,"-") -> -
A60: =A59+1 -> 34 | K60: =SUM(C60:J60) -> 0 | L60: =IFERROR(((C60+D60)*$Q$3)+((E60+F60)*$Q$4)+((G60+H60)*$Q$5)+((I60+J60)*$Q$6),"-") -> 0 | S60: =IFERROR(((Q60*R60)*0.21)/R60,"-") -> - | T60: =IFERROR(Q60+S60,"-") -> - | U60: =IFERROR(R60*T60,"-") -> -
A61: =A60+1 -> 35 | K61: =SUM(C61:J61) -> 0 | L61: =IFERROR(((C61+D61)*$Q$3)+((E61+F61)*$Q$4)+((G61+H61)*$Q$5)+((I61+J61)*$Q$6),"-") -> 0 | P61: SERIGRAFIA TOTAL | R61: =SUM(R55:R60) -> 32 | U61: =-SUM(U55:U60) -> -116.16
A65: 1 | B65: =B27 -> JAIME MILL | C65: =_xlfn.TEXTJOIN(", ",TRUE, IF(OR(C27>0,E27>0,G27>0,I27>0),"M",""), IF(OR(D27>0,F27>0,H27>0,J27>0),"L","") ) -> M | D65: =IF(C65="M",1,IF(C65="L",2,IF(C65="M, L",3))) -> 1 | E65: =K27 -> 3 | F65: =L27 -> 120 | G65: =$B$2 -> DROP 1
A66: 2 | B66: =B28 -> PETER | C66: =_xlfn.TEXTJOIN(", ",TRUE, IF(OR(C28>0,E28>0,G28>0,I28>0),"M",""), IF(OR(D28>0,F28>0,H28>0,J28>0),"L","") ) -> M | D66: =IF(C66="M",1,IF(C66="L",2,IF(C66="M, L",3))) -> 1 | E66: =K28 -> 2 | F66: =L28 -> 105 | G66: =$B$2 -> DROP 1
A67: 3 | B67: =B29 -> LUIS CANADA | C67: =_xlfn.TEXTJOIN(", ",TRUE, IF(OR(C29>0,E29>0,G29>0,I29>0),"M",""), IF(OR(D29>0,F29>0,H29>0,J29>0),"L","") ) -> M | D67: =IF(C67="M",1,IF(C67="L",2,IF(C67="M, L",3))) -> 1 | E67: =K29 -> 2 | F67: =L29 -> 80 | G67: =$B$2 -> DROP 1
A68: =A67+1 -> 4 | B68: =B30 -> JAIME BUSTAMANTE | C68: =_xlfn.TEXTJOIN(", ",TRUE, IF(OR(C30>0,E30>0,G30>0,I30>0),"M",""), IF(OR(D30>0,F30>0,H30>0,J30>0),"L","") ) -> M | D68: =IF(C68="M",1,IF(C68="L",2,IF(C68="M, L",3))) -> 1 | E68: =K30 -> 3 | F68: =L30 -> 112 | G68: =$B$2 -> DROP 1
A69: =A68+1 -> 5 | B69: =B31 -> QUINTANA | C69: =_xlfn.TEXTJOIN(", ",TRUE, IF(OR(C31>0,E31>0,G31>0,I31>0),"M",""), IF(OR(D31>0,F31>0,H31>0,J31>0),"L","") ) -> L | D69: =IF(C69="M",1,IF(C69="L",2,IF(C69="M, L",3))) -> 2 | E69: =K31 -> 1 | F69: =L31 -> 55 | G69: =$B$2 -> DROP 1
A70: =A69+1 -> 6 | B70: =B32 -> MUÑOZ | C70: L | D70: =IF(C70="M",1,IF(C70="L",2,IF(C70="M, L",3))) -> 2 | E70: =K32 -> 4 | F70: =L32 -> 232 | G70: =$B$2 -> DROP 1
A71: =A70+1 -> 7 | B71: =B33 -> PUIG AMIGO JACO | C71: =_xlfn.TEXTJOIN(", ",TRUE, IF(OR(C33>0,E33>0,G33>0,I33>0),"M",""), IF(OR(D33>0,F33>0,H33>0,J33>0),"L","") ) -> M | D71: =IF(C71="M",1,IF(C71="L",2,IF(C71="M, L",3))) -> 1 | E71: =K33 -> 1 | F71: =L33 -> 30 | G71: =$B$2 -> DROP 1
A72: =A71+1 -> 8 | B72: =B34 -> GA | C72: =_xlfn.TEXTJOIN(", ",TRUE, IF(OR(C34>0,E34>0,G34>0,I34>0),"M",""), IF(OR(D34>0,F34>0,H34>0,J34>0),"L","") ) -> M | D72: =IF(C72="M",1,IF(C72="L",2,IF(C72="M, L",3))) -> 1 | E72: =K34 -> 1 | F72: =L34 -> 30 | G72: =$B$2 -> DROP 1
A73: =A72+1 -> 9 | B73: =B35 -> NACHO PEREZ | C73: =_xlfn.TEXTJOIN(", ",TRUE, IF(OR(C35>0,E35>0,G35>0,I35>0),"M",""), IF(OR(D35>0,F35>0,H35>0,J35>0),"L","") ) -> M | D73: =IF(C73="M",1,IF(C73="L",2,IF(C73="M, L",3))) -> 1 | E73: =K35 -> 1 | F73: =L35 -> 30 | G73: =$B$2 -> DROP 1
A74: =A73+1 -> 10 | B74: =B36 -> CASAPE | C74: =_xlfn.TEXTJOIN(", ",TRUE, IF(OR(C36>0,E36>0,G36>0,I36>0),"M",""), IF(OR(D36>0,F36>0,H36>0,J36>0),"L","") ) -> M | D74: =IF(C74="M",1,IF(C74="L",2,IF(C74="M, L",3))) -> 1 | E74: =K36 -> 1 | F74: =L36 -> 30 | G74: =$B$2 -> DROP 1
A75: =A74+1 -> 11 | B75: =B37 -> JUANTO | C75: =_xlfn.TEXTJOIN(", ",TRUE, IF(OR(C37>0,E37>0,G37>0,I37>0),"M",""), IF(OR(D37>0,F37>0,H37>0,J37>0),"L","") ) -> M | D75: =IF(C75="M",1,IF(C75="L",2,IF(C75="M, L",3))) -> 1 | E75: =K37 -> 1 | F75: =L37 -> 55 | G75: =$B$2 -> DROP 1
A76: =A75+1 -> 12 | B76: =B38 -> DIEGO AMIGO JACO | C76: =_xlfn.TEXTJOIN(", ",TRUE, IF(OR(C38>0,E38>0,G38>0,I38>0),"M",""), IF(OR(D38>0,F38>0,H38>0,J38>0),"L","") ) -> M | D76: =IF(C76="M",1,IF(C76="L",2,IF(C76="M, L",3))) -> 1 | E76: =K38 -> 1 | F76: =L38 -> 30 | G76: =$B$2 -> DROP 1
A77: =A76+1 -> 13 | B77: =B39 -> JAIME X | C77: =_xlfn.TEXTJOIN(", ",TRUE, IF(OR(C39>0,E39>0,G39>0,I39>0),"M",""), IF(OR(D39>0,F39>0,H39>0,J39>0),"L","") ) -> M | D77: =IF(C77="M",1,IF(C77="L",2,IF(C77="M, L",3))) -> 1 | E77: =K39 -> 1 | F77: =L39 -> 30 | G77: =$B$2 -> DROP 1
A78: =A77+1 -> 14 | B78: =B40 -> AMIGO ANGEL | C78: =_xlfn.TEXTJOIN(", ",TRUE, IF(OR(C40>0,E40>0,G40>0,I40>0),"M",""), IF(OR(D40>0,F40>0,H40>0,J40>0),"L","") ) -> M | D78: =IF(C78="M",1,IF(C78="L",2,IF(C78="M, L",3))) -> 1 | E78: =K40 -> 1 | F78: =L40 -> 30 | G78: =$B$2 -> DROP 1
A79: =A78+1 -> 15 | B79: =B41 -> GENOVEVA | C79: =_xlfn.TEXTJOIN(", ",TRUE, IF(OR(C41>0,E41>0,G41>0,I41>0),"M",""), IF(OR(D41>0,F41>0,H41>0,J41>0),"L","") ) -> M | D79: =IF(C79="M",1,IF(C79="L",2,IF(C79="M, L",3))) -> 1 | E79: =K41 -> 1 | F79: =L41 -> 40 | G79: =$B$2 -> DROP 1
A80: =A79+1 -> 16 | B80: =B42 -> CANDELA | C80: =_xlfn.TEXTJOIN(", ",TRUE, IF(OR(C42>0,E42>0,G42>0,I42>0),"M",""), IF(OR(D42>0,F42>0,H42>0,J42>0),"L","") ) -> M | D80: =IF(C80="M",1,IF(C80="L",2,IF(C80="M, L",3))) -> 1 | E80: =K42 -> 1 | F80: =L42 -> 40 | G80: =$B$2 -> DROP 1
A81: =A80+1 -> 17 | B81: =B43 -> 0 | C81: =_xlfn.TEXTJOIN(", ",TRUE, IF(OR(C43>0,E43>0,G43>0,I43>0),"M",""), IF(OR(D43>0,F43>0,H43>0,J43>0),"L","") ) | D81: =IF(C81="M",1,IF(C81="L",2,IF(C81="M, L",3))) -> FALSE | E81: =K43 -> 0 | F81: =L43 -> 0
A82: =A81+1 -> 18 | B82: =B44 -> 0 | C82: =_xlfn.TEXTJOIN(", ",TRUE, IF(OR(C44>0,E44>0,G44>0,I44>0),"M",""), IF(OR(D44>0,F44>0,H44>0,J44>0),"L","") ) | D82: =IF(C82="M",1,IF(C82="L",2,IF(C82="M, L",3))) -> FALSE | E82: =K44 -> 0 | F82: =L44 -> 0
A83: =A82+1 -> 19 | B83: =B45 -> 0 | C83: =_xlfn.TEXTJOIN(", ",TRUE, IF(OR(C45>0,E45>0,G45>0,I45>0),"M",""), IF(OR(D45>0,F45>0,H45>0,J45>0),"L","") ) | D83: =IF(C83="M",1,IF(C83="L",2,IF(C83="M, L",3))) -> FALSE | E83: =K45 -> 0 | F83: =L45 -> 0
A84: =A83+1 -> 20 | B84: =B46 -> 0 | C84: =_xlfn.TEXTJOIN(", ",TRUE, IF(OR(C46>0,E46>0,G46>0,I46>0),"M",""), IF(OR(D46>0,F46>0,H46>0,J46>0),"L","") ) | D84: =IF(C84="M",1,IF(C84="L",2,IF(C84="M, L",3))) -> FALSE | E84: =K46 -> 0 | F84: =L46 -> 0
A85: =A84+1 -> 21 | B85: =B47 -> 0 | C85: =_xlfn.TEXTJOIN(", ",TRUE, IF(OR(C47>0,E47>0,G47>0,I47>0),"M",""), IF(OR(D47>0,F47>0,H47>0,J47>0),"L","") ) | D85: =IF(C85="M",1,IF(C85="L",2,IF(C85="M, L",3))) -> FALSE | E85: =K47 -> 0 | F85: =L47 -> 0
A86: =A85+1 -> 22 | B86: =B48 -> 0 | C86: =_xlfn.TEXTJOIN(", ",TRUE, IF(OR(C48>0,E48>0,G48>0,I48>0),"M",""), IF(OR(D48>0,F48>0,H48>0,J48>0),"L","") ) | D86: =IF(C86="M",1,IF(C86="L",2,IF(C86="M, L",3))) -> FALSE | E86: =K48 -> 0 | F86: =L48 -> 0
A87: =A86+1 -> 23 | B87: =B49 -> 0 | C87: =_xlfn.TEXTJOIN(", ",TRUE, IF(OR(C49>0,E49>0,G49>0,I49>0),"M",""), IF(OR(D49>0,F49>0,H49>0,J49>0),"L","") ) | D87: =IF(C87="M",1,IF(C87="L",2,IF(C87="M, L",3))) -> FALSE | E87: =K49 -> 0 | F87: =L49 -> 0
A88: =A87+1 -> 24 | B88: =B50 -> 0 | C88: =_xlfn.TEXTJOIN(", ",TRUE, IF(OR(C50>0,E50>0,G50>0,I50>0),"M",""), IF(OR(D50>0,F50>0,H50>0,J50>0),"L","") ) | D88: =IF(C88="M",1,IF(C88="L",2,IF(C88="M, L",3))) -> FALSE | E88: =K50 -> 0 | F88: =L50 -> 0
A89: =A88+1 -> 25 | B89: =B51 -> 0 | C89: =_xlfn.TEXTJOIN(", ",TRUE, IF(OR(C51>0,E51>0,G51>0,I51>0),"M",""), IF(OR(D51>0,F51>0,H51>0,J51>0),"L","") ) | D89: =IF(C89="M",1,IF(C89="L",2,IF(C89="M, L",3))) -> FALSE | E89: =K51 -> 0 | F89: =L51 -> 0
A90: =A89+1 -> 26 | B90: =B52 -> 0 | C90: =_xlfn.TEXTJOIN(", ",TRUE, IF(OR(C52>0,E52>0,G52>0,I52>0),"M",""), IF(OR(D52>0,F52>0,H52>0,J52>0),"L","") ) | D90: =IF(C90="M",1,IF(C90="L",2,IF(C90="M, L",3))) -> FALSE | E90: =K52 -> 0 | F90: =L52 -> 0
A91: =A90+1 -> 27 | B91: =B53 -> 0 | C91: =_xlfn.TEXTJOIN(", ",TRUE, IF(OR(C53>0,E53>0,G53>0,I53>0),"M",""), IF(OR(D53>0,F53>0,H53>0,J53>0),"L","") ) | D91: =IF(C91="M",1,IF(C91="L",2,IF(C91="M, L",3))) -> FALSE | E91: =K53 -> 0 | F91: =L53 -> 0
A92: =A91+1 -> 28 | B92: =B54 -> 0 | C92: =_xlfn.TEXTJOIN(", ",TRUE, IF(OR(C54>0,E54>0,G54>0,I54>0),"M",""), IF(OR(D54>0,F54>0,H54>0,J54>0),"L","") ) | D92: =IF(C92="M",1,IF(C92="L",2,IF(C92="M, L",3))) -> FALSE | E92: =K54 -> 0 | F92: =L54 -> 0
... A99: =A98+1 -> 35 | B99: =B61 -> 0 | C99: =_xlfn.TEXTJOIN(", ",TRUE, IF(OR(C61>0,E61>0,G61>0,I61>0),"M",""), IF(OR(D61>0,F61>0,H61>0,J61>0),"L","") ) | D99: =IF(C99="M",1,IF(C99="L",2,IF(C99="M, L",3))) -> FALSE | E99: =K61 -> 0 | F99: =L61 -> 0

Sheet 1
G3: HOODIES | R3: TEES | AC3: CREWNECK | AL3: TOTAL RUE PORTER $ | AO3: TOTAL RUE PORTER € | AR3: ENVIO | AU3: TOTAL | AX3: CANTIDAD | BA3: FECHA | BD3: COBRO | BI3: INGRESOS | BN3: =BF56 -> 1130
G5: PRICE $ | H5: PRICE € | I5: M | J5: L | K5: UNITS | L5: TOTAL $ | M5: TOTAL € | R5: PRICE $ | S5: PRICE € | T5: M | U5: L | V5: UNITS | W5: TOTAL $ | X5: TOTAL € | AC5: PRICE $ | AD5: PRICE € | AE5: M | AF5: L | AG5: UNITS | AH5: TOTAL $ | AI5: TOTAL € | BV5: =BC48 -> 7 | BW5: =BD48 -> 2 | BX5: =BC50 -> 5 | BY5: =BD50 -> 0 | BZ5: =BC52 -> 6 | CA5: =BD52 -> 0 | CB5: =BC54 -> 6 | CC5: =BD54 -> 0 | CD5: =SUM(BV5:CC6) -> 26
AL6: =L37+W37+AH37+L75+W75+AH75 -> 659.2 | AO6: =M37+X37+AI37+M75+X75+AI75 -> 557.96 | AR6: 90 | AU6: =AL6+AR6 -> 749.2 | AX6: =K37+V37+AG37+K75+V75+AG75 -> 32 | BA6: 44281 | BD6: 655.48 | BI6: RUE PORTER | BN6: =BD6 -> 655.48
D7: BLACK | G7: 30.5 | H7: 25.8 | K7: =I7+J7 -> 0 | L7: =G7*K7 -> 0 | M7: =H7*K7 -> 0 | O7: BLACK | R7: 9.45 | S7: 8.01 | V7: =T7+U7 -> 0 | W7: =R7*V7 -> 0 | X7: =S7*V7 -> 0 | Z7: BLACK | AG7: =AE7+AF7 -> 0 | AH7: =AC7*AG7 -> 0 | AI7: =AD7*AG7 -> 0 | BV7: M | BW7: L | BX7: M | BY7: L | BZ7: M | CA7: L | CB7: M | CC7: L | CD7: UNITS | CE7: TOTAL € | CF7: PAYMENT | CI7: CASH | CJ7: CREDIT | CK7: COBRO | CM7: FECHA
BI8: SERIGRAFIA | BN8: =AT24 -> 116.16
D9: VINTAGE BLACK | G9: 32.5 | H9: 27.5 | I9: 8 | J9: 2 | K9: =I9+J9 -> 10 | L9: =G9*K9 -> 325 | M9: =H9*K9 -> 275 | O9: VINTAGE BLACK | R9: 10.85 | S9: 9.2 | V9: =T9+U9 -> 0 | W9: =R9*V9 -> 0 | X9: =S9*V9 -> 0 | Z9: VINTAGE BLACK | AG9: =AE9+AF9 -> 0 | AH9: =AC9*AG9 -> 0 | AI9: =AD9*AG9 -> 0 | BR9: JAIME RICO | BV9: 1 | BW9: 0 | BX9: 0 | BY9: 0 | BZ9: 1 | CA9: 0 | CB9: 1 | CC9: 0 | CD9: =SUM(BV9:CC10) -> 3 | CE9: =BV9*55+BW9*55+BX9*55+BY9*55+BZ9*30+CA9*30+CB9*30+CC9*30 -> 115 | CF9: 120€ EFECTIVO | CI9: 120 | CJ9: 0 | CK9: REVOLUT
BI10: ETIQUETAS | BN10: 66.46
D11: GARMENT DYED | K11: =I11+J11 -> 0 | L11: =G11*K11 -> 0 | M11: =H11*K11 -> 0 | O11: GARMENT DYED | V11: =T11+U11 -> 0 | W11: =R11*V11 -> 0 | X11: =S11*V11 -> 0 | Z11: GARMENT DYED | AG11: =AE11+AF11 -> 0 | AH11: =AC11*AG11 -> 0 | AI11: =AD11*AG11 -> 0 | BR11: PETER | BV11: 1 | BW11: 0 | BX11: 1 | BY11: 0 | BZ11: 0 | CA11: 0 | CB11: 0 | CC11: 0 | CD11: =SUM(BV11:CC12) -> 2 | CE11: =BV11*55+BW11*55+BX11*55+BY11*55+BZ11*30+CA11*30+CB11*30+CC11*30 -> 110 | CF11: 105€ TARJETA | CI11: 0 | CJ11: 105 | CK11: REVOLUT | CN11: 44472
AL12: SERIGRAFIA | BI12: COSTE TOTAL | BN12: =SUM(BN6:BO11) -> 838.1
D13: HEATHER GREY | G13: 30.5 | H13: 25.8 | I13: 6 | K13: =I13+J13 -> 6 | L13: =G13*K13 -> 183 | M13: =H13*K13 -> 154.8 | O13: HEATHER GREY | R13: 9.45 | S13: 8.01 | V13: =T13+U13 -> 0 | W13: =R13*V13 -> 0 | X13: =S13*V13 -> 0 | Z13: HEATHER GREY | AG13: =AE13+AF13 -> 0 | AH13: =AC13*AG13 -> 0 | AI13: =AD13*AG13 -> 0 | BR13: LUIS CANADA | BV13: 1 | BW13: 0 | BX13: 0 | BY13: 0 | BZ13: 0 | CA13: 0 | CB13: 1 | CC13: 0 | CD13: =SUM(BV13:CC14) -> 2 | CE13: =BV13*55+BW13*55+BX13*55+BY13*55+BZ13*30+CA13*30+CB13*30+CC13*30 -> 85 | CF13: 50€ EFECTVO + 30€ TARJETA | CI13: 50 | CJ13: 30 | CK13: REVOLUT
AP14: PRICE € | AQ14: UNITS | AR14: IVA | AS14: PER UNIT | AT14: TOTAL € | BB14: PRICE | BC14: M | BD14: L | BE14: UNITS | BF14: TOTAL €
D15: WHITE | G15: 30.5 | H15: 25.8 | K15: =I15+J15 -> 0 | L15: =G15*K15 -> 0 | M15: =H15*K15 -> 0 | O15: WHITE | R15: 9.45 | S15: 8.01 | T15: 8 | V15: =T15+U15 -> 8 | W15: =R15*V15 -> 75.6 | X15: =S15*V15 -> 64.08 | Z15: WHITE | AG15: =AE15+AF15 -> 0 | AH15: =AC15*AG15 -> 0 | AI15: =AD15*AG15 -> 0 | BI15: TOTAL FINAL | BN15: =BN3-BN12 -> 291.9 | BR15: JAIME BUST | BV15: 1 | BW15: 0 | BX15: 0 | BY15: 0 | BZ15: 1 | CA15: 0 | CB15: 0 | CC15: 0 | CD15: =SUM(BV15:CC16) -> 2 | CE15: =BV15*55+BW15*55+BX15*55+BY15*55+BZ15*30+CA15*30+CB15*30+CC15*30 -> 85 | CF15: 80€ TARJETA | CI15: 0 | CJ15: 80 | CK15: REVOLUT
AM16: MIRILLA | AP16: 3.5 | AQ16: =K9 -> 10 | AR16: =((AP16*AQ16)*0.21)/AQ16 -> 0.735 | AS16: =AP16+AR16 -> 4.235 | AT16: =AQ16*AS16 -> 42.35 | AY16: MIRILLA | BB16: =AP48 -> 55 | BC16: =I9 -> 8 | BD16: =J9 -> 2 | BE16: =BC16+BD16 -> 10 | BF16: =BB16*BE16 -> 550
D17: VINTAGE BROWN | G17: 32.5 | H17: 27.5 | K17: =I17+J17 -> 0 | L17: =G17*K17 -> 0 | M17: =H17*K17 -> 0 | O17: VINTAGE BROWN | R17: 10.85 | S17: 9.2 | V17: =T17+U17 -> 0 | W17: =R17*V17 -> 0 | X17: =S17*V17 -> 0 | Z17: VINTAGE BROWN | AG17: =AE17+AF17 -> 0 | AH17: =AC17*AG17 -> 0 | AI17: =AD17*AG17 -> 0 | BR17: QUINTANA | BV17: 0 | BW17: 1 | BX17: 0 | BY17: 0 | BZ17: 0 | CA17: 0 | CB17: 0 | CC17: 0 | CD17: =SUM(BV17:CC18) -> 1 | CE17: =BV17*55+BW17*55+BX17*55+BY17*55+BZ17*30+CA17*30+CB17*30+CC17*30 -> 55 | CF17: 55€ TARJETA | CI17: 0 | CJ17: 55 | CK17: REVOLUT
AM18: CARA | AP18: 3.5 | AQ18: =K13 -> 6 | AR18: =((AP18*AQ18)*0.21)/AQ18 -> 0.735 | AS18: =AP18+AR18 -> 4.235 | AT18: =AQ18*AS18 -> 25.41 | AY18: CARA | BB18: =AP50 -> 55 | BC18: =I13 -> 6 | BD18: 0 | BE18: =BC18+BD18 -> 6 | BF18: =BB18*BE18 -> 330
D19: CAMEL | K19: =I19+J19 -> 0 | L19: =G19*K19 -> 0 | M19: =H19*K19 -> 0 | O19: CAMEL | V19: =T19+U19 -> 0 | W19: =R19*V19 -> 0 | X19: =S19*V19 -> 0 | Z19: CAMEL | AG19: =AE19+AF19 -> 0 | AH19: =AC19*AG19 -> 0 | AI19: =AD19*AG19 -> 0 | BR19: MUÑOZ | BV19: 2 | BW19: 1 | BX19: 0 | BY19: 0 | BZ19: 1 | CA19: 0 | CB19: 0 | CC19: 0 | CD19: =SUM(BV19:CC20) -> 4 | CE19: =BV19*55+BW19*55+BX19*55+BY19*55+BZ19*30+CA19*30+CB19*30+CC19*30 -> 195 | CF19: 195€ + ENVIO TARJETA | CI19: 0 | CJ19: 232 | CK19: REVOLUT
AM20: AIRLINE | AP20: 2.5 | AQ20: =V15 -> 8 | AR20: =((AP20*AQ20)*0.21)/AQ20 -> 0.525 | AS20: =AP20+AR20 -> 3.025 | AT20: =AQ20*AS20 -> 24.2 | AY20: AIRLINE | BB20: =AP52 -> 30 | BC20: =T15 -> 8 | BD20: 0 | BE20: =BC20+BD20 -> 8 | BF20: =BB20*BE20 -> 240
D21: KHAKI | K21: =I21+J21 -> 0 | L21: =G21*K21 -> 0 | M21: =H21*K21 -> 0 | O21: KHAKI | V21: =T21+U21 -> 0 | W21: =R21*V21 -> 0 | X21: =S21*V21 -> 0 | Z21: KHAKI | AG21: =AE21+AF21 -> 0 | AH21: =AC21*AG21 -> 0 | AI21: =AD21*AG21 -> 0 | BR21: PUIG | BV21: 0 | BW21: 0 | BX21: 0 | BY21: 0 | BZ21: 0 | CA21: 0 | CB21: 1 | CC21: 0 | CD21: =SUM(BV21:CC22) -> 1 | CE21: =BV21*55+BW21*55+BX21*55+BY21*55+BZ21*30+CA21*30+CB21*30+CC21*30 -> 30 | CF21: 30€ EFECTIVO | CI21: 30 | CJ21: 0 | CK21: REVOLUT
AM22: MADRID | AP22: 2.5 | AQ22: =V35 -> 8 | AR22: =((AP22*AQ22)*0.21)/AQ22 -> 0.525 | AS22: =AP22+AR22 -> 3.025 | AT22: =AQ22*AS22 -> 24.2 | AY22: MADRID | BB22: =AP54 -> 30 | BC22: =T35 -> 8 | BD22: 0 | BE22: =BC22+BD22 -> 8 | BF22: =BB22*BE22 -> 240
D23: SAND | G23: 30.5 | H23: 25.8 | K23: =I23+J23 -> 0 | L23: =G23*K23 -> 0 | M23: =H23*K23 -> 0 | O23: SAND | R23: 9.45 | S23: 8.01 | V23: =T23+U23 -> 0 | W23: =R23*V23 -> 0 | X23: =S23*V23 -> 0 | Z23: SAND | AG23: =AE23+AF23 -> 0 | AH23: =AC23*AG23 -> 0 | AI23: =AD23*AG23 -> 0 | BR23: GA | BV23: 0 | BW23: 0 | BX23: 0 | BY23: 0 | BZ23: 0 | CA23: 0 | CB23: 1 | CC23: 0 | CD23: =SUM(BV23:CC24) -> 1 | CE23: =BV23*55+BW23*55+BX23*55+BY23*55+BZ23*30+CA23*30+CB23*30+CC23*30 -> 30 | CF23: 30€ EFECTIVO | CI23: 30 | CJ23: 0 | CK23: REVOLUT
AQ24: =SUM(AQ16:AQ23) -> 32 | AR24: =SUM(AR16:AR23) -> 2.52 | AT24: =SUM(AT16:AT23) -> 116.16 | BE24: =SUM(BE16:BE23) -> 32 | BF24: =SUM(BF16:BF23) -> 1360
D25: CREAM | G25: 30.5 | H25: 25.8 | K25: =I25+J25 -> 0 | L25: =G25*K25 -> 0 | M25: =H25*K25 -> 0 | O25: CREAM | R25: 9.45 | S25: 8.01 | V25: =T25+U25 -> 0 | W25: =R25*V25 -> 0 | X25: =S25*V25 -> 0 | Z25: CREAM | AG25: =AE25+AF25 -> 0 | AH25: =AC25*AG25 -> 0 | AI25: =AD25*AG25 -> 0 | BR25: NACHO PEREZ | BV25: 0 | BW25: 0 | BY25: 0 | BZ25: 1 | CA25: 0 | CB25: 0 | CC25: 0 | CD25: =SUM(BV25:CC26) -> 1 | CE25: =BV25*55+BW25*55+BX25*55+BY25*55+BZ25*30+CA25*30+CB25*30+CC25*30 -> 30 | CF25: 30€ EFECTIVO | CI25: 30 | CJ25: 0 | CK25: REVOLUT
D27: PINK DUST | G27: 30.5 | H27: 25.8 | K27: =I27+J27 -> 0 | L27: =G27*K27 -> 0 | M27: =H27*K27 -> 0 | O27: PINK DUST | R27: 9.45 | S27: 8.01 | V27: =T27+U27 -> 0 | W27: =R27*V27 -> 0 | X27: =S27*V27 -> 0 | Z27: PINK DUST | AG27: =AE27+AF27 -> 0 | AH27: =AC27*AG27 -> 0 | AI27: =AD27*AG27 -> 0 | BR27: CASAPE | BV27: 0 | BW27: 0 | BX27: 0 | BY27: 0 | BZ27: 1 | CA27: 0 | CB27: 0 | CC27: 0 | CD27: =SUM(BV27:CC28) -> 1 | CE27: =BV27*55+BW27*55+BX27*55+BY27*55+BZ27*30+CA27*30+CB27*30+CC27*30 -> 30 | CF27: 30€ EFECTIVO | CI27: 30 | CJ27: 0 | CK27: REVOLUT
AL28: COST PER UNIT | AX28: GON Y JACO
D29: PASTEL BLUE | K29: =I29+J29 -> 0 | L29: =G29*K29 -> 0 | M29: =H29*K29 -> 0 | O29: PASTEL BLUE | V29: =T29+U29 -> 0 | W29: =R29*V29 -> 0 | X29: =S29*V29 -> 0 | Z29: PASTEL BLUE | AG29: =AE29+AF29 -> 0 | AH29: =AC29*AG29 -> 0 | AI29: =AD29*AG29 -> 0 | BR29: JUANPA | BV29: 1 | BW29: 0 | BY29: 0 | CA29: 0 | CC29: 0 | CD29: =SUM(BV29:CC30) -> 1 | CE29: =BV29*55+BW29*55+BX29*55+BY29*55+BZ29*30+CA29*30+CB29*30+CC29*30 -> 55 | CF29: 55€ EFECTIVO | CI29: 55 | CJ29: 0 | CK29: REVOLUT
AP30: BLANK | AQ30: SERIGRAFIA | AR30: EXTRA | AS30: TOTAL € | BB30: M | BC30: L | BD30: UNITS | BE30: COST | BF30: TOTAL €
D31: SAGE PURPLE | G31: 30.5 | H31: 25.8 | K31: =I31+J31 -> 0 | L31: =G31*K31 -> 0 | M31: =H31*K31 -> 0 | O31: SAGE PURPLE | R31: 9.45 | S31: 8.01 | V31: =T31+U31 -> 0 | W31: =R31*V31 -> 0 | X31: =S31*V31 -> 0 | Z31: SAGE PURPLE | AG31: =AE31+AF31 -> 0 | AH31: =AC31*AG31 -> 0 | AI31: =AD31*AG31 -> 0 | BR31: DIEGO | BV31: 0 | BW31: 0 | BY31: 0 | BZ31: 1 | CA31: 0 | CC31: 0 | CD31: =SUM(BV31:CC32) -> 1 | CE31: =BV31*55+BW31*55+BX31*55+BY31*55+BZ31*30+CA31*30+CB31*30+CC31*30 -> 30 | CF31: 30€ EFECTIVO | CI31: 30 | CJ31: 0 | CK31: REVOLUT
AM32: MIRILLA | AP32: =H9 -> 27.5 | AQ32: =AS16 -> 4.235 | AS32: =SUM(AP32:AR33) -> 31.735 | AY32: MIRILLA | BB32: 1 | BC32: 0 | BD32: =BB32+BC32 -> 1 | BE32: =AS32 -> 31.735 | BF32: =BE32*BD32 -> 31.735
D33: ORANGE | K33: =I33+J33 -> 0 | L33: =G33*K33 -> 0 | M33: =H33*K33 -> 0 | O33: ORANGE | R33: 9.45 | S33: 8.01 | V33: =T33+U33 -> 0 | W33: =R33*V33 -> 0 | X33: =S33*V33 -> 0 | Z33: ORANGE | AG33: =AE33+AF33 -> 0 | AH33: =AC33*AG33 -> 0 | AI33: =AD33*AG33 -> 0 | BR33: JAIME X | BV33: 0 | BW33: 0 | BY33: 0 | BZ33: 0 | CA33: 0 | CB33: 1 | CC33: 0 | CD33: =SUM(BV33:CC34) -> 1 | CE33: =BV33*55+BW33*55+BX33*55+BY33*55+BZ33*30+CA33*30+CB33*30+CC33*30 -> 30 | CF33: 30€ EFECTIVO | CI33: 30 | CJ33: 0 | CK33: REVOLUT
AM34: CARA | AP34: =H13 -> 25.8 | AQ34: =AS18 -> 4.235 | AS34: =SUM(AP34:AR35) -> 30.035 | AY34: CARA | BB34: 1 | BC34: 0 | BD34: =BB34+BC34 -> 1 | BE34: =AS34 -> 30.035 | BF34: =BE34*BD34 -> 30.035
D35: FOREST GREEN | G35: 30.5 | H35: 25.8 | K35: =I35+J35 -> 0 | L35: =G35*K35 -> 0 | M35: =H35*K35 -> 0 | O35: GREEN | R35: 9.45 | S35: 8.01 | T35: 8 | V35: =T35+U35 -> 8 | W35: =R35*V35 -> 75.6 | X35: =S35*V35 -> 64.08 | Z35: FOREST GREEN | AG35: =AE35+AF35 -> 0 | AH35: =AC35*AG35 -> 0 | AI35: =AD35*AG35 -> 0 | BR35: AMIGO ANGEL | BV35: 0 | BW35: 0 | BY35: 0 | BZ35: 0 | CA35: 0 | CB35: 1 | CC35: 0 | CD35: =SUM(BV35:CC36) -> 1 | CE35: =BV35*55+BW35*55+BX35*55+BY35*55+BZ35*30+CA35*30+CB35*30+CC35*30 -> 30 | CF35: 30€ EFECTIVO | CI35: 30 | CJ35: 0 | CK35: REVOLUT
AM36: AIRLINE | AP36: =S15 -> 8.01 | AQ36: =AS20 -> 3.025 | AS36: =SUM(AP36:AR37) -> 11.035 | AY36: AIRLINE | BB36: 2 | BC36: 0 | BD36: =BB36+BC36 -> 2 | BE36: =AS36 -> 11.035 | BF36: =BE36*BD36 -> 22.07
I37: =SUM(I7:I36) -> 14 | J37: =SUM(J7:J36) -> 2 | K37: =SUM(K7:K36) -> 16 | L37: =SUM(L7:L36) -> 508 | M37: =SUM(M7:M36) -> 429.8 | T37: =SUM(T7:T36) -> 16 | U37: =SUM(U7:U36) -> 0 | V37: =SUM(V7:V36) -> 16 | W37: =SUM(W7:W36) -> 151.2 | X37: =SUM(X7:X36) -> 128.16 | AE37: =SUM(AE7:AE36) -> 0 | AF37: =SUM(AF7:AF36) -> 0 | AG37: =SUM(AG7:AG36) -> 0 | AH37: =SUM(AH7:AH36) -> 0 | AI37: =SUM(AI7:AI36) -> 0 | BR37: GENO | BW37: 0 | BX37: 1 | BY37: 0 | CA37: 0 | CC37: 0 | CD37: =SUM(BV37:CC38) -> 1 | CE37: =BV37*55+BW37*55+BX37*55+BY37*55+BZ37*30+CA37*30+CB37*30+CC37*30 -> 55 | CF37: 20€ EFECTIVO + 20€ TARJETA | CI37: 20 | CJ37: 20 | CK37: REVOLUT
AM38: MADRID | AP38: =S35 -> 8.01 | AQ38: =AS22 -> 3.025 | AS38: =SUM(AP38:AR39) -> 11.035 | AY38: MADRID | BB38: 2 | BC38: 0 | BD38: =BB38+BC38 -> 2 | BE38: =AS38 -> 11.035 | BF38: =BE38*BD38 -> 22.07
BR39: CANDELA | BW39: 0 | BX39: 1 | BY39: 0 | CA39: 0 | CC39: 0 | CD39: =SUM(BV39:CC40) -> 1 | CE39: =BV39*55+BW39*55+BX39*55+BY39*55+BZ39*30+CA39*30+CB39*30+CC39*30 -> 55 | CF39: 40€ TARJETA | CI39: 0 | CJ39: 40 | CK39: REVOLUT
BD40: =SUM(BD32:BD39) -> 6 | BF40: =SUM(BF32:BF39) -> 105.91
G41: LONGSLEEVE | R41: SWEATPANTS | AC41: SHORT SWEATPANTS | BR41: AMIGO JAIME | BW41: 0 | BX41: 1 | BY41: 0 | CA41: 0 | CC41: 0 | CD41: =SUM(BV41:CC42) -> 1 | CE41: =BV41*55+BW41*55+BX41*55+BY41*55+BZ41*30+CA41*30+CB41*30+CC41*30 -> 55 | CF41: 32€ TARJETA | CI41: 0 | CJ41: 32 | CK41: REVOLUT | CM41: 44626
G43: PRICE $ | H43: PRICE € | I43: M | J43: L | K43: UNITS | L43: TOTAL $ | M43: TOTAL € | R43: PRICE $ | S43: PRICE € | T43: M | U43: L | V43: UNITS | W43: TOTAL $ | X43: TOTAL € | AC43: PRICE $ | AD43: PRICE € | AE43: M | AF43: L | AG43: UNITS | AH43: TOTAL $ | AI43: TOTAL € | CD43: =SUM(BV43:CC44) -> 0 | CE43: =BV43*55+BW43*55+BX43*55+BY43*55+BZ43*30+CA43*30+CB43*30+CC43*30 -> 0
AL44: PROFFIT PER UNIT
D45: BLACK | K45: =I45+J45 -> 0 | L45: =G45*K45 -> 0 | M45: =H45*K45 -> 0 | O45: BLACK | V45: =T45+U45 -> 0 | W45: =R45*V45 -> 0 | X45: =S45*V45 -> 0 | Z45: BLACK | AG45: =AE45+AF45 -> 0 | AH45: =AC45*AG45 -> 0 | AI45: =AD45*AG45 -> 0 | CD45: =SUM(BV45:CC46) -> 0 | CE45: =BV45*55+BW45*55+BX45*55+BY45*55+BZ45*30+CA45*30+CB45*30+CC45*30 -> 0
AP46: SALE | AQ46: COST | AR46: PROFIT | AS46: P.MARGIN | BB46: PRICE | BC46: M | BD46: L | BE46: UNITS | BF46: TOTAL €
D47: VINTAGE BLACK | K47: =I47+J47 -> 0 | L47: =G47*K47 -> 0 | M47: =H47*K47 -> 0 | O47: VINTAGE BLACK | V47: =T47+U47 -> 0 | W47: =R47*V47 -> 0 | X47: =S47*V47 -> 0 | Z47: VINTAGE BLACK | AG47: =AE47+AF47 -> 0 | AH47: =AC47*AG47 -> 0 | AI47: =AD47*AG47 -> 0 | CD47: =SUM(BV47:CC48) -> 0 | CE47: =BV47*55+BW47*55+BX47*55+BY47*55+BZ47*30+CA47*30+CB47*30+CC47*30 -> 0
AM48: MIRILLA | AP48: 55 | AQ48: =AS32 -> 31.735 | AR48: =AP48-AQ48 -> 23.265 | AS48: =(AP48-AQ48)/AQ48 -> 0.73310225 | AY48: MIRILLA | BB48: =AP48 -> 55 | BC48: =BC16-BB32 -> 7 | BD48: =BD16-BC32 -> 2 | BE48: =BC48+BD48 -> 9 | BF48: =BB48*BE48 -> 495
D49: GARMENT DYED | K49: =I49+J49 -> 0 | L49: =G49*K49 -> 0 | M49: =H49*K49 -> 0 | O49: GARMENT DYED | V49: =T49+U49 -> 0 | W49: =R49*V49 -> 0 | X49: =S49*V49 -> 0 | Z49: GARMENT DYED | AG49: =AE49+AF49 -> 0 | AH49: =AC49*AG49 -> 0 | AI49: =AD49*AG49 -> 0 | CD49: =SUM(BV49:CC50) -> 0 | CE49: =BV49*55+BW49*55+BX49*55+BY49*55+BZ49*30+CA49*30+CB49*30+CC49*30 -> 0
AM50: CARA | AP50: 55 | AQ50: =AS34 -> 30.035 | AR50: =AP50-AQ50 -> 24.965 | AS50: =(AP50-AQ50)/AQ50 -> 0.83119694 | AY50: CARA | BB50: =AP50 -> 55 | BC50: =BC18-BB34 -> 5 | BD50: =BD18-BC34 -> 0 | BE50: =BC50+BD50 -> 5 | BF50: =BB50*BE50 -> 275
D51: HEATHER GREY | K51: =I51+J51 -> 0 | L51: =G51*K51 -> 0 | M51: =H51*K51 -> 0 | O51: HEATHER GREY | V51: =T51+U51 -> 0 | W51: =R51*V51 -> 0 | X51: =S51*V51 -> 0 | Z51: HEATHER GREY | AG51: =AE51+AF51 -> 0 | AH51: =AC51*AG51 -> 0 | AI51: =AD51*AG51 -> 0 | CD51: =SUM(BV51:CC52) -> 0 | CE51: =BV51*55+BW51*55+BX51*55+BY51*55+BZ51*30+CA51*30+CB51*30+CC51*30 -> 0
AM52: AIRLINE | AP52: 30 | AQ52: =AS36 -> 11.035 | AR52: =AP52-AQ52 -> 18.965 | AS52: =(AP52-AQ52)/AQ52 -> 1.7186226 | AY52: AIRLINE | BB52: =AP52 -> 30 | BC52: =BC20-BB36 -> 6 | BD52: =BD20-BC36 -> 0 | BE52: =BC52+BD52 -> 6 | BF52: =BB52*BE52 -> 180
D53: WHITE | K53: =I53+J53 -> 0 | L53: =G53*K53 -> 0 | M53: =H53*K53 -> 0 | O53: WHITE | V53: =T53+U53 -> 0 | W53: =R53*V53 -> 0 | X53: =S53*V53 -> 0 | Z53: WHITE | AG53: =AE53+AF53 -> 0 | AH53: =AC53*AG53 -> 0 | AI53: =AD53*AG53 -> 0 | CD53: =SUM(BV53:CC54) -> 0 | CE53: =BV53*55+BW53*55+BX53*55+BY53*55+BZ53*30+CA53*30+CB53*30+CC53*30 -> 0
AM54: MADRID | AP54: 30 | AQ54: =AS38 -> 11.035 | AR54: =AP54-AQ54 -> 18.965 | AS54: =(AP54-AQ54)/AQ54 -> 1.7186226 | AY54: MADRID | BB54: =AP54 -> 30 | BC54: =BC22-BB38 -> 6 | BD54: =BD22-BC38 -> 0 | BE54: =BC54+BD54 -> 6 | BF54: =BB54*BE54 -> 180
D55: VINTAGE BROWN | K55: =I55+J55 -> 0 | L55: =G55*K55 -> 0 | M55: =H55*K55 -> 0 | O55: VINTAGE BROWN | V55: =T55+U55 -> 0 | W55: =R55*V55 -> 0 | X55: =S55*V55 -> 0 | Z55: VINTAGE BROWN | AG55: =AE55+AF55 -> 0 | AH55: =AC55*AG55 -> 0 | AI55: =AD55*AG55 -> 0 | CD55: =SUM(BV55:CC56) -> 0 | CE55: =BV55*55+BW55*55+BX55*55+BY55*55+BZ55*30+CA55*30+CB55*30+CC55*30 -> 0
BE56: =SUM(BE48:BE55) -> 26 | BF56: =SUM(BF48:BF55) -> 1130
D57: CAMEL | K57: =I57+J57 -> 0 | L57: =G57*K57 -> 0 | M57: =H57*K57 -> 0 | O57: CAMEL | V57: =T57+U57 -> 0 | W57: =R57*V57 -> 0 | X57: =S57*V57 -> 0 | Z57: CAMEL | AG57: =AE57+AF57 -> 0 | AH57: =AC57*AG57 -> 0 | AI57: =AD57*AG57 -> 0 | CD57: =SUM(BV57:CC58) -> 0 | CE57: =BV57*55+BW57*55+BX57*55+BY57*55+BZ57*30+CA57*30+CB57*30+CC57*30 -> 0
D59: KHAKI | K59: =I59+J59 -> 0 | L59: =G59*K59 -> 0 | M59: =H59*K59 -> 0 | O59: KHAKI | V59: =T59+U59 -> 0 | W59: =R59*V59 -> 0 | X59: =S59*V59 -> 0 | Z59: KHAKI | AG59: =AE59+AF59 -> 0 | AH59: =AC59*AG59 -> 0 | AI59: =AD59*AG59 -> 0 | CD59: =SUM(BV59:CC60) -> 0 | CE59: =BV59*55+BW59*55+BX59*55+BY59*55+BZ59*30+CA59*30+CB59*30+CC59*30 -> 0
D61: SAND | K61: =I61+J61 -> 0 | L61: =G61*K61 -> 0 | M61: =H61*K61 -> 0 | O61: SAND | V61: =T61+U61 -> 0 | W61: =R61*V61 -> 0 | X61: =S61*V61 -> 0 | Z61: SAND | AG61: =AE61+AF61 -> 0 | AH61: =AC61*AG61 -> 0 | AI61: =AD61*AG61 -> 0 | CD61: =SUM(BV61:CC62) -> 0 | CE61: =BV61*55+BW61*55+BX61*55+BY61*55+BZ61*30+CA61*30+CB61*30+CC61*30 -> 0
D63: CREAM | K63: =I63+J63 -> 0 | L63: =G63*K63 -> 0 | M63: =H63*K63 -> 0 | O63: CREAM | V63: =T63+U63 -> 0 | W63: =R63*V63 -> 0 | X63: =S63*V63 -> 0 | Z63: CREAM | AG63: =AE63+AF63 -> 0 | AH63: =AC63*AG63 -> 0 | AI63: =AD63*AG63 -> 0 | CD63: =SUM(BV63:CC64) -> 0 | CE63: =BV63*55+BW63*55+BX63*55+BY63*55+BZ63*30+CA63*30+CB63*30+CC63*30 -> 0
D65: PINK DUST | K65: =I65+J65 -> 0 | L65: =G65*K65 -> 0 | M65: =H65*K65 -> 0 | O65: PINK DUST | V65: =T65+U65 -> 0 | W65: =R65*V65 -> 0 | X65: =S65*V65 -> 0 | Z65: PINK DUST | AG65: =AE65+AF65 -> 0 | AH65: =AC65*AG65 -> 0 | AI65: =AD65*AG65 -> 0 | CD65: =SUM(BV65:CC66) -> 0 | CE65: =BV65*55+BW65*55+BX65*55+BY65*55+BZ65*30+CA65*30+CB65*30+CC65*30 -> 0
D67: PASTEL BLUE | K67: =I67+J67 -> 0 | L67: =G67*K67 -> 0 | M67: =H67*K67 -> 0 | O67: PASTEL BLUE | V67: =T67+U67 -> 0 | W67: =R67*V67 -> 0 | X67: =S67*V67 -> 0 | Z67: PASTEL BLUE | AG67: =AE67+AF67 -> 0 | AH67: =AC67*AG67 -> 0 | AI67: =AD67*AG67 -> 0 | CD67: =SUM(BV67:CC68) -> 0 | CE67: =BV67*55+BW67*55+BX67*55+BY67*55+BZ67*30+CA67*30+CB67*30+CC67*30 -> 0
D69: SAGE PURPLE | K69: =I69+J69 -> 0 | L69: =G69*K69 -> 0 | M69: =H69*K69 -> 0 | O69: SAGE PURPLE | V69: =T69+U69 -> 0 | W69: =R69*V69 -> 0 | X69: =S69*V69 -> 0 | Z69: SAGE PURPLE | AG69: =AE69+AF69 -> 0 | AH69: =AC69*AG69 -> 0 | AI69: =AD69*AG69 -> 0 | CD69: =SUM(BV69:CC70) -> 0 | CE69: =BV69*55+BW69*55+BX69*55+BY69*55+BZ69*30+CA69*30+CB69*30+CC69*30 -> 0
D71: ORANGE | K71: =I71+J71 -> 0 | L71: =G71*K71 -> 0 | M71: =H71*K71 -> 0 | O71: ORANGE | V71: =T71+U71 -> 0 | W71: =R71*V71 -> 0 | X71: =S71*V71 -> 0 | Z71: ORANGE | AG71: =AE71+AF71 -> 0 | AH71: =AC71*AG71 -> 0 | AI71: =AD71*AG71 -> 0
BT72: SOLD | BV72: =SUM(BV9:BV70) -> 7 | BW72: =SUM(BW9:BW70) -> 2 | BX72: =SUM(BX9:BX70) -> 4 | BY72: =SUM(BY9:BY70) -> 0 | BZ72: =SUM(BZ9:BZ70) -> 6 | CA72: =SUM(CA9:CA70) -> 0 | CB72: =SUM(CB9:CB70) -> 6 | CC72: =SUM(CC9:CC70) -> 0 | ... CE72: =SUM(CE9:CE70) -> 1075 | CI72: =SUM(CI9:CI70) -> 455 | CJ72: =SUM(CJ9:CJ70) -> 594 | CK72: =SUM(CK9:CL70) -> 0
D73: FOREST GREEN | K73: =I73+J73 -> 0 | L73: =G73*K73 -> 0 | M73: =H73*K73 -> 0 | O73: FOREST GREEN | V73: =T73+U73 -> 0 | W73: =R73*V73 -> 0 | X73: =S73*V73 -> 0 | Z73: FOREST GREEN | AG73: =AE73+AF73 -> 0 | AH73: =AC73*AG73 -> 0 | AI73: =AD73*AG73 -> 0
BT74: STOCK | BV74: =BV5-BV72 -> 0 | BW74: =BW5-BW72 -> 0 | BX74: =BX5-BX72 -> 1 | BY74: =BY5-BY72 -> 0 | BZ74: =BZ5-BZ72 -> 0 | CA74: =CA5-CA72 -> 0 | CB74: =CB5-CB72 -> 0 | CC74: =CC5-CC72 -> 0 | CD74: =CD5-CD72 -> 1 | CJ74: =CI72+CJ72+CK72 -> 1049
I75: =SUM(I45:I74) -> 0 | J75: =SUM(J45:J74) -> 0 | K75: =SUM(K45:K74) -> 0 | L75: =SUM(L45:L74) -> 0 | M75: =SUM(M45:M74) -> 0 | T75: =SUM(T45:T74) -> 0 | U75: =SUM(U45:U74) -> 0 | V75: =SUM(V45:V74) -> 0 | W75: =SUM(W45:W74) -> 0 | X75: =SUM(X45:X74) -> 0 | AE75: =SUM(AE45:AE74) -> 0 | AF75: =SUM(AF45:AF74) -> 0 | AG75: =SUM(AG45:AG74) -> 0 | AH75: =SUM(AH45:AH74) -> 0 | AI75: =SUM(AI45:AI74) -> 0
CG77: INGRESOS | CL77: =CJ74 -> 1049
BT78: SOLD | BV78: =CD72 -> 25
CG80: RUE PORTER | CL80: =BN6 -> 655.48
CG82: SERIGRAFIA | CL82: =BN8 -> 116.16
CG84: ETIQUETAS | CL84: 66.46
CG86: COSTE TOTAL | CL86: =SUM(CL80:CM85) -> 838.1
CG89: TOTAL FINAL | CL89: =CL77-CL86 -> 210.9

Sheet DROP 2
B2: DROP 2 | P2: INGRESOS FINALES | Q2: PRECIO | R2: M | S2: L | T2: UNIDADES | U2: TOTAL | Y2: INGRESOS | Z2: PRECIO | AA2: M | AB2: L | AC2: UNIDADES | AD2: TOTAL
P3: =$P$27 -> OJOS | Q3: =Z3 -> 49 | R3: 4 | S3: 6 | T3: =SUM(R3:S3) -> 10 | U3: =IFERROR(Q3*T3,"-") -> 490 | Y3: =$P$27 -> OJOS | Z3: =Z35 -> 49 | AA3: =R27 -> 7 | AB3: =S27 -> 7 | AC3: =SUM(AA3:AB3) -> 14 | AD3: =IFERROR(Z3*AC3,"-") -> 686
P4: =$P$28 -> MIRILLA | Q4: =Z4 -> 34 | R4: 2 | S4: 4 | T4: =SUM(R4:S4) -> 6 | U4: =IFERROR(Q4*T4,"-") -> 204 | Y4: =$P$28 -> MIRILLA | Z4: =Z36 -> 34 | AA4: =R28-4 -> 10 | AB4: =S28 -> 7 | AC4: =SUM(AA4:AB4) -> 17 | AD4: =IFERROR(Z4*AC4,"-") -> 578
C5: PPTO | D5: REAL | P5: =$P$29 -> SEÑORA | Q5: =Z5 -> 29 | R5: 2 | S5: 3 | T5: =SUM(R5:S5) -> 5 | U5: =IFERROR(Q5*T5,"-") -> 145 | Y5: =$P$29 -> SEÑORA | Z5: =Z37 -> 29 | AA5: =R29 -> 6 | AB5: =S29 -> 4 | AC5: =SUM(AA5:AB5) -> 10 | AD5: =IFERROR(Z5*AC5,"-") -> 290
B6: INGRESOS | C6: =U9+U18 -> 1318 | D6: =SUM(L27:$L$61) -> 1304 | P6: =$P$30 -> CALAVERA | Q6: =Z6 -> 29 | R6: =AA6-AA15 -> 2 | S6: =AB6-AB15 -> 2 | T6: =SUM(R6:S6) -> 4 | U6: =IFERROR(Q6*T6,"-") -> 116 | Y6: =$P$30 -> CALAVERA | Z6: =Z38 -> 29 | AA6: =R30 -> 2 | AB6: =S30 -> 2 | AC6: =SUM(AA6:AB6) -> 4 | AD6: =IFERROR(Z6*AC6,"-") -> 116
B7: Otros ingresos | C7: 0 | R7: =AA7-AA16 -> 0 | S7: =AB7-AB16 -> 0 | T7: =SUM(R7:S7) -> 0 | U7: =IFERROR(Q7*T7,"-") -> 0 | AA7: =R31 -> 0 | AB7: =S31 -> 0 | AC7: =SUM(AA7:AB7) -> 0 | AD7: =IFERROR(Z7*AC7,"-") -> 0
B8: TOTAL INGRESOS | C8: =SUM(C6:C7) -> 1318 | D8: =SUM(D6:D7) -> 1304 | R8: =AA8-AA17 -> 0 | S8: =AB8-AB17 -> 0 | T8: =SUM(R8:S8) -> 0 | U8: =IFERROR(Q8*T8,"-") -> 0 | AA8: =R32 -> 0 | AB8: =S32 -> 0 | AC8: =SUM(AA8:AB8) -> 0 | AD8: =IFERROR(Z8*AC8,"-") -> 0
B9: Gasto Blanks 1 | C9: =-$W$52 -> -887.43 | D9: =C9 -> -887.43 | P9: INGRESOS TOTALES FINALES | T9: =SUM(T3:T8) -> 25 | U9: =SUM(U3:U8) -> 955 | Y9: INGRESOS TOTALES | AC9: =SUM(AC3:AC8) -> 45 | AD9: =SUM(AD3:AD8) -> 1670
B10: Gasto Serigrafia | C10: =-$U$61 -> -246.235 | D10: =C10 -> -246.235
B11: Publicidad | C11: =-40 -> -40 | D11: =C11 -> -40 | P11: INGRESOS FINALES CON % | Q11: PRECIO | R11: M | S11: L | T11: UNIDADES | U11: TOTAL | Y11: GON JACO | Z11: COSTE | AA11: M | AB11: L | AC11: UNIDADES | AD11: TOTAL
B12: Otros gastos | C12: =-12.69-26.33-49.01 -> -88.03 | D12: =C12 -> -88.03 | P12: =$P$27 -> OJOS | Q12: 39 | R12: =(AA3-AA12)-R3 -> 1 | S12: =(AB3-AB12)-S3 -> 1 | T12: =SUM(R12:S12) -> 2 | U12: =IFERROR(Q12*T12,"-") -> 78 | Y12: =$P$27 -> OJOS | Z12: =AA35 -> -35.055102 | AA12: 2 | AC12: =SUM(AA12:AB12) -> 2 | AD12: =IFERROR(Z12*AC12,"-") -> -70.110204
P13: =$P$28 -> MIRILLA | Q13: 27 | R13: =(AA4-AA13)-R4 -> 5 | S13: =(AB4-AB13)-S4 -> 3 | T13: =SUM(R13:S13) -> 8 | U13: =IFERROR(Q13*T13,"-") -> 216 | Y13: =$P$28 -> MIRILLA | Z13: =AA36 -> -16.755102 | AA13: 3 | AC13: =SUM(AA13:AB13) -> 3 | AD13: =IFERROR(Z13*AC13,"-") -> -50.265306
B14: TOTAL GASTOS | C14: =SUM(C9:C13) -> -1261.695 | D14: =SUM(D9:D13) -> -1261.695 | P14: =$P$29 -> SEÑORA | Q14: 23 | R14: =(AA5-AA14)-R5 -> 2 | S14: =(AB5-AB14)-S5 -> 1 | T14: =SUM(R14:S14) -> 3 | U14: =IFERROR(Q14*T14,"-") -> 69 | Y14: =$P$29 -> SEÑORA | Z14: =AA37 -> -14.960102 | AA14: 2 | AC14: =SUM(AA14:AB14) -> 2 | AD14: =IFERROR(Z14*AC14,"-") -> -29.920204
P15: =$P$30 -> CALAVERA | Q15: 23 | R15: =(AA6-AA15)-R6 -> 0 | S15: =(AB6-AB15)-S6 -> 0 | T15: =SUM(R15:S15) -> 0 | U15: =IFERROR(Q15*T15,"-") -> 0 | Y15: =$P$30 -> CALAVERA | Z15: =AA38 -> -22.805102 | AC15: =SUM(AA15:AB15) -> 0 | AD15: =IFERROR(Z15*AC15,"-") -> 0
R16: =(AA7-AA16)-R7 -> 0 | S16: =(AB7-AB16)-S7 -> 0 | T16: =SUM(R16:S16) -> 0 | U16: =IFERROR(Q16*T16,"-") -> 0 | AC16: =SUM(AA16:AB16) -> 0 | AD16: =IFERROR(Z16*AC16,"-") -> 0
B17: BENEFICIO | C17: =C8+C14 -> 56.305 | D17: =D8+D14 -> 42.305 | R17: =(AA8-AA17)-R8 -> 0 | S17: =(AB8-AB17)-S8 -> 0 | T17: =SUM(R17:S17) -> 0 | U17: =IFERROR(Q17*T17,"-") -> 0 | AC17: =SUM(AA17:AB17) -> 0 | AD17: =IFERROR(Z17*AC17,"-") -> 0
P18: INGRESOS TOTALES FINALES | T18: =SUM(T12:T17) -> 13 | U18: =SUM(U12:U17) -> 363 | Y18: COSTE TOTAL | AC18: =SUM(AC12:AC17) -> 7 | AD18: =SUM(AD12:AD17) -> -150.29571
B19: RATIO DE BLANKS | C19: =IFERROR(ABS($C$9/$C$8),"-") -> 0.67331563 | D19: =IFERROR(ABS($D$10/$D$8),"-") -> 0.18883052
B20: COR% | C20: =IFERROR(ABS($C$14/$C$8),"-") -> 0.95727997 | D20: =IFERROR(ABS($D$14/$D$8),"-") -> 0.96755752
C22: =$P$27 -> OJOS | E22: =$P$28 -> MIRILLA | G22: =$P$29 -> SEÑORA | I22: =$P$30 -> CALAVERA
C23: M | D23: L | E23: M | F23: L | G23: M | H23: L | I23: M | J23: L | K23: TOTAL
B24: SOLD | C24: =SUM(C27:C61) -> 5 | D24: =SUM(D27:D61) -> 7 | E24: =SUM(E27:E61) -> 7 | F24: =SUM(F27:F61) -> 7 | G24: =SUM(G27:G61) -> 4 | H24: =SUM(H27:H61) -> 4 | I24: =SUM(I27:I61) -> 2 | J24: =SUM(J27:J61) -> 2 | K24: =SUM(C24:J24) -> 38 | L24: =K24-SUM(K27:K61) -> 0
B25: STOCK | C25: =R3+R12-C24 -> 0 | D25: =S3+S12-D24 -> 0 | E25: =R4+R13-E24 -> 0 | F25: =S4+S13-F24 -> 0 | G25: =R5+R14-G24 -> 0 | H25: =S5+S14-H24 -> 0 | I25: =R6-I24 -> 0 | J25: =S6-J24 -> 0 | K25: =SUM(C25:J25) -> 0
B26: NOMBRE | K26: UNIDADES | L26: INGRESO | M26: FECHA | P26: BLANKS 1 | Q26: UND€ | R26: M | S26: L | T26: UNIDADES | U26: EXTRA | V26: € PER UND | W26: TOTAL | Y26: COSTE POR UND | Z26: BLANKS | AA26: SERIGRAFIA | AB26: EXTRA | AC26: TOTAL
A27: 1 | B27: ANGEL AMIGO JACO | D27: 1 | G27: 1 | K27: =SUM(C27:J27) -> 2 | L27: =IFERROR(((C27+D27)*$Q$3)+((E27+F27)*$Q$4)+((G27+H27)*$Q$5)+((I27+J27)*$Q$6),"-") -> 78 | P27: OJOS | Q27: 27.5 | R27: 7 | S27: 7 | T27: =R27+S27 -> 14 | U27: =IFERROR($W$36/$T$33,"-") -> 3.925102 | V27: =IFERROR(Q27+U27,"-") -> 31.425102 | W27: =IFERROR(T27*V27,"-") -> 439.95143 | Y27: =$P$27 -> OJOS | Z27: =V27 -> 31.425102 | AA27: =T55 -> 3.63 | AC27: =SUM(Z27:AB27) -> 35.055102
A28: 2 | B28: DIEGO AMIGO JACO | F28: 1 | H28: 1 | K28: =SUM(C28:J28) -> 2 | L28: =IFERROR(((C28+D28)*$Q$3)+((E28+F28)*$Q$4)+((G28+H28)*$Q$5)+((I28+J28)*$Q$6),"-") -> 63 | P28: MIRILLA | Q28: 9.2 | R28: 14 | S28: 7 | T28: =R28+S28 -> 21 | U28: =IFERROR($W$36/$T$33,"-") -> 3.925102 | V28: =IFERROR(Q28+U28,"-") -> 13.125102 | W28: =IFERROR(T28*V28,"-") -> 275.62714 | Y28: =$P$28 -> MIRILLA | Z28: =V28 -> 13.125102 | AA28: =T56 -> 3.63 | AC28: =SUM(Z28:AB28) -> 16.755102
A29: 3 | B29: JUANMA | I29: 1 | K29: =SUM(C29:J29) -> 1 | L29: =IFERROR(((C29+D29)*$Q$3)+((E29+F29)*$Q$4)+((G29+H29)*$Q$5)+((I29+J29)*$Q$6),"-") -> 29 | P29: SEÑORA | Q29: 8.01 | R29: 6 | S29: 4 | T29: =R29+S29 -> 10 | U29: =IFERROR($W$36/$T$33,"-") -> 3.925102 | V29: =IFERROR(Q29+U29,"-") -> 11.935102 | W29: =IFERROR(T29*V29,"-") -> 119.35102 | Y29: =$P$29 -> SEÑORA | Z29: =V29 -> 11.935102 | AA29: =T57 -> 3.025 | AC29: =SUM(Z29:AB29) -> 14.960102
A30: =A29+1 -> 4 | B30: JUANTO | E30: 1 | G30: 1 | K30: =SUM(C30:J30) -> 2 | L30: =IFERROR(((C30+D30)*$Q$3)+((E30+F30)*$Q$4)+((G30+H30)*$Q$5)+((I30+J30)*$Q$6),"-") -> 63 | P30: CALAVERA | Q30: 9.2 | R30: 2 | S30: 2 | T30: =R30+S30 -> 4 | U30: =IFERROR($W$36/$T$33,"-") -> 3.925102 | V30: =IFERROR(Q30+U30,"-") -> 13.125102 | W30: =IFERROR(T30*V30,"-") -> 52.500408 | Y30: =$P$30 -> CALAVERA | Z30: =V30 -> 13.125102 | AA30: =T58 -> 9.68 | AC30: =SUM(Z30:AB30) -> 22.805102
A31: =A30+1 -> 5 | B31: JORGE PUIG | C31: 1 | K31: =SUM(C31:J31) -> 1 | L31: =IFERROR(((C31+D31)*$Q$3)+((E31+F31)*$Q$4)+((G31+H31)*$Q$5)+((I31+J31)*$Q$6),"-") -> 49 | T31: =R31+S31 -> 0 | V31: =IFERROR(Q31+U31,"-") -> 0 | W31: =IFERROR(T31*V31,"-") -> 0 | AC31: =SUM(Z31:AB31) -> 0
A32: =A31+1 -> 6 | B32: NACHO PEREZ | F32: 1 | K32: =SUM(C32:J32) -> 1 | L32: =IFERROR(((C32+D32)*$Q$3)+((E32+F32)*$Q$4)+((G32+H32)*$Q$5)+((I32+J32)*$Q$6),"-") -> 34 | T32: =R32+S32 -> 0 | V32: =IFERROR(Q32+U32,"-") -> 0 | W32: =IFERROR(T32*V32,"-") -> 0 | AC32: =SUM(Z32:AB32) -> 0
A33: =A32+1 -> 7 | B33: PETER | E33: 1 | K33: =SUM(C33:J33) -> 1 | L33: =IFERROR(((C33+D33)*$Q$3)+((E33+F33)*$Q$4)+((G33+H33)*$Q$5)+((I33+J33)*$Q$6),"-") -> 34 | P33: TOTAL | T33: =SUM(T27:T32) -> 49 | W33: =SUM(W27:W32) -> 887.43
A34: =A33+1 -> 8 | B34: BARALLOBRE | H34: 1 | K34: =SUM(C34:J34) -> 1 | L34: =IFERROR(((C34+D34)*$Q$3)+((E34+F34)*$Q$4)+((G34+H34)*$Q$5)+((I34+J34)*$Q$6),"-") -> 29 | P34: Envio | W34: 150 | Y34: BENEFICIO POR UND | Z34: PRECIO | AA34: COSTE | AB34: BENEFICIO | AC34: MARGEN
A35: =A34+1 -> 9 | B35: PUIG AMIGO JACO | C35: 1 | I35: 1 | K35: =SUM(C35:J35) -> 2 | L35: =IFERROR(((C35+D35)*$Q$3)+((E35+F35)*$Q$4)+((G35+H35)*$Q$5)+((I35+J35)*$Q$6),"-") -> 78 | P35: Otros gastos | W35: 42.33 | Y35: =$P$27 -> OJOS | Z35: 49 | AA35: =-AC27 -> -35.055102 | AB35: =SUM(Z35:AA35) -> 13.944898 | AC35: =AB35/Z35 -> 0.28458975
A36: =A35+1 -> 10 | B36: FORMARIZ | C36: 1 | K36: =SUM(C36:J36) -> 1 | L36: =IFERROR(((C36+D36)*$Q$3)+((E36+F36)*$Q$4)+((G36+H36)*$Q$5)+((I36+J36)*$Q$6),"-") -> 49 | P36: TOTAL EXTRAS | W36: =SUM(W34:W35) -> 192.33 | Y36: =$P$28 -> MIRILLA | Z36: 34 | AA36: =-AC28 -> -16.755102 | AB36: =SUM(Z36:AA36) -> 17.244898 | AC36: =AB36/Z36 -> 0.50720288
A37: =A36+1 -> 11 | B37: DOMINGUEZ | F37: 1 | H37: 1 | K37: =SUM(C37:J37) -> 2 | L37: =IFERROR(((C37+D37)*$Q$3)+((E37+F37)*$Q$4)+((G37+H37)*$Q$5)+((I37+J37)*$Q$6),"-") -> 63 | P37: BLANKS TOTAL | W37: =W33 -> 887.43 | Y37: =$P$29 -> SEÑORA | Z37: 29 | AA37: =-AC29 -> -14.960102 | AB37: =SUM(Z37:AA37) -> 14.039898 | AC37: =AB37/Z37 -> 0.48413441
A38: =A37+1 -> 12 | B38: IÑIGO | D38: 1 | K38: =SUM(C38:J38) -> 1 | L38: =IFERROR(((C38+D38)*$Q$3)+((E38+F38)*$Q$4)+((G38+H38)*$Q$5)+((I38+J38)*$Q$6),"-")-9 -> 40 | W38: =Q27*T27+Q28*T28+Q29*T29+Q30*T30+Q31*T31+Q32*T32+W36-W37 -> 0 | Y38: =$P$30 -> CALAVERA | Z38: 29 | AA38: =-AC30 -> -22.805102 | AB38: =SUM(Z38:AA38) -> 6.194898 | AC38: =AB38/Z38 -> 0.21361717
A39: =A38+1 -> 13 | B39: MUÑOZ | C39: 1 | J39: 1 | K39: =SUM(C39:J39) -> 2 | L39: =IFERROR(((C39+D39)*$Q$3)+((E39+F39)*$Q$4)+((G39+H39)*$Q$5)+((I39+J39)*$Q$6),"-") -> 78 | P39: BLANKS 2 | Q39: UND€ | R39: M | S39: L | T39: UNIDADES | U39: EXTRA | V39: € PER UND | W39: TOTAL
A40: =A39+1 -> 14 | B40: TITO | D40: 1 | K40: =SUM(C40:J40) -> 1 | L40: =IFERROR(((C40+D40)*$Q$3)+((E40+F40)*$Q$4)+((G40+H40)*$Q$5)+((I40+J40)*$Q$6),"-")-4 -> 45 | T40: =SUM(R40:S40) -> 0 | U40: =IFERROR($W$49/$T$46,"-") -> - | V40: =IFERROR(Q40+U40,"-") -> - | W40: =IFERROR(T40*V40,"-") -> -
A41: =A40+1 -> 15 | B41: CARLOTA DEL OLMO | D41: 1 | K41: =SUM(C41:J41) -> 1 | L41: =IFERROR(((C41+D41)*$Q$3)+((E41+F41)*$Q$4)+((G41+H41)*$Q$5)+((I41+J41)*$Q$6),"-")+3.7 -> 52.7 | T41: =SUM(R41:S41) -> 0 | U41: =IFERROR($W$49/$T$46,"-") -> - | V41: =IFERROR(Q41+U41,"-") -> - | W41: =IFERROR(T41*V41,"-") -> -
A42: =A41+1 -> 16 | B42: GENOVEVA | D42: 1 | K42: =SUM(C42:J42) -> 1 | L42: =IFERROR(((C42+D42)*$Q$3)+((E42+F42)*$Q$4)+((G42+H42)*$Q$5)+((I42+J42)*$Q$6),"-")+5.3 -> 54.3 | T42: =SUM(R42:S42) -> 0 | U42: =IFERROR($W$49/$T$46,"-") -> - | V42: =IFERROR(Q42+U42,"-") -> - | W42: =IFERROR(T42*V42,"-") -> -
A43: =A42+1 -> 17 | B43: RODRI AMIGO JACO | F43: 1 | K43: =SUM(C43:J43) -> 1 | L43: =IFERROR(((C43+D43)*$Q$3)+((E43+F43)*$Q$4)+((G43+H43)*$Q$5)+((I43+J43)*$Q$6),"-") -> 34 | T43: =SUM(R43:S43) -> 0 | U43: =IFERROR($W$49/$T$46,"-") -> - | V43: =IFERROR(Q43+U43,"-") -> - | W43: =IFERROR(T43*V43,"-") -> -
A44: =A43+1 -> 18 | B44: CASAPE | J44: 1 | K44: =SUM(C44:J44) -> 1 | L44: =IFERROR(((C44+D44)*$Q$3)+((E44+F44)*$Q$4)+((G44+H44)*$Q$5)+((I44+J44)*$Q$6),"-") -> 29 | T44: =SUM(R44:S44) -> 0 | V44: =IFERROR(Q44+U44,"-") -> 0 | W44: =IFERROR(T44*V44,"-") -> 0
A45: =A44+1 -> 19 | B45: MARIO MIRON | D45: 1 | K45: =SUM(C45:J45) -> 1 | L45: =IFERROR(((C45+D45)*$Q$3)+((E45+F45)*$Q$4)+((G45+H45)*$Q$5)+((I45+J45)*$Q$6),"-") -> 49 | T45: =SUM(R45:S45) -> 0 | V45: =IFERROR(Q45+U45,"-") -> 0 | W45: =IFERROR(T45*V45,"-") -> 0
A46: =A45+1 -> 20 | B46: CHIARRI | C46: 1 | K46: =SUM(C46:J46) -> 1 | L46: =IFERROR(((C46+D46)*$Q$12)+((E46+F46)*$Q$13)+((G46+H46)*$Q$14)+((I46+J46)*$Q$15),"-") -> 39 | P46: TOTAL | T46: =SUM(T40:T45) -> 0 | W46: =SUM(W40:W45) -> 0
A47: =A46+1 -> 21 | B47: CHORVO | E47: 1 | K47: =SUM(C47:J47) -> 1 | L47: =IFERROR(((C47+D47)*$Q$12)+((E47+F47)*$Q$13)+((G47+H47)*$Q$14)+((I47+J47)*$Q$15),"-") -> 27 | P47: Envio
A48: =A47+1 -> 22 | B48: ALVARO NISTAL | D48: 1 | K48: =SUM(C48:J48) -> 1 | L48: =IFERROR(((C48+D48)*$Q$12)+((E48+F48)*$Q$13)+((G48+H48)*$Q$14)+((I48+J48)*$Q$15),"-") -> 39 | P48: Otros gastos
A49: =A48+1 -> 23 | B49: VINTED | E49: 1 | F49: 1 | H49: 1 | K49: =SUM(C49:J49) -> 3 | L49: =IFERROR(((C49+D49)*$Q$12)+((E49+F49)*$Q$13)+((G49+H49)*$Q$14)+((I49+J49)*$Q$15),"-")-4 -> 73 | P49: TOTAL EXTRAS | W49: =SUM(W47:W48) -> 0
A50: =A49+1 -> 24 | B50: JAIME BUSTAMANTE | E50: 1 | F50: 1 | G50: 2 | K50: =SUM(C50:J50) -> 4 | L50: =IFERROR(((C50+D50)*$Q$12)+((E50+F50)*$Q$13)+((G50+H50)*$Q$14)+((I50+J50)*$Q$15),"-") -> 100 | P50: BLANKS TOTAL | W50: =-W46 -> 0
A51: =A50+1 -> 25 | B51: NICO RUIZ | E51: 1 | K51: =SUM(C51:J51) -> 1 | L51: =IFERROR(((C51+D51)*$Q$12)+((E51+F51)*$Q$13)+((G51+H51)*$Q$14)+((I51+J51)*$Q$15),"-")-2 -> 25 | W51: =Q40*T40+Q41*T41+Q42*T42+Q43*T43+Q44*T44+Q45*T45+W49+W50 -> 0
A52: =A51+1 -> 26 | B52: QUINTANA | F52: 1 | K52: =SUM(C52:J52) -> 1 | L52: =IFERROR(((C52+D52)*$Q$12)+((E52+F52)*$Q$13)+((G52+H52)*$Q$14)+((I52+J52)*$Q$15),"-")-2 -> 25 | P52: COSTE TOTAL BLANKS | W52: =W37+W50 -> 887.43
A53: =A52+1 -> 27 | B53: BARTA | E53: 1 | K53: =SUM(C53:J53) -> 1 | L53: =IFERROR(((C53+D53)*$Q$12)+((E53+F53)*$Q$13)+((G53+H53)*$Q$14)+((I53+J53)*$Q$15),"-")-2 -> 25
A54: =A53+1 -> 28 | K54: =SUM(C54:J54) -> 0 | L54: =IFERROR(((C54+D54)*$Q$12)+((E54+F54)*$Q$13)+((G54+H54)*$Q$14)+((I54+J54)*$Q$15),"-") -> 0 | P54: SERIGRAFIA | Q54: €/UND | R54: UNIDADES | S54: IVA | T54: € PER UND | U54: TOTAL
A55: =A54+1 -> 29 | K55: =SUM(C55:J55) -> 0 | L55: =IFERROR(((C55+D55)*$Q$12)+((E55+F55)*$Q$13)+((G55+H55)*$Q$14)+((I55+J55)*$Q$15),"-") -> 0 | P55: =$P$27 -> OJOS | Q55: 3 | R55: =T27 -> 14 | S55: =IFERROR(((Q55*R55)*0.21)/R55,"-") -> 0.63 | T55: =IFERROR(Q55+S55,"-") -> 3.63 | U55: =IFERROR(R55*T55,"-") -> 50.82
A56: =A55+1 -> 30 | K56: =SUM(C56:J56) -> 0 | L56: =IFERROR(((C56+D56)*$Q$12)+((E56+F56)*$Q$13)+((G56+H56)*$Q$14)+((I56+J56)*$Q$15),"-") -> 0 | P56: =$P$28 -> MIRILLA | Q56: 3 | R56: 34 | S56: =IFERROR(((Q56*R56)*0.21)/R56,"-") -> 0.63 | T56: =IFERROR(Q56+S56,"-") -> 3.63 | U56: =IFERROR(R56*T56,"-") -> 123.42
A57: =A56+1 -> 31 | K57: =SUM(C57:J57) -> 0 | L57: =IFERROR(((C57+D57)*$Q$12)+((E57+F57)*$Q$13)+((G57+H57)*$Q$14)+((I57+J57)*$Q$15),"-") -> 0 | P57: =$P$29 -> SEÑORA | Q57: 2.5 | R57: 11 | S57: =IFERROR(((Q57*R57)*0.21)/R57,"-") -> 0.525 | T57: =IFERROR(Q57+S57,"-") -> 3.025 | U57: =IFERROR(R57*T57,"-") -> 33.275
A58: =A57+1 -> 32 | K58: =SUM(C58:J58) -> 0 | L58: =IFERROR(((C58+D58)*$Q$12)+((E58+F58)*$Q$13)+((G58+H58)*$Q$14)+((I58+J58)*$Q$15),"-") -> 0 | P58: =$P$30 -> CALAVERA | Q58: 8 | R58: =T30 -> 4 | S58: =IFERROR(((Q58*R58)*0.21)/R58,"-") -> 1.68 | T58: =IFERROR(Q58+S58,"-") -> 9.68 | U58: =IFERROR(R58*T58,"-") -> 38.72
A59: =A58+1 -> 33 | K59: =SUM(C59:J59) -> 0 | L59: =IFERROR(((C59+D59)*$Q$12)+((E59+F59)*$Q$13)+((G59+H59)*$Q$14)+((I59+J59)*$Q$15),"-") -> 0 | S59: =IFERROR(((Q59*R59)*0.21)/R59,"-") -> - | T59: =IFERROR(Q59+S59,"-") -> - | U59: =IFERROR(R59*T59,"-") -> -
A60: =A59+1 -> 34 | K60: =SUM(C60:J60) -> 0 | L60: =IFERROR(((C60+D60)*$Q$12)+((E60+F60)*$Q$13)+((G60+H60)*$Q$14)+((I60+J60)*$Q$15),"-") -> 0 | S60: =IFERROR(((Q60*R60)*0.21)/R60,"-") -> - | T60: =IFERROR(Q60+S60,"-") -> - | U60: =IFERROR(R60*T60,"-") -> -
A61: =A60+1 -> 35 | K61: =SUM(C61:J61) -> 0 | L61: =IFERROR(((C61+D61)*$Q$12)+((E61+F61)*$Q$13)+((G61+H61)*$Q$14)+((I61+J61)*$Q$15),"-") -> 0 | P61: SERIGRAFIA TOTAL | R61: =SUM(R55:R60) -> 63 | U61: =SUM(U55:U60) -> 246.235
A65: 1 | B65: =B27 -> ANGEL AMIGO JACO | C65: =_xlfn.TEXTJOIN(", ",TRUE, IF(OR(C27>0,E27>0,G27>0,I27>0),"M",""), IF(OR(D27>0,F27>0,H27>0,J27>0),"L","") ) -> M, L | D65: =IF(C65="M",1,IF(C65="L",2,IF(C65="M, L",3))) -> 3 | E65: =K27 -> 2 | F65: =L27 -> 78 | G65: =$B$2 -> DROP 2
A66: 2 | B66: =B28 -> DIEGO AMIGO JACO | C66: =_xlfn.TEXTJOIN(", ",TRUE, IF(OR(C28>0,E28>0,G28>0,I28>0),"M",""), IF(OR(D28>0,F28>0,H28>0,J28>0),"L","") ) -> L | D66: =IF(C66="M",1,IF(C66="L",2,IF(C66="M, L",3))) -> 2 | E66: =K28 -> 2 | F66: =L28 -> 63 | G66: =$B$2 -> DROP 2
A67: 3 | B67: =B29 -> JUANMA | C67: =_xlfn.TEXTJOIN(", ",TRUE, IF(OR(C29>0,E29>0,G29>0,I29>0),"M",""), IF(OR(D29>0,F29>0,H29>0,J29>0),"L","") ) -> M | D67: =IF(C67="M",1,IF(C67="L",2,IF(C67="M, L",3))) -> 1 | E67: =K29 -> 1 | F67: =L29 -> 29 | G67: =$B$2 -> DROP 2
A68: =A67+1 -> 4 | B68: =B30 -> JUANTO | C68: =_xlfn.TEXTJOIN(", ",TRUE, IF(OR(C30>0,E30>0,G30>0,I30>0),"M",""), IF(OR(D30>0,F30>0,H30>0,J30>0),"L","") ) -> M | D68: =IF(C68="M",1,IF(C68="L",2,IF(C68="M, L",3))) -> 1 | E68: =K30 -> 2 | F68: =L30 -> 63 | G68: =$B$2 -> DROP 2
A69: =A68+1 -> 5 | B69: =B31 -> JORGE PUIG | C69: =_xlfn.TEXTJOIN(", ",TRUE, IF(OR(C31>0,E31>0,G31>0,I31>0),"M",""), IF(OR(D31>0,F31>0,H31>0,J31>0),"L","") ) -> M | D69: =IF(C69="M",1,IF(C69="L",2,IF(C69="M, L",3))) -> 1 | E69: =K31 -> 1 | F69: =L31 -> 49 | G69: =$B$2 -> DROP 2
A70: =A69+1 -> 6 | B70: =B32 -> NACHO PEREZ | C70: =_xlfn.TEXTJOIN(", ",TRUE, IF(OR(C32>0,E32>0,G32>0,I32>0),"M",""), IF(OR(D32>0,F32>0,H32>0,J32>0),"L","") ) -> L | D70: =IF(C70="M",1,IF(C70="L",2,IF(C70="M, L",3))) -> 2 | E70: =K32 -> 1 | F70: =L32 -> 34 | G70: =$B$2 -> DROP 2
A71: =A70+1 -> 7 | B71: =B33 -> PETER | C71: =_xlfn.TEXTJOIN(", ",TRUE, IF(OR(C33>0,E33>0,G33>0,I33>0),"M",""), IF(OR(D33>0,F33>0,H33>0,J33>0),"L","") ) -> M | D71: =IF(C71="M",1,IF(C71="L",2,IF(C71="M, L",3))) -> 1 | E71: =K33 -> 1 | F71: =L33 -> 34 | G71: =$B$2 -> DROP 2
A72: =A71+1 -> 8 | B72: =B34 -> BARALLOBRE | C72: =_xlfn.TEXTJOIN(", ",TRUE, IF(OR(C34>0,E34>0,G34>0,I34>0),"M",""), IF(OR(D34>0,F34>0,H34>0,J34>0),"L","") ) -> L | D72: =IF(C72="M",1,IF(C72="L",2,IF(C72="M, L",3))) -> 2 | E72: =K34 -> 1 | F72: =L34 -> 29 | G72: =$B$2 -> DROP 2
A73: =A72+1 -> 9 | B73: =B35 -> PUIG AMIGO JACO | C73: =_xlfn.TEXTJOIN(", ",TRUE, IF(OR(C35>0,E35>0,G35>0,I35>0),"M",""), IF(OR(D35>0,F35>0,H35>0,J35>0),"L","") ) -> M | D73: =IF(C73="M",1,IF(C73="L",2,IF(C73="M, L",3))) -> 1 | E73: =K35 -> 2 | F73: =L35 -> 78 | G73: =$B$2 -> DROP 2
A74: =A73+1 -> 10 | B74: =B36 -> FORMARIZ | C74: =_xlfn.TEXTJOIN(", ",TRUE, IF(OR(C36>0,E36>0,G36>0,I36>0),"M",""), IF(OR(D36>0,F36>0,H36>0,J36>0),"L","") ) -> M | D74: =IF(C74="M",1,IF(C74="L",2,IF(C74="M, L",3))) -> 1 | E74: =K36 -> 1 | F74: =L36 -> 49 | G74: =$B$2 -> DROP 2
A75: =A74+1 -> 11 | B75: =B37 -> DOMINGUEZ | C75: =_xlfn.TEXTJOIN(", ",TRUE, IF(OR(C37>0,E37>0,G37>0,I37>0),"M",""), IF(OR(D37>0,F37>0,H37>0,J37>0),"L","") ) -> L | D75: =IF(C75="M",1,IF(C75="L",2,IF(C75="M, L",3))) -> 2 | E75: =K37 -> 2 | F75: =L37 -> 63 | G75: =$B$2 -> DROP 2
A76: =A75+1 -> 12 | B76: =B38 -> IÑIGO | C76: =_xlfn.TEXTJOIN(", ",TRUE, IF(OR(C38>0,E38>0,G38>0,I38>0),"M",""), IF(OR(D38>0,F38>0,H38>0,J38>0),"L","") ) -> L | D76: =IF(C76="M",1,IF(C76="L",2,IF(C76="M, L",3))) -> 2 | E76: =K38 -> 1 | F76: =L38 -> 40 | G76: =$B$2 -> DROP 2
A77: =A76+1 -> 13 | B77: =B39 -> MUÑOZ | C77: L | D77: =IF(C77="M",1,IF(C77="L",2,IF(C77="M, L",3))) -> 2 | E77: =K39 -> 2 | F77: =L39 -> 78 | G77: =$B$2 -> DROP 2
A78: =A77+1 -> 14 | B78: =B40 -> TITO | C78: =_xlfn.TEXTJOIN(", ",TRUE, IF(OR(C40>0,E40>0,G40>0,I40>0),"M",""), IF(OR(D40>0,F40>0,H40>0,J40>0),"L","") ) -> L | D78: =IF(C78="M",1,IF(C78="L",2,IF(C78="M, L",3))) -> 2 | E78: =K40 -> 1 | F78: =L40 -> 45 | G78: =$B$2 -> DROP 2
A79: =A78+1 -> 15 | B79: =B41 -> CARLOTA DEL OLMO | C79: =_xlfn.TEXTJOIN(", ",TRUE, IF(OR(C41>0,E41>0,G41>0,I41>0),"M",""), IF(OR(D41>0,F41>0,H41>0,J41>0),"L","") ) -> L | D79: =IF(C79="M",1,IF(C79="L",2,IF(C79="M, L",3))) -> 2 | E79: =K41 -> 1 | F79: =L41 -> 52.7 | G79: =$B$2 -> DROP 2
A80: =A79+1 -> 16 | B80: =B42 -> GENOVEVA | C80: =_xlfn.TEXTJOIN(", ",TRUE, IF(OR(C42>0,E42>0,G42>0,I42>0),"M",""), IF(OR(D42>0,F42>0,H42>0,J42>0),"L","") ) -> L | D80: =IF(C80="M",1,IF(C80="L",2,IF(C80="M, L",3))) -> 2 | E80: =K42 -> 1 | F80: =L42 -> 54.3 | G80: =$B$2 -> DROP 2
A81: =A80+1 -> 17 | B81: =B43 -> RODRI AMIGO JACO | C81: =_xlfn.TEXTJOIN(", ",TRUE, IF(OR(C43>0,E43>0,G43>0,I43>0),"M",""), IF(OR(D43>0,F43>0,H43>0,J43>0),"L","") ) -> L | D81: =IF(C81="M",1,IF(C81="L",2,IF(C81="M, L",3))) -> 2 | E81: =K43 -> 1 | F81: =L43 -> 34 | G81: =$B$2 -> DROP 2
A82: =A81+1 -> 18 | B82: =B44 -> CASAPE | C82: =_xlfn.TEXTJOIN(", ",TRUE, IF(OR(C44>0,E44>0,G44>0,I44>0),"M",""), IF(OR(D44>0,F44>0,H44>0,J44>0),"L","") ) -> L | D82: =IF(C82="M",1,IF(C82="L",2,IF(C82="M, L",3))) -> 2 | E82: =K44 -> 1 | F82: =L44 -> 29 | G82: =$B$2 -> DROP 2
A83: =A82+1 -> 19 | B83: =B45 -> MARIO MIRON | C83: =_xlfn.TEXTJOIN(", ",TRUE, IF(OR(C45>0,E45>0,G45>0,I45>0),"M",""), IF(OR(D45>0,F45>0,H45>0,J45>0),"L","") ) -> L | D83: =IF(C83="M",1,IF(C83="L",2,IF(C83="M, L",3))) -> 2 | E83: =K45 -> 1 | F83: =L45 -> 49 | G83: =$B$2 -> DROP 2
A84: =A83+1 -> 20 | B84: =B46 -> CHIARRI | C84: =_xlfn.TEXTJOIN(", ",TRUE, IF(OR(C46>0,E46>0,G46>0,I46>0),"M",""), IF(OR(D46>0,F46>0,H46>0,J46>0),"L","") ) -> M | D84: =IF(C84="M",1,IF(C84="L",2,IF(C84="M, L",3))) -> 1 | E84: =K46 -> 1 | F84: =L46 -> 39 | G84: =$B$2 -> DROP 2
A85: =A84+1 -> 21 | B85: =B47 -> CHORVO | C85: =_xlfn.TEXTJOIN(", ",TRUE, IF(OR(C47>0,E47>0,G47>0,I47>0),"M",""), IF(OR(D47>0,F47>0,H47>0,J47>0),"L","") ) -> M | D85: =IF(C85="M",1,IF(C85="L",2,IF(C85="M, L",3))) -> 1 | E85: =K47 -> 1 | F85: =L47 -> 27 | G85: =$B$2 -> DROP 2
A86: =A85+1 -> 22 | B86: =B48 -> ALVARO NISTAL | C86: =_xlfn.TEXTJOIN(", ",TRUE, IF(OR(C48>0,E48>0,G48>0,I48>0),"M",""), IF(OR(D48>0,F48>0,H48>0,J48>0),"L","") ) -> L | D86: =IF(C86="M",1,IF(C86="L",2,IF(C86="M, L",3))) -> 2 | E86: =K48 -> 1 | F86: =L48 -> 39 | G86: =$B$2 -> DROP 2
A87: =A86+1 -> 23 | B87: =B49 -> VINTED | C87: =_xlfn.TEXTJOIN(", ",TRUE, IF(OR(C49>0,E49>0,G49>0,I49>0),"M",""), IF(OR(D49>0,F49>0,H49>0,J49>0),"L","") ) -> M, L | D87: =IF(C87="M",1,IF(C87="L",2,IF(C87="M, L",3))) -> 3 | E87: =K49 -> 3 | F87: =L49 -> 73 | G87: =$B$2 -> DROP 2
A88: =A87+1 -> 24 | B88: =B50 -> JAIME BUSTAMANTE | C88: =_xlfn.TEXTJOIN(", ",TRUE, IF(OR(C50>0,E50>0,G50>0,I50>0),"M",""), IF(OR(D50>0,F50>0,H50>0,J50>0),"L","") ) -> M, L | D88: =IF(C88="M",1,IF(C88="L",2,IF(C88="M, L",3))) -> 3 | E88: =K50 -> 4 | F88: =L50 -> 100 | G88: =$B$2 -> DROP 2
A89: =A88+1 -> 25 | B89: =B51 -> NICO RUIZ | C89: =_xlfn.TEXTJOIN(", ",TRUE, IF(OR(C51>0,E51>0,G51>0,I51>0),"M",""), IF(OR(D51>0,F51>0,H51>0,J51>0),"L","") ) -> M | D89: =IF(C89="M",1,IF(C89="L",2,IF(C89="M, L",3))) -> 1 | E89: =K51 -> 1 | F89: =L51 -> 25 | G89: =$B$2 -> DROP 2
... A99: =A98+1 -> 35 | B99: =B61 -> 0 | C99: =_xlfn.TEXTJOIN(", ",TRUE, IF(OR(C61>0,E61>0,G61>0,I61>0),"M",""), IF(OR(D61>0,F61>0,H61>0,J61>0),"L","") ) | D99: =IF(C99="M",1,IF(C99="L",2,IF(C99="M, L",3))) -> FALSE | E99: =K61 -> 0 | F99: =L61 -> 0 | G99: =$B$2 -> DROP 2

Sheet  2
G3: HOODIES | R3: TEES | AC3: CREWNECK | AL3: TOTAL RUE PORTER $ | AO3: TOTAL RUE PORTER € | AR3: ENVIO | AU3: TOTAL | AX3: CANTIDAD | BA3: FECHA | BD3: COBRO | BI3: INGRESOS | BN3: =BF56 -> 1412
G5: PRICE $ | H5: PRICE € | I5: M | J5: L | K5: UNITS | L5: TOTAL $ | M5: TOTAL € | R5: PRICE $ | S5: PRICE € | T5: M | U5: L | V5: UNITS | W5: TOTAL $ | X5: TOTAL € | AC5: PRICE $ | AD5: PRICE € | AE5: M | AF5: L | AG5: UNITS | AH5: TOTAL $ | AI5: TOTAL € | BV5: =BC48 -> 5 | BW5: =BD48 -> 7 | BX5: =BC50 -> 7 | BY5: =BD50 -> 7 | BZ5: =BC52 -> 4 | CA5: =BD52 -> 4 | CB5: =BC54 -> 2 | CC5: =BD54 -> 2 | CD5: =SUM(BV5:CC6) -> 38
AL6: =L37+W37+AH37+L75+W75+AH75 -> 885.95 | AO6: =M37+X37+AI37+M75+X75+AI75 -> 695.1 | AR6: 150 | AU6: =AL6+AR6 -> 1035.95 | AX6: =K37+V37+AG37+K75+V75+AG75 -> 49 | BA6: 44497 | BD6: 887.43 | BI6: RUE PORTER | BN6: =BD6 -> 887.43
D7: BLACK | G7: 32.95 | H7: 25.8 | K7: =I7+J7 -> 0 | L7: =G7*K7 -> 0 | M7: =H7*K7 -> 0 | O7: BLACK | R7: 9.95 | S7: 8.01 | V7: =T7+U7 -> 0 | W7: =R7*V7 -> 0 | X7: =S7*V7 -> 0 | Z7: BLACK | AG7: =AE7+AF7 -> 0 | AH7: =AC7*AG7 -> 0 | AI7: =AD7*AG7 -> 0 | BV7: M | BW7: L | BX7: M | BY7: L | BZ7: M | CA7: L | CB7: M | CC7: L | CD7: UNITS | CE7: TOTAL € | CF7: PAYMENT | CI7: CASH | CJ7: CREDIT | CK7: COBRO | CM7: FECHA
BI8: SERIGRAFIA | BN8: =AT24 -> 246.235
D9: VINTAGE BLACK | G9: 34.5 | H9: 27.5 | I9: 7 | J9: 7 | K9: =I9+J9 -> 14 | L9: =G9*K9 -> 483 | M9: =H9*K9 -> 385 | O9: VINTAGE BLACK | R9: 11.45 | S9: 9.2 | T9: 14 | U9: 7 | V9: =T9+U9 -> 21 | W9: =R9*V9 -> 240.45 | X9: =S9*V9 -> 193.2 | Z9: VINTAGE BLACK | AG9: =AE9+AF9 -> 0 | AH9: =AC9*AG9 -> 0 | AI9: =AD9*AG9 -> 0 | BR9: ANGEL | BV9: 0 | BW9: 1 | BX9: 0 | BY9: 0 | BZ9: 1 | CA9: 0 | CB9: 0 | CC9: 0 | CD9: =SUM(BV9:CC10) -> 2 | CE9: =BV9*49+BW9*49+BX9*34+BY9*34+BZ9*29+CA9*29+CB9*29+CC9*29 -> 78 | CF9: 78€ EFECTIVO | CI9: 78 | CK9: REVOLUT
BI10: ETIQUETAS | BN10: 49.01
D11: GARMENT DYED | K11: =I11+J11 -> 0 | L11: =G11*K11 -> 0 | M11: =H11*K11 -> 0 | O11: GARMENT DYED | V11: =T11+U11 -> 0 | W11: =R11*V11 -> 0 | X11: =S11*V11 -> 0 | Z11: GARMENT DYED | AG11: =AE11+AF11 -> 0 | AH11: =AC11*AG11 -> 0 | AI11: =AD11*AG11 -> 0 | BR11: DIEGO | BV11: 0 | BW11: 0 | BX11: 0 | BY11: 1 | BZ11: 0 | CA11: 1 | CB11: 0 | CC11: 0 | CD11: =SUM(BV11:CC12) -> 2 | CE11: =BV11*49+BW11*49+BX11*34+BY11*34+BZ11*29+CA11*29+CB11*29+CC11*29 -> 63 | CF11: 63€ EFECTIVO | CI11: 63 | CK11: REVOLUT
AL12: SERIGRAFIA | BI12: BOLSAS | BN12: 12.69
D13: HEATHER GREY | G13: 32.95 | H13: 25.8 | K13: =I13+J13 -> 0 | L13: =G13*K13 -> 0 | M13: =H13*K13 -> 0 | O13: HEATHER GREY | R13: 9.95 | S13: 8.01 | V13: =T13+U13 -> 0 | W13: =R13*V13 -> 0 | X13: =S13*V13 -> 0 | Z13: HEATHER GREY | AG13: =AE13+AF13 -> 0 | AH13: =AC13*AG13 -> 0 | AI13: =AD13*AG13 -> 0 | BR13: JUANMA | BV13: 0 | BW13: 0 | BX13: 0 | BY13: 0 | BZ13: 0 | CA13: 0 | CB13: 1 | CC13: 0 | CD13: =SUM(BV13:CC14) -> 1 | CE13: =BV13*49+BW13*49+BX13*34+BY13*34+BZ13*29+CA13*29+CB13*29+CC13*29 -> 29 | CF13: 29€ EFECTIVO | CI13: 29 | CK13: REVOLUT
AP14: PRICE € | AQ14: UNITS | AR14: IVA | AS14: PER UNIT | AT14: TOTAL € | BB14: PRICE | BC14: M | BD14: L | BE14: UNITS | BF14: TOTAL € | BI14: PEGATINAS | BN14: 26.33
D15: WHITE | G15: 32.95 | H15: 25.8 | K15: =I15+J15 -> 0 | L15: =G15*K15 -> 0 | M15: =H15*K15 -> 0 | O15: WHITE | R15: 9.95 | S15: 8.01 | T15: 6 | U15: 4 | V15: =T15+U15 -> 10 | W15: =R15*V15 -> 99.5 | X15: =S15*V15 -> 80.1 | Z15: WHITE | AG15: =AE15+AF15 -> 0 | AH15: =AC15*AG15 -> 0 | AI15: =AD15*AG15 -> 0 | BR15: JUANTO | BV15: 0 | BW15: 0 | BX15: 1 | BY15: 0 | BZ15: 1 | CA15: 0 | CB15: 0 | CC15: 0 | CD15: =SUM(BV15:CC16) -> 2 | CE15: =BV15*49+BW15*49+BX15*34+BY15*34+BZ15*29+CA15*29+CB15*29+CC15*29 -> 63 | CF15: 63€ TARJETA | CJ15: 63 | CK15: REVOLUT
AM16: OJOS | AP16: 3 | AQ16: =K9 -> 14 | AR16: =((AP16*AQ16)*0.21)/AQ16 -> 0.63 | AS16: =AP16+AR16 -> 3.63 | AT16: =AQ16*AS16 -> 50.82 | AY16: OJOS | BB16: =AP48 -> 49 | BC16: =I9 -> 7 | BD16: =J9 -> 7 | BE16: =BC16+BD16 -> 14 | BF16: =BB16*BE16 -> 686 | BI16: PUBLICIDAD | BN16: 40
D17: VINTAGE BROWN | G17: 34.5 | H17: 27.5 | K17: =I17+J17 -> 0 | L17: =G17*K17 -> 0 | M17: =H17*K17 -> 0 | O17: VINTAGE BROWN | R17: 15.75 | S17: 9.2 | T17: 2 | U17: 2 | V17: =T17+U17 -> 4 | W17: =R17*V17 -> 63 | X17: =S17*V17 -> 36.8 | Z17: VINTAGE BROWN | AG17: =AE17+AF17 -> 0 | AH17: =AC17*AG17 -> 0 | AI17: =AD17*AG17 -> 0 | BR17: JORGE PUIG | BV17: 1 | BW17: 0 | BX17: 0 | BY17: 0 | BZ17: 0 | CA17: 0 | CB17: 0 | CC17: 0 | CD17: =SUM(BV17:CC18) -> 1 | CE17: =BV17*49+BW17*49+BX17*34+BY17*34+BZ17*29+CA17*29+CB17*29+CC17*29 -> 49 | CF17: 49€ TARJETA | CJ17: 49 | CK17: REVOLUT
AM18: MIRILLA | AP18: 3 | AQ18: 34 | AR18: =((AP18*AQ18)*0.21)/AQ18 -> 0.63 | AS18: =AP18+AR18 -> 3.63 | AT18: =AQ18*AS18 -> 123.42 | AY18: MIRILLA | BB18: =AP50 -> 34 | BC18: =T9-4 -> 10 | BD18: =U9 -> 7 | BE18: =BC18+BD18 -> 17 | BF18: =BB18*BE18 -> 578 | BI18: COSTE TOTAL | BN18: =SUM(BN6:BO17) -> 1261.695
D19: CAMEL | K19: =I19+J19 -> 0 | L19: =G19*K19 -> 0 | M19: =H19*K19 -> 0 | O19: CAMEL | V19: =T19+U19 -> 0 | W19: =R19*V19 -> 0 | X19: =S19*V19 -> 0 | Z19: CAMEL | AG19: =AE19+AF19 -> 0 | AH19: =AC19*AG19 -> 0 | AI19: =AD19*AG19 -> 0 | BR19: NACHO | BV19: 0 | BW19: 0 | BX19: 0 | BY19: 1 | BZ19: 0 | CA19: 0 | CB19: 0 | CC19: 0 | CD19: =SUM(BV19:CC20) -> 1 | CE19: =BV19*49+BW19*49+BX19*34+BY19*34+BZ19*29+CA19*29+CB19*29+CC19*29 -> 34 | CF19: 34€ EFECTIVO | CI19: 34 | CK19: REVOLUT
AM20: SEÑORA | AP20: 2.5 | AQ20: =V15+1 -> 11 | AR20: =((AP20*AQ20)*0.21)/AQ20 -> 0.525 | AS20: =AP20+AR20 -> 3.025 | AT20: =AQ20*AS20 -> 33.275 | AY20: SEÑORA | BB20: =AP52 -> 29 | BC20: =T15 -> 6 | BD20: =U15 -> 4 | BE20: =BC20+BD20 -> 10 | BF20: =BB20*BE20 -> 290
D21: KHAKI | K21: =I21+J21 -> 0 | L21: =G21*K21 -> 0 | M21: =H21*K21 -> 0 | O21: KHAKI | V21: =T21+U21 -> 0 | W21: =R21*V21 -> 0 | X21: =S21*V21 -> 0 | Z21: KHAKI | AG21: =AE21+AF21 -> 0 | AH21: =AC21*AG21 -> 0 | AI21: =AD21*AG21 -> 0 | BI21: TOTAL FINAL | BN21: =BN3-BN18 -> 150.305 | BR21: PETER | BV21: 0 | BW21: 0 | BX21: 1 | BY21: 0 | BZ21: 0 | CA21: 0 | CB21: 0 | CC21: 0 | CD21: =SUM(BV21:CC22) -> 1 | CE21: =BV21*49+BW21*49+BX21*34+BY21*34+BZ21*29+CA21*29+CB21*29+CC21*29 -> 34 | CF21: 34€ TARJETA | CJ21: 34 | CK21: REVOLUT
AM22: CALAVERA | AP22: 8 | AQ22: =V17 -> 4 | AR22: =((AP22*AQ22)*0.21)/AQ22 -> 1.68 | AS22: =AP22+AR22 -> 9.68 | AT22: =AQ22*AS22 -> 38.72 | AY22: CALAVERA | BB22: =AP54 -> 29 | BC22: =T17 -> 2 | BD22: =U17 -> 2 | BE22: =BC22+BD22 -> 4 | BF22: =BB22*BE22 -> 116
D23: SAND | G23: 32.95 | H23: 25.8 | K23: =I23+J23 -> 0 | L23: =G23*K23 -> 0 | M23: =H23*K23 -> 0 | O23: SAND | R23: 9.95 | S23: 8.01 | V23: =T23+U23 -> 0 | W23: =R23*V23 -> 0 | X23: =S23*V23 -> 0 | Z23: SAND | AG23: =AE23+AF23 -> 0 | AH23: =AC23*AG23 -> 0 | AI23: =AD23*AG23 -> 0 | BR23: BARALLOBRE | BV23: 0 | BW23: 0 | BX23: 0 | BY23: 0 | BZ23: 0 | CA23: 1 | CB23: 0 | CC23: 0 | CD23: =SUM(BV23:CC24) -> 1 | CE23: =BV23*49+BW23*49+BX23*34+BY23*34+BZ23*29+CA23*29+CB23*29+CC23*29 -> 29 | CF23: 29€ TARJETA | CJ23: 29 | CK23: REVOLUT
AQ24: =SUM(AQ16:AQ23) -> 63 | AR24: =SUM(AR16:AR23) -> 3.465 | AT24: =SUM(AT16:AT23) -> 246.235 | BE24: =SUM(BE16:BE23) -> 45 | BF24: =SUM(BF16:BF23) -> 1670
D25: CREAM | G25: 32.95 | H25: 25.8 | K25: =I25+J25 -> 0 | L25: =G25*K25 -> 0 | M25: =H25*K25 -> 0 | O25: CREAM | R25: 9.95 | S25: 8.01 | V25: =T25+U25 -> 0 | W25: =R25*V25 -> 0 | X25: =S25*V25 -> 0 | Z25: CREAM | AG25: =AE25+AF25 -> 0 | AH25: =AC25*AG25 -> 0 | AI25: =AD25*AG25 -> 0 | BR25: PUIG | BV25: 1 | BW25: 0 | BX25: 0 | BY25: 0 | BZ25: 0 | CA25: 0 | CB25: 1 | CC25: 0 | CD25: =SUM(BV25:CC26) -> 2 | CE25: =BV25*49+BW25*49+BX25*34+BY25*34+BZ25*29+CA25*29+CB25*29+CC25*29 -> 78 | CF25: 78€ TARJETA | CJ25: 78 | CK25: REVOLUT | CM25: 44517
D27: PINK DUST | G27: 32.95 | H27: 25.8 | K27: =I27+J27 -> 0 | L27: =G27*K27 -> 0 | M27: =H27*K27 -> 0 | O27: PINK DUST | R27: 9.95 | S27: 8.01 | V27: =T27+U27 -> 0 | W27: =R27*V27 -> 0 | X27: =S27*V27 -> 0 | Z27: PINK DUST | AG27: =AE27+AF27 -> 0 | AH27: =AC27*AG27 -> 0 | AI27: =AD27*AG27 -> 0 | BR27: FORMARIZ | BV27: 1 | BW27: 0 | BX27: 0 | BY27: 0 | BZ27: 0 | CA27: 0 | CB27: 0 | CC27: 0 | CD27: =SUM(BV27:CC28) -> 1 | CE27: =BV27*49+BW27*49+BX27*34+BY27*34+BZ27*29+CA27*29+CB27*29+CC27*29 -> 49 | CF27: 49€ TARJETA | CJ27: 49 | CK27: REVOLUT | CM27: 44536
AL28: COST PER UNIT | AX28: GON Y JACO
D29: PASTEL BLUE | K29: =I29+J29 -> 0 | L29: =G29*K29 -> 0 | M29: =H29*K29 -> 0 | O29: PASTEL BLUE | V29: =T29+U29 -> 0 | W29: =R29*V29 -> 0 | X29: =S29*V29 -> 0 | Z29: PASTEL BLUE | AG29: =AE29+AF29 -> 0 | AH29: =AC29*AG29 -> 0 | AI29: =AD29*AG29 -> 0 | BR29: DOMINGUEZ | BV29: 0 | BW29: 0 | BX29: 0 | BY29: 1 | BZ29: 0 | CA29: 1 | CB29: 0 | CC29: 0 | CD29: =SUM(BV29:CC30) -> 2 | CE29: =BV29*49+BW29*49+BX29*34+BY29*34+BZ29*29+CA29*29+CB29*29+CC29*29 -> 63 | CF29: 63€ TARJETA | CJ29: 63 | CK29: REVOLUT | CM29: 44514
AP30: BLANK | AQ30: SERIGRAFIA | AR30: EXTRA | AS30: TOTAL € | BB30: M | BC30: L | BD30: UNITS | BE30: COST | BF30: TOTAL €
D31: SAGE PURPLE | G31: 32.95 | H31: 25.8 | K31: =I31+J31 -> 0 | L31: =G31*K31 -> 0 | M31: =H31*K31 -> 0 | O31: SAGE PURPLE | R31: 9.95 | S31: 8.01 | V31: =T31+U31 -> 0 | W31: =R31*V31 -> 0 | X31: =S31*V31 -> 0 | Z31: SAGE PURPLE | AG31: =AE31+AF31 -> 0 | AH31: =AC31*AG31 -> 0 | AI31: =AD31*AG31 -> 0 | BR31: IÑIGO | BV31: 0 | BW31: 1 | BX31: 0 | BY31: 0 | BZ31: 0 | CA31: 0 | CB31: 0 | CC31: 0 | CD31: =SUM(BV31:CC32) -> 1 | CE31: =BV31*49+BW31*49+BX31*34+BY31*34+BZ31*29+CA31*29+CB31*29+CC31*29 -> 49 | CF31: 40€ TARJETA | CJ31: 40 | CK31: REVOLUT | CM31: 44658
AM32: OJOS | AQ32: =AS16 -> 3.63 | AS32: =SUM(AP32:AR33) -> 3.63 | AY32: OJOS | BB32: 2 | BC32: 0 | BD32: =BB32+BC32 -> 2 | BE32: =AS32 -> 3.63 | BF32: =BE32*BD32 -> 7.26
D33: ORANGE | K33: =I33+J33 -> 0 | L33: =G33*K33 -> 0 | M33: =H33*K33 -> 0 | O33: ORANGE | R33: 9.95 | S33: 8.01 | V33: =T33+U33 -> 0 | W33: =R33*V33 -> 0 | X33: =S33*V33 -> 0 | Z33: ORANGE | AG33: =AE33+AF33 -> 0 | AH33: =AC33*AG33 -> 0 | AI33: =AD33*AG33 -> 0 | BR33: MUÑOZ | BV33: 0 | BW33: 0 | BX33: 0 | BY33: 0 | BZ33: 0 | CA33: 0 | CB33: 0 | CC33: 1 | CD33: =SUM(BV33:CC34) -> 1 | CE33: =BV33*49+BW33*49+BX33*34+BY33*34+BZ33*29+CA33*29+CB33*29+CC33*29 -> 29 | CF33: 29€ TARJETA | CJ33: 29 | CK33: REVOLUT | CM33: 44540
AM34: MIRILLA | AQ34: =AS18 -> 3.63 | AS34: =SUM(AP34:AR35) -> 3.63 | AY34: MIRILLA | BB34: 3 | BC34: 0 | BD34: =BB34+BC34 -> 3 | BE34: =AS34 -> 3.63 | BF34: =BE34*BD34 -> 10.89
D35: FOREST GREEN | G35: 32.95 | H35: 25.8 | K35: =I35+J35 -> 0 | L35: =G35*K35 -> 0 | M35: =H35*K35 -> 0 | O35: GREEN | R35: 9.95 | S35: 8.01 | V35: =T35+U35 -> 0 | W35: =R35*V35 -> 0 | X35: =S35*V35 -> 0 | Z35: FOREST GREEN | AG35: =AE35+AF35 -> 0 | AH35: =AC35*AG35 -> 0 | AI35: =AD35*AG35 -> 0 | BR35: TITO | BV35: 0 | BW35: 1 | BX35: 0 | BY35: 0 | BZ35: 0 | CA35: 0 | CB35: 0 | CC35: 0 | CD35: =SUM(BV35:CC36) -> 1 | CE35: =BV35*49+BW35*49+BX35*34+BY35*34+BZ35*29+CA35*29+CB35*29+CC35*29 -> 49 | CF35: 49€ TARJETA | CJ35: 45 | CK35: REVOLUT | CM35: 44549
AM36: SEÑORA | AQ36: =AS20 -> 3.025 | AS36: =SUM(AP36:AR37) -> 3.025 | AY36: SEÑORA | BB36: 2 | BC36: 0 | BD36: =BB36+BC36 -> 2 | BE36: =AS36 -> 3.025 | BF36: =BE36*BD36 -> 6.05
I37: =SUM(I7:I36) -> 7 | J37: =SUM(J7:J36) -> 7 | K37: =SUM(K7:K36) -> 14 | L37: =SUM(L7:L36) -> 483 | M37: =SUM(M7:M36) -> 385 | T37: =SUM(T7:T36) -> 22 | U37: =SUM(U7:U36) -> 13 | V37: =SUM(V7:V36) -> 35 | W37: =SUM(W7:W36) -> 402.95 | X37: =SUM(X7:X36) -> 310.1 | AE37: =SUM(AE7:AE36) -> 0 | AF37: =SUM(AF7:AF36) -> 0 | AG37: =SUM(AG7:AG36) -> 0 | AH37: =SUM(AH7:AH36) -> 0 | AI37: =SUM(AI7:AI36) -> 0 | BR37: CARLOTA DEL OLMO | BV37: 0 | BW37: 1 | BX37: 0 | BY37: 0 | BZ37: 0 | CA37: 0 | CB37: 0 | CC37: 0 | CD37: =SUM(BV37:CC38) -> 1 | CE37: =BV37*49+BW37*49+BX37*34+BY37*34+BZ37*29+CA37*29+CB37*29+CC37*29 -> 49 | CF37: 52,7€ STRIPE | CJ37: 52.7 | CK37: REVOLUT | CM37: 44537
AM38: CALAVERA | AQ38: =AS22 -> 9.68 | AS38: =SUM(AP38:AR39) -> 9.68 | AY38: CALAVERA | BB38: 0 | BC38: 0 | BD38: =BB38+BC38 -> 0 | BE38: =AS38 -> 9.68 | BF38: =BE38*BD38 -> 0
BR39: GENOVEVA | BV39: 0 | BW39: 1 | BX39: 0 | BY39: 0 | BZ39: 0 | CA39: 0 | CB39: 0 | CC39: 0 | CD39: =SUM(BV39:CC40) -> 1 | CE39: =BV39*49+BW39*49+BX39*34+BY39*34+BZ39*29+CA39*29+CB39*29+CC39*29 -> 49 | CF39: 54,3€ STRIPE | CJ39: 54.3 | CK39: REVOLUT | CM39: 44545
BD40: =SUM(BD32:BD39) -> 7 | BF40: =SUM(BF32:BF39) -> 24.2
G41: LONGSLEEVE | R41: SWEATPANTS | AC41: SHORT SWEATPANTS | BR41: AMIGO MUÑOZ | BV41: 1 | BW41: 0 | BX41: 0 | BY41: 0 | BZ41: 0 | CA41: 0 | CB41: 0 | CC41: 0 | CD41: =SUM(BV41:CC42) -> 1 | CE41: =BV41*49+BW41*49+BX41*34+BY41*34+BZ41*29+CA41*29+CB41*29+CC41*29 -> 49 | CF41: 49€ TARJETA | CJ41: 49 | CK41: REVOLUT | CM41: 44561
G43: PRICE $ | H43: PRICE € | I43: M | J43: L | K43: UNITS | L43: TOTAL $ | M43: TOTAL € | R43: PRICE $ | S43: PRICE € | T43: M | U43: L | V43: UNITS | W43: TOTAL $ | X43: TOTAL € | AC43: PRICE $ | AD43: PRICE € | AE43: M | AF43: L | AG43: UNITS | AH43: TOTAL $ | AI43: TOTAL € | BR43: RODRI | BV43: 0 | BW43: 0 | BX43: 0 | BY43: 1 | BZ43: 0 | CA43: 0 | CB43: 0 | CC43: 0 | CD43: =SUM(BV43:CC44) -> 1 | CE43: =BV43*49+BW43*49+BX43*34+BY43*34+BZ43*29+CA43*29+CB43*29+CC43*29 -> 34 | CF43: 34€ TARJETA | CJ43: 34 | CK43: REVOLUT | CM43: 44549
AL44: PROFFIT PER UNIT
D45: BLACK | K45: =I45+J45 -> 0 | L45: =G45*K45 -> 0 | M45: =H45*K45 -> 0 | O45: BLACK | V45: =T45+U45 -> 0 | W45: =R45*V45 -> 0 | X45: =S45*V45 -> 0 | Z45: BLACK | AG45: =AE45+AF45 -> 0 | AH45: =AC45*AG45 -> 0 | AI45: =AD45*AG45 -> 0 | BR45: CASAPE | BV45: 0 | BW45: 0 | BX45: 0 | BY45: 0 | BZ45: 0 | CA45: 0 | CB45: 0 | CC45: 1 | CD45: =SUM(BV45:CC46) -> 1 | CE45: =BV45*49+BW45*49+BX45*34+BY45*34+BZ45*29+CA45*29+CB45*29+CC45*29 -> 29 | CF45: 29€ TARJETA | CJ45: 29 | CK45: REVOLUT | CM45: 44783
AP46: SALE | AQ46: COST | AR46: PROFIT | AS46: P.MARGIN | BB46: PRICE | BC46: M | BD46: L | BE46: UNITS | BF46: TOTAL €
D47: VINTAGE BLACK | K47: =I47+J47 -> 0 | L47: =G47*K47 -> 0 | M47: =H47*K47 -> 0 | O47: VINTAGE BLACK | V47: =T47+U47 -> 0 | W47: =R47*V47 -> 0 | X47: =S47*V47 -> 0 | Z47: VINTAGE BLACK | AG47: =AE47+AF47 -> 0 | AH47: =AC47*AG47 -> 0 | AI47: =AD47*AG47 -> 0 | BR47: MIRON | BV47: 0 | BW47: 1 | BX47: 0 | BY47: 0 | BZ47: 0 | CA47: 0 | CB47: 0 | CC47: 0 | CD47: =SUM(BV47:CC48) -> 1 | CE47: =BV47*49+BW47*49+BX47*34+BY47*34+BZ47*29+CA47*29+CB47*29+CC47*29 -> 49 | CF47: 49€ TARJETA | CJ47: 49 | CK47: REVOLUT | CM47: 44551
AM48: OJOS | AP48: 49 | AQ48: =AS32 -> 3.63 | AR48: =AP48-AQ48 -> 45.37 | AS48: =(AP48-AQ48)/AQ48 -> 12.498623 | AY48: OJOS | BB48: =AP48 -> 49 | BC48: =BC16-BB32 -> 5 | BD48: =BD16-BC32 -> 7 | BE48: =BC48+BD48 -> 12 | BF48: =BB48*BE48 -> 588
D49: GARMENT DYED | K49: =I49+J49 -> 0 | L49: =G49*K49 -> 0 | M49: =H49*K49 -> 0 | O49: GARMENT DYED | V49: =T49+U49 -> 0 | W49: =R49*V49 -> 0 | X49: =S49*V49 -> 0 | Z49: GARMENT DYED | AG49: =AE49+AF49 -> 0 | AH49: =AC49*AG49 -> 0 | AI49: =AD49*AG49 -> 0 | BR49: CHIARRI | BV49: 1 | BW49: 0 | BX49: 0 | BY49: 0 | BZ49: 0 | CA49: 0 | CB49: 0 | CC49: 0 | CD49: =SUM(BV49:CC50) -> 1 | CE49: =BV49*39+BW49*39+BX49*27+BY49*27+BZ49*23+CA49*23+CB49*23+CC49*23 -> 39 | CF49: 39€ TARJETA | CJ49: 39 | CK49: REVOLUT | CM49: 44557
AM50: MIRILLA | AP50: 34 | AQ50: =AS34 -> 3.63 | AR50: =AP50-AQ50 -> 30.37 | AS50: =(AP50-AQ50)/AQ50 -> 8.3663912 | AY50: MIRILLA | BB50: =AP50 -> 34 | BC50: =BC18-BB34 -> 7 | BD50: =BD18-BC34 -> 7 | BE50: =BC50+BD50 -> 14 | BF50: =BB50*BE50 -> 476
D51: HEATHER GREY | K51: =I51+J51 -> 0 | L51: =G51*K51 -> 0 | M51: =H51*K51 -> 0 | O51: HEATHER GREY | V51: =T51+U51 -> 0 | W51: =R51*V51 -> 0 | X51: =S51*V51 -> 0 | Z51: HEATHER GREY | AG51: =AE51+AF51 -> 0 | AH51: =AC51*AG51 -> 0 | AI51: =AD51*AG51 -> 0 | BR51: CHORVO | BV51: 0 | BW51: 0 | BX51: 1 | BY51: 0 | BZ51: 0 | CA51: 0 | CB51: 0 | CC51: 0 | CD51: =SUM(BV51:CC52) -> 1 | CE51: =BV51*39+BW51*39+BX51*27+BY51*27+BZ51*23+CA51*23+CB51*23+CC51*23 -> 27 | CF51: 27€ TARJETA | CJ51: 27 | CK51: REVOLUT | CM51: 44783
AM52: SEÑORA | AP52: 29 | AQ52: =AS36 -> 3.025 | AR52: =AP52-AQ52 -> 25.975 | AS52: =(AP52-AQ52)/AQ52 -> 8.5867769 | AY52: SEÑORA | BB52: =AP52 -> 29 | BC52: =BC20-BB36 -> 4 | BD52: =BD20-BC36 -> 4 | BE52: =BC52+BD52 -> 8 | BF52: =BB52*BE52 -> 232
D53: WHITE | K53: =I53+J53 -> 0 | L53: =G53*K53 -> 0 | M53: =H53*K53 -> 0 | O53: WHITE | V53: =T53+U53 -> 0 | W53: =R53*V53 -> 0 | X53: =S53*V53 -> 0 | Z53: WHITE | AG53: =AE53+AF53 -> 0 | AH53: =AC53*AG53 -> 0 | AI53: =AD53*AG53 -> 0 | BR53: ALVARO (@alvaroonistal) | BV53: 0 | BW53: 1 | BX53: 0 | BY53: 0 | BZ53: 0 | CA53: 0 | CB53: 0 | CC53: 0 | CD53: =SUM(BV53:CC54) -> 1 | CE53: =BV53*39+BW53*39+BX53*27+BY53*27+BZ53*23+CA53*23+CB53*23+CC53*23 -> 39 | CF53: 39€ TARJETA | CJ53: 39 | CK53: REVOLUT | CM53: 44550
AM54: CALAVERA | AP54: 29 | AQ54: =AS38 -> 9.68 | AR54: =AP54-AQ54 -> 19.32 | AS54: =(AP54-AQ54)/AQ54 -> 1.9958678 | AY54: CALAVERA | BB54: =AP54 -> 29 | BC54: =BC22-BB38 -> 2 | BD54: =BD22-BC38 -> 2 | BE54: =BC54+BD54 -> 4 | BF54: =BB54*BE54 -> 116
D55: VINTAGE BROWN | K55: =I55+J55 -> 0 | L55: =G55*K55 -> 0 | M55: =H55*K55 -> 0 | O55: VINTAGE BROWN | V55: =T55+U55 -> 0 | W55: =R55*V55 -> 0 | X55: =S55*V55 -> 0 | Z55: VINTAGE BROWN | AG55: =AE55+AF55 -> 0 | AH55: =AC55*AG55 -> 0 | AI55: =AD55*AG55 -> 0 | BR55: BALTHAZAR (Paris) | BV55: 0 | BW55: 0 | BX55: 0 | BY55: 1 | BZ55: 0 | CA55: 0 | CB55: 0 | CC55: 0 | CD55: =SUM(BV55:CC56) -> 1 | CE55: =BV55*39+BW55*39+BX55*27+BY55*27+BZ55*23+CA55*23+CB55*23+CC55*23 -> 27 | CF55: 25€ VINTED | CJ55: 25 | CK55: REVOLUT | CM55: 44620
BE56: =SUM(BE48:BE55) -> 38 | BF56: =SUM(BF48:BF55) -> 1412
D57: CAMEL | K57: =I57+J57 -> 0 | L57: =G57*K57 -> 0 | M57: =H57*K57 -> 0 | O57: CAMEL | V57: =T57+U57 -> 0 | W57: =R57*V57 -> 0 | X57: =S57*V57 -> 0 | Z57: CAMEL | AG57: =AE57+AF57 -> 0 | AH57: =AC57*AG57 -> 0 | AI57: =AD57*AG57 -> 0 | BR57: TITOUAN | BV57: 0 | BW57: 0 | BX57: 1 | BY57: 0 | BZ57: 0 | CA57: 0 | CB57: 0 | CC57: 0 | CD57: =SUM(BV57:CC58) -> 1 | CE57: =BV57*39+BW57*39+BX57*27+BY57*27+BZ57*23+CA57*23+CB57*23+CC57*23 -> 27 | CF57: 25€ VINTED | CJ57: 25 | CK57: REVOLUT | CM57: 44620
D59: KHAKI | K59: =I59+J59 -> 0 | L59: =G59*K59 -> 0 | M59: =H59*K59 -> 0 | O59: KHAKI | V59: =T59+U59 -> 0 | W59: =R59*V59 -> 0 | X59: =S59*V59 -> 0 | Z59: KHAKI | AG59: =AE59+AF59 -> 0 | AH59: =AC59*AG59 -> 0 | AI59: =AD59*AG59 -> 0 | BR59: JUST.JEANNE | BV59: 0 | BW59: 0 | BX59: 0 | BY59: 0 | BZ59: 0 | CA59: 1 | CB59: 0 | CC59: 0 | CD59: =SUM(BV59:CC60) -> 1 | CE59: =BV59*39+BW59*39+BX59*27+BY59*27+BZ59*23+CA59*23+CB59*23+CC59*23 -> 23 | CF59: 23€ VINTED | CJ59: 23 | CK59: REVOLUT | CM59: 44620
D61: SAND | K61: =I61+J61 -> 0 | L61: =G61*K61 -> 0 | M61: =H61*K61 -> 0 | O61: SAND | V61: =T61+U61 -> 0 | W61: =R61*V61 -> 0 | X61: =S61*V61 -> 0 | Z61: SAND | AG61: =AE61+AF61 -> 0 | AH61: =AC61*AG61 -> 0 | AI61: =AD61*AG61 -> 0 | BH61: % DISCOUNT % | BR61: JAIME | BV61: 0 | BW61: 0 | BX61: 0 | BY61: 1 | BZ61: 1 | CA61: 0 | CB61: 0 | CC61: 0 | CD61: =SUM(BV61:CC62) -> 2 | CE61: =BV61*39+BW61*39+BX61*27+BY61*27+BZ61*23+CA61*23+CB61*23+CC61*23 -> 50 | CF61: 30€ EFECTIVO + 20€ TARJETA | CI61: 30 | CJ61: 20 | CK61: REVOLUT | CM61: 44626
D63: CREAM | K63: =I63+J63 -> 0 | L63: =G63*K63 -> 0 | M63: =H63*K63 -> 0 | O63: CREAM | V63: =T63+U63 -> 0 | W63: =R63*V63 -> 0 | X63: =S63*V63 -> 0 | Z63: CREAM | AG63: =AE63+AF63 -> 0 | AH63: =AC63*AG63 -> 0 | AI63: =AD63*AG63 -> 0 | BB63: PRICE | BC63: M | BD63: L | BE63: UNITS | BF63: TOTAL € | BL63: PRICE | BM63: M | BN63: L | BO63: UNITS | BP63: TOTAL € | BR63: AMIGO JAIME | BV63: 0 | BW63: 0 | BX63: 1 | BY63: 0 | BZ63: 1 | CA63: 0 | CB63: 0 | CC63: 0 | CD63: =SUM(BV63:CC64) -> 2 | CE63: =BV63*39+BW63*39+BX63*27+BY63*27+BZ63*23+CA63*23+CB63*23+CC63*23 -> 50 | CF63: 50€ TARJETA | CJ63: 50 | CK63: REVOLUT | CM63: 44626
D65: PINK DUST | K65: =I65+J65 -> 0 | L65: =G65*K65 -> 0 | M65: =H65*K65 -> 0 | O65: PINK DUST | V65: =T65+U65 -> 0 | W65: =R65*V65 -> 0 | X65: =S65*V65 -> 0 | Z65: PINK DUST | AG65: =AE65+AF65 -> 0 | AH65: =AC65*AG65 -> 0 | AI65: =AD65*AG65 -> 0 | AY65: OJOS | BB65: =BB48 -> 49 | BC65: 4 | BD65: 6 | BE65: =BC65+BD65 -> 10 | BF65: =BB65*BE65 -> 490 | BI65: OJOS | BL65: 39 | BM65: =BC48-BC65 -> 1 | BN65: =BD48-BD65 -> 1 | BO65: =BM65+BN65 -> 2 | BP65: =BL65*BO65 -> 78 | BR65: NICO RUIZ | BV65: 0 | BW65: 0 | BX65: 1 | BY65: 0 | BZ65: 0 | CA65: 0 | CB65: 0 | CC65: 0 | CD65: =SUM(BV65:CC66) -> 1 | CE65: =BV65*39+BW65*39+BX65*27+BY65*27+BZ65*23+CA65*23+CB65*23+CC65*23 -> 27 | CF65: 25€ TARJETA | CJ65: 25 | CK65: REVOLUT | CM65: 44677
D67: PASTEL BLUE | K67: =I67+J67 -> 0 | L67: =G67*K67 -> 0 | M67: =H67*K67 -> 0 | O67: PASTEL BLUE | V67: =T67+U67 -> 0 | W67: =R67*V67 -> 0 | X67: =S67*V67 -> 0 | Z67: PASTEL BLUE | AG67: =AE67+AF67 -> 0 | AH67: =AC67*AG67 -> 0 | AI67: =AD67*AG67 -> 0 | AY67: MIRILLA | BB67: =BB50 -> 34 | BC67: 2 | BD67: 4 | BE67: =BC67+BD67 -> 6 | BF67: =BB67*BE67 -> 204 | BI67: MIRILLA | BL67: 27 | BM67: =BC50-BC67 -> 5 | BN67: =BD50-BD67 -> 3 | BO67: =BM67+BN67 -> 8 | BP67: =BL67*BO67 -> 216 | BR67: QUINTANA | BV67: 0 | BW67: 0 | BX67: 0 | BY67: 1 | BZ67: 0 | CA67: 0 | CB67: 0 | CC67: 0 | CD67: =SUM(BV67:CC68) -> 1 | CE67: =BV67*39+BW67*39+BX67*27+BY67*27+BZ67*23+CA67*23+CB67*23+CC67*23 -> 27 | CF67: 25€ TARJETA | CJ67: 25 | CK67: REVOLUT | CM67: 44722
D69: SAGE PURPLE | K69: =I69+J69 -> 0 | L69: =G69*K69 -> 0 | M69: =H69*K69 -> 0 | O69: SAGE PURPLE | V69: =T69+U69 -> 0 | W69: =R69*V69 -> 0 | X69: =S69*V69 -> 0 | Z69: SAGE PURPLE | AG69: =AE69+AF69 -> 0 | AH69: =AC69*AG69 -> 0 | AI69: =AD69*AG69 -> 0 | AY69: SEÑORA | BB69: =BB52 -> 29 | BC69: 2 | BD69: 3 | BE69: =BC69+BD69 -> 5 | BF69: =BB69*BE69 -> 145 | BI69: SEÑORA | BL69: 23 | BM69: =BC52-BC69 -> 2 | BN69: =BD52-BD69 -> 1 | BO69: =BM69+BN69 -> 3 | BP69: =BL69*BO69 -> 69 | BR69: BARTA | BV69: 0 | BW69: 0 | BX69: 1 | BY69: 0 | BZ69: 0 | CA69: 0 | CB69: 0 | CC69: 0 | CD69: =SUM(BV69:CC70) -> 1 | CE69: =BV69*39+BW69*39+BX69*27+BY69*27+BZ69*23+CA69*23+CB69*23+CC69*23 -> 27 | CF69: 25€ TARJETA | CJ69: 25 | CK69: REVOLUT | CM69: 44716
D71: ORANGE | K71: =I71+J71 -> 0 | L71: =G71*K71 -> 0 | M71: =H71*K71 -> 0 | O71: ORANGE | V71: =T71+U71 -> 0 | W71: =R71*V71 -> 0 | X71: =S71*V71 -> 0 | Z71: ORANGE | AG71: =AE71+AF71 -> 0 | AH71: =AC71*AG71 -> 0 | AI71: =AD71*AG71 -> 0 | AY71: CALAVERA | BB71: =BB54 -> 29 | BC71: 2 | BD71: 2 | BE71: =BC71+BD71 -> 4 | BF71: =BB71*BE71 -> 116 | BI71: CALAVERA | BL71: 23 | BM71: =BC54-BC71 -> 0 | BN71: =BD54-BD71 -> 0 | BO71: =BM71+BN71 -> 0 | BP71: =BL71*BO71 -> 0
BT72: SOLD | BV72: =SUM(BV9:BV70) -> 5 | BW72: =SUM(BW9:BW70) -> 7 | BX72: =SUM(BX9:BX70) -> 7 | BY72: =SUM(BY9:BY70) -> 7 | BZ72: =SUM(BZ9:BZ70) -> 4 | CA72: =SUM(CA9:CA70) -> 4 | CB72: =SUM(CB9:CB70) -> 2 | CC72: =SUM(CC9:CC70) -> 2 | ... CE72: =SUM(CE9:CE70) -> 1318 | CI72: =SUM(CI9:CI70) -> 234 | CJ72: =SUM(CJ9:CJ70) -> 1070 | CK72: =SUM(CK9:CL70) -> 0
D73: FOREST GREEN | K73: =I73+J73 -> 0 | L73: =G73*K73 -> 0 | M73: =H73*K73 -> 0 | O73: FOREST GREEN | V73: =T73+U73 -> 0 | W73: =R73*V73 -> 0 | X73: =S73*V73 -> 0 | Z73: FOREST GREEN | AG73: =AE73+AF73 -> 0 | AH73: =AC73*AG73 -> 0 | AI73: =AD73*AG73 -> 0 | BE73: =SUM(BE65:BE72) -> 25 | BF73: =SUM(BF65:BF72) -> 955 | BO73: =SUM(BO65:BO72) -> 13 | BP73: =SUM(BP65:BP72) -> 363
BT74: STOCK | BV74: =BV5-BV72 -> 0 | BW74: =BW5-BW72 -> 0 | BX74: =BX5-BX72 -> 0 | BY74: =BY5-BY72 -> 0 | BZ74: =BZ5-BZ72 -> 0 | CA74: =CA5-CA72 -> 0 | CB74: =CB5-CB72 -> 0 | CC74: =CC5-CC72 -> 0 | CD74: =CD5-CD72 -> 0 | CJ74: =CI72+CJ72+CK72 -> 1304
I75: =SUM(I45:I74) -> 0 | J75: =SUM(J45:J74) -> 0 | K75: =SUM(K45:K74) -> 0 | L75: =SUM(L45:L74) -> 0 | M75: =SUM(M45:M74) -> 0 | T75: =SUM(T45:T74) -> 0 | U75: =SUM(U45:U74) -> 0 | V75: =SUM(V45:V74) -> 0 | W75: =SUM(W45:W74) -> 0 | X75: =SUM(X45:X74) -> 0 | AE75: =SUM(AE45:AE74) -> 0 | AF75: =SUM(AF45:AF74) -> 0 | AG75: =SUM(AG45:AG74) -> 0 | AH75: =SUM(AH45:AH74) -> 0 | AI75: =SUM(AI45:AI74) -> 0
CG77: INGRESOS | CL77: =CJ74 -> 1304
BH78: INGRESOS | BM78: =BF73+BP73 -> 1318 | BT78: SOLD | BV78: =CD72 -> 38
CG80: RUE PORTER | CL80: =BM81 -> 887.43
BH81: RUE PORTER | BM81: =BN6 -> 887.43
CG82: SERIGRAFIA | CL82: =BM83 -> 246.235
BH83: SERIGRAFIA | BM83: =BN8 -> 246.235
CG84: ETIQUETAS | CL84: 49.01
BH85: ETIQUETAS | BM85: 49.01
CG86: BOLSAS | CL86: 12.69
BH87: BOLSAS | BM87: 12.69
CG88: PEGATINAS | CL88: 26.33
BH89: PEGATINAS | BM89: 26.33
CG90: PUBLICIDAD | CL90: 40
BH91: PUBLICIDAD | BM91: 40
CG92: COSTE TOTAL | CL92: =SUM(CL80:CM91) -> 1261.695
BH93: COSTE TOTAL | BM93: =SUM(BM81:BN92) -> 1261.695
CG95: TOTAL FINAL | CL95: =CL77-CL92 -> 42.305
BH96: TOTAL FINAL | BM96: =BM78-BM93 -> 56.305

Sheet SUMMER DROP
B2: SUMMER DROP | P2: INGRESOS FINALES | Q2: PRECIO | R2: M | S2: L | T2: UNIDADES | U2: TOTAL | Y2: INGRESOS | Z2: PRECIO | AA2: M | AB2: L | AC2: UNIDADES | AD2: TOTAL
P3: =$P$27 -> RUSA | Q3: =Z3 -> 19 | R3: =AA3-AA12 -> 7 | S3: =AB3-AB12 -> 6 | T3: =SUM(R3:S3) -> 13 | U3: =IFERROR(Q3*T3,"-") -> 247 | Y3: =$P$27 -> RUSA | Z3: =Z35 -> 19 | AA3: =R27+1 -> 8 | AB3: =S27 -> 7 | AC3: =SUM(AA3:AB3) -> 15 | AD3: =IFERROR(Z3*AC3,"-") -> 285
P4: =$P$28 -> MANOS | Q4: =Z4 -> 19 | R4: =AA4-AA13 -> 6 | S4: =AB4-AB13 -> 7 | T4: =SUM(R4:S4) -> 13 | U4: =IFERROR(Q4*T4,"-") -> 247 | Y4: =$P$28 -> MANOS | Z4: =Z36 -> 19 | AA4: =R28 -> 7 | AB4: =S28+1 -> 8 | AC4: =SUM(AA4:AB4) -> 15 | AD4: =IFERROR(Z4*AC4,"-") -> 285
C5: PPTO | D5: REAL | P5: =$P$29 -> 0 | Q5: =Z5 -> 0 | R5: =AA5-AA14 -> 0 | S5: =AB5-AB14 -> 0 | T5: =SUM(R5:S5) -> 0 | U5: =IFERROR(Q5*T5,"-") -> 0 | Y5: =$P$29 -> 0 | Z5: =Z37 -> 0 | AA5: =R29 -> 0 | AB5: =S29 -> 0 | AC5: =SUM(AA5:AB5) -> 0 | AD5: =IFERROR(Z5*AC5,"-") -> 0
B6: INGRESOS | C6: =U9 -> 494 | D6: =SUM(L27:$L$61) -> 494 | P6: =$P$30 -> 0 | Q6: =Z6 -> 0 | R6: =AA6-AA15 -> 0 | S6: =AB6-AB15 -> 0 | T6: =SUM(R6:S6) -> 0 | U6: =IFERROR(Q6*T6,"-") -> 0 | Y6: =$P$30 -> 0 | Z6: =Z38 -> 0 | AA6: =R30 -> 0 | AB6: =S30 -> 0 | AC6: =SUM(AA6:AB6) -> 0 | AD6: =IFERROR(Z6*AC6,"-") -> 0
B7: Otros ingresos | C7: 0 | R7: =AA7-AA16 -> 0 | S7: =AB7-AB16 -> 0 | T7: =SUM(R7:S7) -> 0 | U7: =IFERROR(Q7*T7,"-") -> 0 | AA7: =R31 -> 0 | AB7: =S31 -> 0 | AC7: =SUM(AA7:AB7) -> 0 | AD7: =IFERROR(Z7*AC7,"-") -> 0
B8: TOTAL INGRESOS | C8: =SUM(C6:C7) -> 494 | D8: =SUM(D6:D7) -> 494 | R8: =AA8-AA17 -> 0 | S8: =AB8-AB17 -> 0 | T8: =SUM(R8:S8) -> 0 | U8: =IFERROR(Q8*T8,"-") -> 0 | AA8: =R32 -> 0 | AB8: =S32 -> 0 | AC8: =SUM(AA8:AB8) -> 0 | AD8: =IFERROR(Z8*AC8,"-") -> 0
B9: Gasto Blanks 1 | C9: =-$W$52 -> -118 | D9: =C9 -> -118 | P9: INGRESOS TOTALES FINALES | T9: =SUM(T3:T8) -> 26 | U9: =SUM(U3:U8) -> 494 | Y9: INGRESOS TOTALES | AC9: =SUM(AC3:AC8) -> 30 | AD9: =SUM(AD3:AD8) -> 570
B10: Gasto Serigrafia | C10: =-$U$61 -> -93.17 | D10: =C10 -> -93.17
B11: Otros gastos | C11: 0 | Y11: GON JACO | Z11: COSTE | AA11: M | AB11: L | AC11: UNIDADES | AD11: TOTAL
Y12: =$P$27 -> RUSA | Z12: =AA35 -> -7.8442857 | AA12: 1 | AB12: 1 | AC12: =SUM(AA12:AB12) -> 2 | AD12: =IFERROR(Z12*AC12,"-") -> -15.688571
Y13: =$P$28 -> MANOS | Z13: =AA36 -> -7.2392857 | AA13: 1 | AB13: 1 | AC13: =SUM(AA13:AB13) -> 2 | AD13: =IFERROR(Z13*AC13,"-") -> -14.478571
B14: TOTAL GASTOS | C14: =SUM(C9:C13) -> -211.17 | D14: =SUM(D9:D13) -> -211.17 | Y14: =$P$29 -> 0 | Z14: =AA37 -> -0.054285714 | AC14: =SUM(AA14:AB14) -> 0 | AD14: =IFERROR(Z14*AC14,"-") -> 0
Y15: =$P$30 -> 0 | Z15: =AA38 -> -0.054285714 | AC15: =SUM(AA15:AB15) -> 0 | AD15: =IFERROR(Z15*AC15,"-") -> 0
AC16: =SUM(AA16:AB16) -> 0 | AD16: =IFERROR(Z16*AC16,"-") -> 0
B17: BENEFICIO | C17: =C8+C14 -> 282.83 | D17: =D8+D14 -> 282.83 | AC17: =SUM(AA17:AB17) -> 0 | AD17: =IFERROR(Z17*AC17,"-") -> 0
Y18: COSTE TOTAL | AC18: =SUM(AC12:AC17) -> 4 | AD18: =SUM(AD12:AD17) -> -30.167143
B19: RATIO DE BLANKS | C19: =IFERROR(ABS($C$9/$C$8),"-") -> 0.2388664 | D19: =IFERROR(ABS($D$10/$D$8),"-") -> 0.18860324
B20: COR% | C20: =IFERROR(ABS($C$14/$C$8),"-") -> 0.42746964 | D20: =IFERROR(ABS($D$14/$D$8),"-") -> 0.42746964
C22: =$P$27 -> RUSA | E22: =$P$28 -> MANOS | G22: =$P$29 -> 0 | I22: =$P$30 -> 0
C23: M | D23: L | E23: M | F23: L | G23: M | H23: L | I23: M | J23: L | K23: TOTAL
B24: SOLD | C24: =SUM(C27:C61) -> 7 | D24: =SUM(D27:D61) -> 6 | E24: =SUM(E27:E61) -> 6 | F24: =SUM(F27:F61) -> 7 | G24: =SUM(G27:G61) -> 0 | H24: =SUM(H27:H61) -> 0 | I24: =SUM(I27:I61) -> 0 | J24: =SUM(J27:J61) -> 0 | K24: =SUM(C24:J24) -> 26 | L24: =K24-SUM(K27:K61) -> 0
B25: STOCK | C25: =R3-C24 -> 0 | D25: =S3-D24 -> 0 | E25: =R4-E24 -> 0 | F25: =S4-F24 -> 0 | G25: =R5-G24 -> 0 | H25: =S5-H24 -> 0 | I25: =R6-I24 -> 0 | J25: =S6-J24 -> 0 | K25: =SUM(C25:J25) -> 0
B26: NOMBRE | K26: UNIDADES | L26: INGRESO | M26: FECHA | P26: BLANKS 1 | Q26: UND€ | R26: M | S26: L | T26: UNIDADES | U26: EXTRA | V26: € PER UND | W26: TOTAL | Y26: COSTE POR UND | Z26: BLANKS | AA26: SERIGRAFIA | AB26: EXTRA | AC26: TOTAL
A27: 1 | B27: MUÑOZ | F27: 1 | K27: =SUM(C27:J27) -> 1 | L27: =IFERROR(((C27+D27)*$Q$3)+((E27+F27)*$Q$4)+((G27+H27)*$Q$5)+((I27+J27)*$Q$6),"-") -> 19 | P27: RUSA | Q27: 4.16 | R27: 7 | S27: 7 | T27: =R27+S27 -> 14 | U27: =IFERROR($W$36/$T$33,"-") -> 0.054285714 | V27: =IFERROR(Q27+U27,"-") -> 4.2142857 | W27: =IFERROR(T27*V27,"-") -> 59 | Y27: =$P$27 -> RUSA | Z27: =V27 -> 4.2142857 | AA27: =T55 -> 3.63 | AC27: =SUM(Z27:AB27) -> 7.8442857
A28: 2 | B28: PETER | D28: 1 | F28: 1 | K28: =SUM(C28:J28) -> 2 | L28: =IFERROR(((C28+D28)*$Q$3)+((E28+F28)*$Q$4)+((G28+H28)*$Q$5)+((I28+J28)*$Q$6),"-") -> 38 | P28: MANOS | Q28: 4.16 | R28: 7 | S28: 7 | T28: =R28+S28 -> 14 | U28: =IFERROR($W$36/$T$33,"-") -> 0.054285714 | V28: =IFERROR(Q28+U28,"-") -> 4.2142857 | W28: =IFERROR(T28*V28,"-") -> 59 | Y28: =$P$28 -> MANOS | Z28: =V28 -> 4.2142857 | AA28: =T56 -> 3.025 | AC28: =SUM(Z28:AB28) -> 7.2392857
A29: 3 | B29: JUANMA | F29: 1 | K29: =SUM(C29:J29) -> 1 | L29: =IFERROR(((C29+D29)*$Q$3)+((E29+F29)*$Q$4)+((G29+H29)*$Q$5)+((I29+J29)*$Q$6),"-") -> 19 | T29: =R29+S29 -> 0 | U29: =IFERROR($W$36/$T$33,"-") -> 0.054285714 | V29: =IFERROR(Q29+U29,"-") -> 0.054285714 | W29: =IFERROR(T29*V29,"-") -> 0 | Y29: =$P$29 -> 0 | Z29: =V29 -> 0.054285714 | AA29: =T57 -> - | AC29: =SUM(Z29:AB29) -> 0.054285714
A30: =A29+1 -> 4 | B30: NICO RUIZ | C30: 1 | E30: 1 | K30: =SUM(C30:J30) -> 2 | L30: =IFERROR(((C30+D30)*$Q$3)+((E30+F30)*$Q$4)+((G30+H30)*$Q$5)+((I30+J30)*$Q$6),"-") -> 38 | T30: =R30+S30 -> 0 | U30: =IFERROR($W$36/$T$33,"-") -> 0.054285714 | V30: =IFERROR(Q30+U30,"-") -> 0.054285714 | W30: =IFERROR(T30*V30,"-") -> 0 | Y30: =$P$30 -> 0 | Z30: =V30 -> 0.054285714 | AA30: =T58 -> - | AC30: =SUM(Z30:AB30) -> 0.054285714
A31: =A30+1 -> 5 | B31: ASTARLOA | D31: 1 | K31: =SUM(C31:J31) -> 1 | L31: =IFERROR(((C31+D31)*$Q$3)+((E31+F31)*$Q$4)+((G31+H31)*$Q$5)+((I31+J31)*$Q$6),"-") -> 19 | T31: =R31+S31 -> 0 | V31: =IFERROR(Q31+U31,"-") -> 0 | W31: =IFERROR(T31*V31,"-") -> 0 | AC31: =SUM(Z31:AB31) -> 0
A32: =A31+1 -> 6 | B32: RUBINI | F32: 1 | K32: =SUM(C32:J32) -> 1 | L32: =IFERROR(((C32+D32)*$Q$3)+((E32+F32)*$Q$4)+((G32+H32)*$Q$5)+((I32+J32)*$Q$6),"-") -> 19 | T32: =R32+S32 -> 0 | V32: =IFERROR(Q32+U32,"-") -> 0 | W32: =IFERROR(T32*V32,"-") -> 0 | AC32: =SUM(Z32:AB32) -> 0
A33: =A32+1 -> 7 | B33: PUIG AMIGO JACO | C33: 1 | K33: =SUM(C33:J33) -> 1 | L33: =IFERROR(((C33+D33)*$Q$3)+((E33+F33)*$Q$4)+((G33+H33)*$Q$5)+((I33+J33)*$Q$6),"-") -> 19 | P33: TOTAL | T33: =SUM(T27:T32) -> 28 | W33: =SUM(W27:W32) -> 118
A34: =A33+1 -> 8 | B34: JUANTO | C34: 1 | E34: 1 | K34: =SUM(C34:J34) -> 2 | L34: =IFERROR(((C34+D34)*$Q$3)+((E34+F34)*$Q$4)+((G34+H34)*$Q$5)+((I34+J34)*$Q$6),"-") -> 38 | P34: Envio | Y34: BENEFICIO POR UND | Z34: PRECIO | AA34: COSTE | AB34: BENEFICIO | AC34: MARGEN
A35: =A34+1 -> 9 | B35: NICO DIAMANTO | C35: 1 | K35: =SUM(C35:J35) -> 1 | L35: =IFERROR(((C35+D35)*$Q$3)+((E35+F35)*$Q$4)+((G35+H35)*$Q$5)+((I35+J35)*$Q$6),"-") -> 19 | P35: Otros gastos | W35: =1.52 -> 1.52 | Y35: =$P$27 -> RUSA | Z35: 19 | AA35: =-AC27 -> -7.8442857 | AB35: =SUM(Z35:AA35) -> 11.155714 | AC35: =AB35/Z35 -> 0.58714286
A36: =A35+1 -> 10 | B36: DOMINGUEZ | D36: 1 | K36: =SUM(C36:J36) -> 1 | L36: =IFERROR(((C36+D36)*$Q$3)+((E36+F36)*$Q$4)+((G36+H36)*$Q$5)+((I36+J36)*$Q$6),"-") -> 19 | P36: TOTAL EXTRAS | W36: =SUM(W34:W35) -> 1.52 | Y36: =$P$28 -> MANOS | Z36: 19 | AA36: =-AC28 -> -7.2392857 | AB36: =SUM(Z36:AA36) -> 11.760714 | AC36: =AB36/Z36 -> 0.61898496
A37: =A36+1 -> 11 | B37: CHORVO | E37: 1 | K37: =SUM(C37:J37) -> 1 | L37: =IFERROR(((C37+D37)*$Q$3)+((E37+F37)*$Q$4)+((G37+H37)*$Q$5)+((I37+J37)*$Q$6),"-") -> 19 | P37: BLANKS TOTAL | W37: =W33 -> 118 | Y37: =$P$29 -> 0 | AA37: =-AC29 -> -0.054285714 | AB37: =SUM(Z37:AA37) -> -0.054285714 | AC37: =AB37/Z37 -> #DIV/0!
A38: =A37+1 -> 12 | B38: DIRECTOR AMIGO JACO | C38: 1 | K38: =SUM(C38:J38) -> 1 | L38: =IFERROR(((C38+D38)*$Q$3)+((E38+F38)*$Q$4)+((G38+H38)*$Q$5)+((I38+J38)*$Q$6),"-") -> 19 | W38: =Q27*T27+Q28*T28+Q29*T29+Q30*T30+Q31*T31+Q32*T32+W36-W37 -> 0 | Y38: =$P$30 -> 0 | AA38: =-AC30 -> -0.054285714 | AB38: =SUM(Z38:AA38) -> -0.054285714 | AC38: =AB38/Z38 -> #DIV/0!
A39: =A38+1 -> 13 | B39: NACHO PEREZ | C39: 1 | K39: =SUM(C39:J39) -> 1 | L39: =IFERROR(((C39+D39)*$Q$3)+((E39+F39)*$Q$4)+((G39+H39)*$Q$5)+((I39+J39)*$Q$6),"-") -> 19 | P39: BLANKS 2 | Q39: UND€ | R39: M | S39: L | T39: UNIDADES | U39: EXTRA | V39: € PER UND | W39: TOTAL
A40: =A39+1 -> 14 | B40: JOSE AMIGO JACO | D40: 1 | F40: 1 | K40: =SUM(C40:J40) -> 2 | L40: =IFERROR(((C40+D40)*$Q$3)+((E40+F40)*$Q$4)+((G40+H40)*$Q$5)+((I40+J40)*$Q$6),"-") -> 38 | T40: =SUM(R40:S40) -> 0 | U40: =IFERROR($W$49/$T$46,"-") -> - | V40: =IFERROR(Q40+U40,"-") -> - | W40: =IFERROR(T40*V40,"-") -> -
A41: =A40+1 -> 15 | B41: BARALLOBRE | D41: 1 | F41: 1 | K41: =SUM(C41:J41) -> 2 | L41: =IFERROR(((C41+D41)*$Q$3)+((E41+F41)*$Q$4)+((G41+H41)*$Q$5)+((I41+J41)*$Q$6),"-") -> 38 | T41: =SUM(R41:S41) -> 0 | U41: =IFERROR($W$49/$T$46,"-") -> - | V41: =IFERROR(Q41+U41,"-") -> - | W41: =IFERROR(T41*V41,"-") -> -
A42: =A41+1 -> 16 | B42: IAGO AMIGO JACO | E42: 1 | K42: =SUM(C42:J42) -> 1 | L42: =IFERROR(((C42+D42)*$Q$3)+((E42+F42)*$Q$4)+((G42+H42)*$Q$5)+((I42+J42)*$Q$6),"-") -> 19 | T42: =SUM(R42:S42) -> 0 | U42: =IFERROR($W$49/$T$46,"-") -> - | V42: =IFERROR(Q42+U42,"-") -> - | W42: =IFERROR(T42*V42,"-") -> -
A43: =A42+1 -> 17 | B43: CASADO | C43: 1 | K43: =SUM(C43:J43) -> 1 | L43: =IFERROR(((C43+D43)*$Q$3)+((E43+F43)*$Q$4)+((G43+H43)*$Q$5)+((I43+J43)*$Q$6),"-") -> 19 | T43: =SUM(R43:S43) -> 0 | U43: =IFERROR($W$49/$T$46,"-") -> - | V43: =IFERROR(Q43+U43,"-") -> - | W43: =IFERROR(T43*V43,"-") -> -
A44: =A43+1 -> 18 | B44: JORGE PUIG | E44: 1 | K44: =SUM(C44:J44) -> 1 | L44: =IFERROR(((C44+D44)*$Q$3)+((E44+F44)*$Q$4)+((G44+H44)*$Q$5)+((I44+J44)*$Q$6),"-") -> 19 | T44: =SUM(R44:S44) -> 0 | V44: =IFERROR(Q44+U44,"-") -> 0 | W44: =IFERROR(T44*V44,"-") -> 0
A45: =A44+1 -> 19 | B45: IÑIGO | D45: 1 | F45: 1 | K45: =SUM(C45:J45) -> 2 | L45: =IFERROR(((C45+D45)*$Q$3)+((E45+F45)*$Q$4)+((G45+H45)*$Q$5)+((I45+J45)*$Q$6),"-") -> 38 | T45: =SUM(R45:S45) -> 0 | V45: =IFERROR(Q45+U45,"-") -> 0 | W45: =IFERROR(T45*V45,"-") -> 0
A46: =A45+1 -> 20 | B46: BRUNITO | E46: 1 | K46: =SUM(C46:J46) -> 1 | L46: =IFERROR(((C46+D46)*$Q$3)+((E46+F46)*$Q$4)+((G46+H46)*$Q$5)+((I46+J46)*$Q$6),"-") -> 19 | P46: TOTAL | T46: =SUM(T40:T45) -> 0 | W46: =SUM(W40:W45) -> 0
A47: =A46+1 -> 21 | K47: =SUM(C47:J47) -> 0 | L47: =IFERROR(((C47+D47)*$Q$3)+((E47+F47)*$Q$4)+((G47+H47)*$Q$5)+((I47+J47)*$Q$6),"-") -> 0 | P47: Envio
A48: =A47+1 -> 22 | K48: =SUM(C48:J48) -> 0 | L48: =IFERROR(((C48+D48)*$Q$3)+((E48+F48)*$Q$4)+((G48+H48)*$Q$5)+((I48+J48)*$Q$6),"-") -> 0 | P48: Otros gastos
A49: =A48+1 -> 23 | K49: =SUM(C49:J49) -> 0 | L49: =IFERROR(((C49+D49)*$Q$3)+((E49+F49)*$Q$4)+((G49+H49)*$Q$5)+((I49+J49)*$Q$6),"-") -> 0 | P49: TOTAL EXTRAS | W49: =SUM(W47:W48) -> 0
A50: =A49+1 -> 24 | K50: =SUM(C50:J50) -> 0 | L50: =IFERROR(((C50+D50)*$Q$3)+((E50+F50)*$Q$4)+((G50+H50)*$Q$5)+((I50+J50)*$Q$6),"-") -> 0 | P50: BLANKS TOTAL | W50: =-W46 -> 0
A51: =A50+1 -> 25 | K51: =SUM(C51:J51) -> 0 | L51: =IFERROR(((C51+D51)*$Q$3)+((E51+F51)*$Q$4)+((G51+H51)*$Q$5)+((I51+J51)*$Q$6),"-") -> 0 | W51: =Q40*T40+Q41*T41+Q42*T42+Q43*T43+Q44*T44+Q45*T45+W49+W50 -> 0
A52: =A51+1 -> 26 | K52: =SUM(C52:J52) -> 0 | L52: =IFERROR(((C52+D52)*$Q$3)+((E52+F52)*$Q$4)+((G52+H52)*$Q$5)+((I52+J52)*$Q$6),"-") -> 0 | P52: COSTE TOTAL BLANKS | W52: =W37+W50 -> 118
A53: =A52+1 -> 27 | K53: =SUM(C53:J53) -> 0 | L53: =IFERROR(((C53+D53)*$Q$3)+((E53+F53)*$Q$4)+((G53+H53)*$Q$5)+((I53+J53)*$Q$6),"-") -> 0
A54: =A53+1 -> 28 | K54: =SUM(C54:J54) -> 0 | L54: =IFERROR(((C54+D54)*$Q$3)+((E54+F54)*$Q$4)+((G54+H54)*$Q$5)+((I54+J54)*$Q$6),"-") -> 0 | P54: SERIGRAFIA | Q54: €/UND | R54: UNIDADES | S54: IVA | T54: € PER UND | U54: TOTAL
A55: =A54+1 -> 29 | K55: =SUM(C55:J55) -> 0 | L55: =IFERROR(((C55+D55)*$Q$3)+((E55+F55)*$Q$4)+((G55+H55)*$Q$5)+((I55+J55)*$Q$6),"-") -> 0 | P55: =$P$27 -> RUSA | Q55: 3 | R55: =T27 -> 14 | S55: =IFERROR(((Q55*R55)*0.21)/R55,"-") -> 0.63 | T55: =IFERROR(Q55+S55,"-") -> 3.63 | U55: =IFERROR(R55*T55,"-") -> 50.82
A56: =A55+1 -> 30 | K56: =SUM(C56:J56) -> 0 | L56: =IFERROR(((C56+D56)*$Q$3)+((E56+F56)*$Q$4)+((G56+H56)*$Q$5)+((I56+J56)*$Q$6),"-") -> 0 | P56: =$P$28 -> MANOS | Q56: 2.5 | R56: =T28 -> 14 | S56: =IFERROR(((Q56*R56)*0.21)/R56,"-") -> 0.525 | T56: =IFERROR(Q56+S56,"-") -> 3.025 | U56: =IFERROR(R56*T56,"-") -> 42.35
A57: =A56+1 -> 31 | K57: =SUM(C57:J57) -> 0 | L57: =IFERROR(((C57+D57)*$Q$3)+((E57+F57)*$Q$4)+((G57+H57)*$Q$5)+((I57+J57)*$Q$6),"-") -> 0 | P57: =$P$29 -> 0 | R57: =T29 -> 0 | S57: =IFERROR(((Q57*R57)*0.21)/R57,"-") -> - | T57: =IFERROR(Q57+S57,"-") -> - | U57: =IFERROR(R57*T57,"-") -> -
A58: =A57+1 -> 32 | K58: =SUM(C58:J58) -> 0 | L58: =IFERROR(((C58+D58)*$Q$3)+((E58+F58)*$Q$4)+((G58+H58)*$Q$5)+((I58+J58)*$Q$6),"-") -> 0 | P58: =$P$30 -> 0 | R58: =T30 -> 0 | S58: =IFERROR(((Q58*R58)*0.21)/R58,"-") -> - | T58: =IFERROR(Q58+S58,"-") -> - | U58: =IFERROR(R58*T58,"-") -> -
A59: =A58+1 -> 33 | K59: =SUM(C59:J59) -> 0 | L59: =IFERROR(((C59+D59)*$Q$3)+((E59+F59)*$Q$4)+((G59+H59)*$Q$5)+((I59+J59)*$Q$6),"-") -> 0 | S59: =IFERROR(((Q59*R59)*0.21)/R59,"-") -> - | T59: =IFERROR(Q59+S59,"-") -> - | U59: =IFERROR(R59*T59,"-") -> -
A60: =A59+1 -> 34 | K60: =SUM(C60:J60) -> 0 | L60: =IFERROR(((C60+D60)*$Q$3)+((E60+F60)*$Q$4)+((G60+H60)*$Q$5)+((I60+J60)*$Q$6),"-") -> 0 | S60: =IFERROR(((Q60*R60)*0.21)/R60,"-") -> - | T60: =IFERROR(Q60+S60,"-") -> - | U60: =IFERROR(R60*T60,"-") -> -
A61: =A60+1 -> 35 | K61: =SUM(C61:J61) -> 0 | L61: =IFERROR(((C61+D61)*$Q$3)+((E61+F61)*$Q$4)+((G61+H61)*$Q$5)+((I61+J61)*$Q$6),"-") -> 0 | P61: SERIGRAFIA TOTAL | R61: =SUM(R55:R60) -> 28 | U61: =SUM(U55:U60) -> 93.17
A65: 1 | B65: =B27 -> MUÑOZ | C65: =_xlfn.TEXTJOIN(", ",TRUE, IF(OR(C27>0,E27>0,G27>0,I27>0),"M",""), IF(OR(D27>0,F27>0,H27>0,J27>0),"L","") ) -> L | D65: =IF(C65="M",1,IF(C65="L",2,IF(C65="M, L",3))) -> 2 | E65: =K27 -> 1 | F65: =L27 -> 19 | G65: =$B$2 -> SUMMER DROP
A66: 2 | B66: =B28 -> PETER | C66: =_xlfn.TEXTJOIN(", ",TRUE, IF(OR(C28>0,E28>0,G28>0,I28>0),"M",""), IF(OR(D28>0,F28>0,H28>0,J28>0),"L","") ) -> L | D66: =IF(C66="M",1,IF(C66="L",2,IF(C66="M, L",3))) -> 2 | E66: =K28 -> 2 | F66: =L28 -> 38 | G66: =$B$2 -> SUMMER DROP
A67: 3 | B67: =B29 -> JUANMA | C67: =_xlfn.TEXTJOIN(", ",TRUE, IF(OR(C29>0,E29>0,G29>0,I29>0),"M",""), IF(OR(D29>0,F29>0,H29>0,J29>0),"L","") ) -> L | D67: =IF(C67="M",1,IF(C67="L",2,IF(C67="M, L",3))) -> 2 | E67: =K29 -> 1 | F67: =L29 -> 19 | G67: =$B$2 -> SUMMER DROP
A68: =A67+1 -> 4 | B68: =B30 -> NICO RUIZ | C68: =_xlfn.TEXTJOIN(", ",TRUE, IF(OR(C30>0,E30>0,G30>0,I30>0),"M",""), IF(OR(D30>0,F30>0,H30>0,J30>0),"L","") ) -> M | D68: =IF(C68="M",1,IF(C68="L",2,IF(C68="M, L",3))) -> 1 | E68: =K30 -> 2 | F68: =L30 -> 38 | G68: =$B$2 -> SUMMER DROP
A69: =A68+1 -> 5 | B69: =B31 -> ASTARLOA | C69: =_xlfn.TEXTJOIN(", ",TRUE, IF(OR(C31>0,E31>0,G31>0,I31>0),"M",""), IF(OR(D31>0,F31>0,H31>0,J31>0),"L","") ) -> L | D69: =IF(C69="M",1,IF(C69="L",2,IF(C69="M, L",3))) -> 2 | E69: =K31 -> 1 | F69: =L31 -> 19 | G69: =$B$2 -> SUMMER DROP
A70: =A69+1 -> 6 | B70: =B32 -> RUBINI | C70: =_xlfn.TEXTJOIN(", ",TRUE, IF(OR(C32>0,E32>0,G32>0,I32>0),"M",""), IF(OR(D32>0,F32>0,H32>0,J32>0),"L","") ) -> L | D70: =IF(C70="M",1,IF(C70="L",2,IF(C70="M, L",3))) -> 2 | E70: =K32 -> 1 | F70: =L32 -> 19 | G70: =$B$2 -> SUMMER DROP
A71: =A70+1 -> 7 | B71: =B33 -> PUIG AMIGO JACO | C71: =_xlfn.TEXTJOIN(", ",TRUE, IF(OR(C33>0,E33>0,G33>0,I33>0),"M",""), IF(OR(D33>0,F33>0,H33>0,J33>0),"L","") ) -> M | D71: =IF(C71="M",1,IF(C71="L",2,IF(C71="M, L",3))) -> 1 | E71: =K33 -> 1 | F71: =L33 -> 19 | G71: =$B$2 -> SUMMER DROP
A72: =A71+1 -> 8 | B72: =B34 -> JUANTO | C72: =_xlfn.TEXTJOIN(", ",TRUE, IF(OR(C34>0,E34>0,G34>0,I34>0),"M",""), IF(OR(D34>0,F34>0,H34>0,J34>0),"L","") ) -> M | D72: =IF(C72="M",1,IF(C72="L",2,IF(C72="M, L",3))) -> 1 | E72: =K34 -> 2 | F72: =L34 -> 38 | G72: =$B$2 -> SUMMER DROP
A73: =A72+1 -> 9 | B73: =B35 -> NICO DIAMANTO | C73: =_xlfn.TEXTJOIN(", ",TRUE, IF(OR(C35>0,E35>0,G35>0,I35>0),"M",""), IF(OR(D35>0,F35>0,H35>0,J35>0),"L","") ) -> M | D73: =IF(C73="M",1,IF(C73="L",2,IF(C73="M, L",3))) -> 1 | E73: =K35 -> 1 | F73: =L35 -> 19 | G73: =$B$2 -> SUMMER DROP
A74: =A73+1 -> 10 | B74: =B36 -> DOMINGUEZ | C74: =_xlfn.TEXTJOIN(", ",TRUE, IF(OR(C36>0,E36>0,G36>0,I36>0),"M",""), IF(OR(D36>0,F36>0,H36>0,J36>0),"L","") ) -> L | D74: =IF(C74="M",1,IF(C74="L",2,IF(C74="M, L",3))) -> 2 | E74: =K36 -> 1 | F74: =L36 -> 19 | G74: =$B$2 -> SUMMER DROP
A75: =A74+1 -> 11 | B75: =B37 -> CHORVO | C75: =_xlfn.TEXTJOIN(", ",TRUE, IF(OR(C37>0,E37>0,G37>0,I37>0),"M",""), IF(OR(D37>0,F37>0,H37>0,J37>0),"L","") ) -> M | D75: =IF(C75="M",1,IF(C75="L",2,IF(C75="M, L",3))) -> 1 | E75: =K37 -> 1 | F75: =L37 -> 19 | G75: =$B$2 -> SUMMER DROP
A76: =A75+1 -> 12 | B76: =B38 -> DIRECTOR AMIGO JACO | C76: =_xlfn.TEXTJOIN(", ",TRUE, IF(OR(C38>0,E38>0,G38>0,I38>0),"M",""), IF(OR(D38>0,F38>0,H38>0,J38>0),"L","") ) -> M | D76: =IF(C76="M",1,IF(C76="L",2,IF(C76="M, L",3))) -> 1 | E76: =K38 -> 1 | F76: =L38 -> 19 | G76: =$B$2 -> SUMMER DROP
A77: =A76+1 -> 13 | B77: =B39 -> NACHO PEREZ | C77: =_xlfn.TEXTJOIN(", ",TRUE, IF(OR(C39>0,E39>0,G39>0,I39>0),"M",""), IF(OR(D39>0,F39>0,H39>0,J39>0),"L","") ) -> M | D77: =IF(C77="M",1,IF(C77="L",2,IF(C77="M, L",3))) -> 1 | E77: =K39 -> 1 | F77: =L39 -> 19 | G77: =$B$2 -> SUMMER DROP
A78: =A77+1 -> 14 | B78: =B40 -> JOSE AMIGO JACO | C78: =_xlfn.TEXTJOIN(", ",TRUE, IF(OR(C40>0,E40>0,G40>0,I40>0),"M",""), IF(OR(D40>0,F40>0,H40>0,J40>0),"L","") ) -> L | D78: =IF(C78="M",1,IF(C78="L",2,IF(C78="M, L",3))) -> 2 | E78: =K40 -> 2 | F78: =L40 -> 38 | G78: =$B$2 -> SUMMER DROP
A79: =A78+1 -> 15 | B79: =B41 -> BARALLOBRE | C79: =_xlfn.TEXTJOIN(", ",TRUE, IF(OR(C41>0,E41>0,G41>0,I41>0),"M",""), IF(OR(D41>0,F41>0,H41>0,J41>0),"L","") ) -> L | D79: =IF(C79="M",1,IF(C79="L",2,IF(C79="M, L",3))) -> 2 | E79: =K41 -> 2 | F79: =L41 -> 38 | G79: =$B$2 -> SUMMER DROP
... A99: =A98+1 -> 35 | B99: =B61 -> 0 | C99: =_xlfn.TEXTJOIN(", ",TRUE, IF(OR(C61>0,E61>0,G61>0,I61>0),"M",""), IF(OR(D61>0,F61>0,H61>0,J61>0),"L","") ) | D99: =IF(C99="M",1,IF(C99="L",2,IF(C99="M, L",3))) -> FALSE | E99: =K61 -> 0 | F99: =L61 -> 0 | G99: =$B$2 -> SUMMER DROP

Sheet A33 X NO ART
B2: A33 X NO ART | P2: INGRESOS FINALES | Q2: PRECIO | R2: M | S2: L | T2: UNIDADES | U2: TOTAL | Y2: INGRESOS | Z2: PRECIO | AA2: M | AB2: L | AC2: UNIDADES | AD2: TOTAL
P3: =$P$27 -> CABEZA | Q3: =Z3 -> 35 | R3: =AA3-AA12 -> 8 | S3: =AB3-AB12 -> 7 | T3: =SUM(R3:S3) -> 15 | U3: =IFERROR(Q3*T3,"-") -> 525 | Y3: =$P$27 -> CABEZA | Z3: =Z35 -> 35 | AA3: =R27 -> 9 | AB3: =S27 -> 8 | AC3: =SUM(AA3:AB3) -> 17 | AD3: =IFERROR(Z3*AC3,"-") -> 595
P4: =$P$28 -> CALAVERA | Q4: =Z4 -> 35 | R4: =AA4-AA13 -> 5 | S4: =AB4-AB13 -> 5 | T4: =SUM(R4:S4) -> 10 | U4: =IFERROR(Q4*T4,"-") -> 350 | Y4: =$P$28 -> CALAVERA | Z4: =Z36 -> 35 | AA4: =R28 -> 6 | AB4: =S28 -> 6 | AC4: =SUM(AA4:AB4) -> 12 | AD4: =IFERROR(Z4*AC4,"-") -> 420
C5: PPTO | D5: REAL | P5: =$P$29 -> 0 | Q5: =Z5 -> 0 | R5: =AA5-AA14 -> 0 | S5: =AB5-AB14 -> 0 | T5: =SUM(R5:S5) -> 0 | U5: =IFERROR(Q5*T5,"-") -> 0 | Y5: =$P$29 -> 0 | Z5: =Z37 -> 0 | AA5: =R29 -> 0 | AB5: =S29 -> 0 | AC5: =SUM(AA5:AB5) -> 0 | AD5: =IFERROR(Z5*AC5,"-") -> 0
B6: INGRESOS | C6: =U9 -> 875 | D6: =SUM(L27:$L$61) -> 830 | P6: =$P$30 -> 0 | Q6: =Z6 -> 0 | R6: =AA6-AA15 -> 0 | S6: =AB6-AB15 -> 0 | T6: =SUM(R6:S6) -> 0 | U6: =IFERROR(Q6*T6,"-") -> 0 | Y6: =$P$30 -> 0 | Z6: =Z38 -> 0 | AA6: =R30 -> 0 | AB6: =S30 -> 0 | AC6: =SUM(AA6:AB6) -> 0 | AD6: =IFERROR(Z6*AC6,"-") -> 0
B7: Otros ingresos | C7: 0 | R7: =AA7-AA16 -> 0 | S7: =AB7-AB16 -> 0 | T7: =SUM(R7:S7) -> 0 | U7: =IFERROR(Q7*T7,"-") -> 0 | AA7: =R31 -> 0 | AB7: =S31 -> 0 | AC7: =SUM(AA7:AB7) -> 0 | AD7: =IFERROR(Z7*AC7,"-") -> 0
B8: TOTAL INGRESOS | C8: =SUM(C6:C7) -> 875 | D8: =SUM(D6:D7) -> 830 | R8: =AA8-AA17 -> 0 | S8: =AB8-AB17 -> 0 | T8: =SUM(R8:S8) -> 0 | U8: =IFERROR(Q8*T8,"-") -> 0 | AA8: =R32 -> 0 | AB8: =S32 -> 0 | AC8: =SUM(AA8:AB8) -> 0 | AD8: =IFERROR(Z8*AC8,"-") -> 0
B9: Gasto Blanks 1 | C9: =-$W$52 -> -578.11 | D9: =C9 -> -578.11 | P9: INGRESOS TOTALES FINALES | T9: =SUM(T3:T8) -> 25 | U9: =SUM(U3:U8) -> 875 | Y9: INGRESOS TOTALES | AC9: =SUM(AC3:AC8) -> 29 | AD9: =SUM(AD3:AD8) -> 1015
B10: Gasto Serigrafia | C10: =-$U$61 -> -212.72 | D10: =C10 -> -212.72
B11: Otros gastos | C11: 0 | Y11: GON JACO | Z11: COSTE | AA11: M | AB11: L | AC11: UNIDADES | AD11: TOTAL
Y12: =$P$27 -> CABEZA | Z12: =AA35 -> -25.984828 | AA12: 1 | AB12: 1 | AC12: =SUM(AA12:AB12) -> 2 | AD12: =IFERROR(Z12*AC12,"-") -> -51.969655
Y13: =$P$28 -> CALAVERA | Z13: =AA36 -> -27.194828 | AA13: 1 | AB13: 1 | AC13: =SUM(AA13:AB13) -> 2 | AD13: =IFERROR(Z13*AC13,"-") -> -54.389655
B14: TOTAL GASTOS | C14: =SUM(C9:C13) -> -790.83 | D14: =SUM(D9:D13) -> -790.83 | Y14: =$P$29 -> 0 | Z14: =AA37 -> 0 | AC14: =SUM(AA14:AB14) -> 0 | AD14: =IFERROR(Z14*AC14,"-") -> 0
Y15: =$P$30 -> 0 | Z15: =AA38 -> 0 | AC15: =SUM(AA15:AB15) -> 0 | AD15: =IFERROR(Z15*AC15,"-") -> 0
AC16: =SUM(AA16:AB16) -> 0 | AD16: =IFERROR(Z16*AC16,"-") -> 0
B17: BENEFICIO | C17: =C8+C14 -> 84.17 | D17: =D8+D14 -> 39.17 | AC17: =SUM(AA17:AB17) -> 0 | AD17: =IFERROR(Z17*AC17,"-") -> 0
Y18: COSTE TOTAL | AC18: =SUM(AC12:AC17) -> 4 | AD18: =SUM(AD12:AD17) -> -106.35931
B19: RATIO DE BLANKS | C19: =IFERROR(ABS($C$9/$C$8),"-") -> 0.66069714 | D19: =IFERROR(ABS($D$10/$D$8),"-") -> 0.25628916
B20: COR% | C20: =IFERROR(ABS($C$14/$C$8),"-") -> 0.90380571 | D20: =IFERROR(ABS($D$14/$D$8),"-") -> 0.95280723
C22: =$P$27 -> CABEZA | E22: =$P$28 -> CALAVERA | G22: =$P$29 -> 0 | I22: =$P$30 -> 0
C23: M | D23: L | E23: M | F23: L | G23: M | H23: L | I23: M | J23: L | K23: TOTAL
B24: SOLD | C24: =SUM(C27:C61) -> 8 | D24: =SUM(D27:D61) -> 7 | E24: =SUM(E27:E61) -> 5 | F24: =SUM(F27:F61) -> 5 | G24: =SUM(G27:G61) -> 0 | H24: =SUM(H27:H61) -> 0 | I24: =SUM(I27:I61) -> 0 | J24: =SUM(J27:J61) -> 0 | K24: =SUM(C24:J24) -> 25 | L24: =K24-SUM(K27:K61) -> 0
B25: STOCK | C25: =R3-C24 -> 0 | D25: =S3-D24 -> 0 | E25: =R4-E24 -> 0 | F25: =S4-F24 -> 0 | G25: =R5-G24 -> 0 | H25: =S5-H24 -> 0 | I25: =R6-I24 -> 0 | J25: =S6-J24 -> 0 | K25: =SUM(C25:J25) -> 0
B26: NOMBRE | K26: UNIDADES | L26: INGRESO | M26: FECHA | P26: BLANKS 1 | Q26: UND€ | R26: M | S26: L | T26: UNIDADES | U26: EXTRA | V26: € PER UND | W26: TOTAL | Y26: COSTE POR UND | Z26: BLANKS | AA26: SERIGRAFIA | AB26: EXTRA | AC26: TOTAL
A27: 1 | B27: PETER | D27: 1 | F27: 1 | K27: =SUM(C27:J27) -> 2 | L27: =IFERROR(((C27+D27)*$Q$3)+((E27+F27)*$Q$4)+((G27+H27)*$Q$5)+((I27+J27)*$Q$6),"-") -> 70 | P27: CABEZA | Q27: 10.26 | R27: 9 | S27: 8 | T27: =R27+S27 -> 17 | U27: =IFERROR($W$36/$T$33,"-") -> 9.6748276 | V27: =IFERROR(Q27+U27,"-") -> 19.934828 | W27: =IFERROR(T27*V27,"-") -> 338.89207 | Y27: =$P$27 -> CABEZA | Z27: =V27 -> 19.934828 | AA27: =T55 -> 6.05 | AC27: =SUM(Z27:AB27) -> 25.984828
A28: 2 | B28: JP | D28: 1 | K28: =SUM(C28:J28) -> 1 | L28: =IFERROR(((C28+D28)*$Q$3)+((E28+F28)*$Q$4)+((G28+H28)*$Q$5)+((I28+J28)*$Q$6),"-") -> 35 | P28: CALAVERA | Q28: 10.26 | R28: 6 | S28: 6 | T28: =R28+S28 -> 12 | U28: =IFERROR($W$36/$T$33,"-") -> 9.6748276 | V28: =IFERROR(Q28+U28,"-") -> 19.934828 | W28: =IFERROR(T28*V28,"-") -> 239.21793 | Y28: =$P$28 -> CALAVERA | Z28: =V28 -> 19.934828 | AA28: =T56 -> 7.26 | AC28: =SUM(Z28:AB28) -> 27.194828
A29: 3 | B29: PUPI | C29: 1 | K29: =SUM(C29:J29) -> 1 | L29: =IFERROR(((C29+D29)*$Q$3)+((E29+F29)*$Q$4)+((G29+H29)*$Q$5)+((I29+J29)*$Q$6),"-") -> 35 | T29: =R29+S29 -> 0 | V29: =IFERROR(Q29+U29,"-") -> 0 | W29: =IFERROR(T29*V29,"-") -> 0 | Y29: =$P$29 -> 0 | Z29: =V29 -> 0 | AA29: =T57 -> - | AC29: =SUM(Z29:AB29) -> 0
A30: =A29+1 -> 4 | B30: SESE | F30: 1 | K30: =SUM(C30:J30) -> 1 | L30: =IFERROR(((C30+D30)*$Q$3)+((E30+F30)*$Q$4)+((G30+H30)*$Q$5)+((I30+J30)*$Q$6),"-") -> 35 | T30: =R30+S30 -> 0 | V30: =IFERROR(Q30+U30,"-") -> 0 | W30: =IFERROR(T30*V30,"-") -> 0 | Y30: =$P$30 -> 0 | Z30: =V30 -> 0 | AA30: =T58 -> - | AC30: =SUM(Z30:AB30) -> 0
A31: =A30+1 -> 5 | B31: LUIS CANADA | C31: 1 | K31: =SUM(C31:J31) -> 1 | L31: =IFERROR(((C31+D31)*$Q$3)+((E31+F31)*$Q$4)+((G31+H31)*$Q$5)+((I31+J31)*$Q$6),"-") -> 35 | T31: =R31+S31 -> 0 | V31: =IFERROR(Q31+U31,"-") -> 0 | W31: =IFERROR(T31*V31,"-") -> 0 | AC31: =SUM(Z31:AB31) -> 0
A32: =A31+1 -> 6 | B32: MUÑOZ | D32: 1 | K32: =SUM(C32:J32) -> 1 | L32: =IFERROR(((C32+D32)*$Q$3)+((E32+F32)*$Q$4)+((G32+H32)*$Q$5)+((I32+J32)*$Q$6),"-") -> 35 | T32: =R32+S32 -> 0 | V32: =IFERROR(Q32+U32,"-") -> 0 | W32: =IFERROR(T32*V32,"-") -> 0 | AC32: =SUM(Z32:AB32) -> 0
A33: =A32+1 -> 7 | B33: NACHO BENITO | F33: 1 | K33: =SUM(C33:J33) -> 1 | L33: =IFERROR(((C33+D33)*$Q$3)+((E33+F33)*$Q$4)+((G33+H33)*$Q$5)+((I33+J33)*$Q$6),"-") -> 35 | P33: TOTAL | T33: =SUM(T27:T32) -> 29 | W33: =SUM(W27:W32) -> 578.11
A34: =A33+1 -> 8 | B34: NACHO PEREZ | E34: 1 | K34: =SUM(C34:J34) -> 1 | L34: =IFERROR(((C34+D34)*$Q$3)+((E34+F34)*$Q$4)+((G34+H34)*$Q$5)+((I34+J34)*$Q$6),"-") -> 35 | P34: Envio | W34: 90 | Y34: BENEFICIO POR UND | Z34: PRECIO | AA34: COSTE | AB34: BENEFICIO | AC34: MARGEN
A35: =A34+1 -> 9 | B35: DOMINGUEZ | C35: 1 | K35: =SUM(C35:J35) -> 1 | L35: =IFERROR(((C35+D35)*$Q$3)+((E35+F35)*$Q$4)+((G35+H35)*$Q$5)+((I35+J35)*$Q$6),"-") -> 35 | P35: Otros gastos | W35: 190.57 | Y35: =$P$27 -> CABEZA | Z35: 35 | AA35: =-AC27 -> -25.984828 | AB35: =SUM(Z35:AA35) -> 9.0151724 | AC35: =AB35/Z35 -> 0.25757635
A36: =A35+1 -> 10 | B36: CHORVO | D36: 1 | F36: 1 | K36: =SUM(C36:J36) -> 2 | L36: =IFERROR(((C36+D36)*$Q$3)+((E36+F36)*$Q$4)+((G36+H36)*$Q$5)+((I36+J36)*$Q$6),"-") -> 70 | P36: TOTAL EXTRAS | W36: =SUM(W34:W35) -> 280.57 | Y36: =$P$28 -> CALAVERA | Z36: 35 | AA36: =-AC28 -> -27.194828 | AB36: =SUM(Z36:AA36) -> 7.8051724 | AC36: =AB36/Z36 -> 0.22300493
A37: =A36+1 -> 11 | B37: CUERVO | E37: 1 | K37: =SUM(C37:J37) -> 1 | L37: =IFERROR(((C37+D37)*$Q$3)+((E37+F37)*$Q$4)+((G37+H37)*$Q$5)+((I37+J37)*$Q$6),"-") -> 35 | P37: BLANKS TOTAL | W37: =W33 -> 578.11 | Y37: =$P$29 -> 0 | AA37: =-AC29 -> 0 | AB37: =SUM(Z37:AA37) -> 0 | AC37: =AB37/Z37 -> #DIV/0!
A38: =A37+1 -> 12 | B38: JUANTO | E38: 1 | K38: =SUM(C38:J38) -> 1 | L38: =IFERROR(((C38+D38)*$Q$3)+((E38+F38)*$Q$4)+((G38+H38)*$Q$5)+((I38+J38)*$Q$6),"-") -> 35 | W38: =Q27*T27+Q28*T28+Q29*T29+Q30*T30+Q31*T31+Q32*T32+W36-W37 -> 0 | Y38: =$P$30 -> 0 | AA38: =-AC30 -> 0 | AB38: =SUM(Z38:AA38) -> 0 | AC38: =AB38/Z38 -> #DIV/0!
A39: =A38+1 -> 13 | B39: ALVARO NISTAL | C39: 1 | K39: =SUM(C39:J39) -> 1 | L39: =IFERROR(((C39+D39)*$Q$3)+((E39+F39)*$Q$4)+((G39+H39)*$Q$5)+((I39+J39)*$Q$6),"-") -> 35 | P39: BLANKS 2 | Q39: UND€ | R39: M | S39: L | T39: UNIDADES | U39: EXTRA | V39: € PER UND | W39: TOTAL
A40: =A39+1 -> 14 | B40: BARALLOBRE | D40: 1 | F40: 1 | K40: =SUM(C40:J40) -> 2 | L40: =IFERROR(((C40+D40)*$Q$3)+((E40+F40)*$Q$4)+((G40+H40)*$Q$5)+((I40+J40)*$Q$6),"-")-10 -> 60 | T40: =SUM(R40:S40) -> 0 | U40: =IFERROR($W$49/$T$46,"-") -> - | V40: =IFERROR(Q40+U40,"-") -> - | W40: =IFERROR(T40*V40,"-") -> -
A41: =A40+1 -> 15 | B41: GABRIEL | C41: 1 | K41: =SUM(C41:J41) -> 1 | L41: =IFERROR(((C41+D41)*$Q$3)+((E41+F41)*$Q$4)+((G41+H41)*$Q$5)+((I41+J41)*$Q$6),"-") -> 35 | T41: =SUM(R41:S41) -> 0 | U41: =IFERROR($W$49/$T$46,"-") -> - | V41: =IFERROR(Q41+U41,"-") -> - | W41: =IFERROR(T41*V41,"-") -> -
A42: =A41+1 -> 16 | B42: NATHAN | C42: 1 | K42: =SUM(C42:J42) -> 1 | L42: =IFERROR(((C42+D42)*$Q$3)+((E42+F42)*$Q$4)+((G42+H42)*$Q$5)+((I42+J42)*$Q$6),"-") -> 35 | T42: =SUM(R42:S42) -> 0 | U42: =IFERROR($W$49/$T$46,"-") -> - | V42: =IFERROR(Q42+U42,"-") -> - | W42: =IFERROR(T42*V42,"-") -> -
A43: =A42+1 -> 17 | B43: JAIME BUSTAMANTE | D43: 1 | E43: 1 | K43: =SUM(C43:J43) -> 2 | L43: =IFERROR(((C43+D43)*$Q$3)+((E43+F43)*$Q$4)+((G43+H43)*$Q$5)+((I43+J43)*$Q$6),"-") -> 70 | T43: =SUM(R43:S43) -> 0 | U43: =IFERROR($W$49/$T$46,"-") -> - | V43: =IFERROR(Q43+U43,"-") -> - | W43: =IFERROR(T43*V43,"-") -> -
A44: =A43+1 -> 18 | B44: JUANMA | C44: 1 | K44: =SUM(C44:J44) -> 1 | L44: =IFERROR(((C44+D44)*$Q$3)+((E44+F44)*$Q$4)+((G44+H44)*$Q$5)+((I44+J44)*$Q$6),"-") -> 35 | T44: =SUM(R44:S44) -> 0 | V44: =IFERROR(Q44+U44,"-") -> 0 | W44: =IFERROR(T44*V44,"-") -> 0
A45: =A44+1 -> 19 | B45: CRIS ARTEAGA | D45: 1 | K45: =SUM(C45:J45) -> 1 | L45: =IFERROR(((C45+D45)*$Q$3)+((E45+F45)*$Q$4)+((G45+H45)*$Q$5)+((I45+J45)*$Q$6),"-") -> 35 | T45: =SUM(R45:S45) -> 0 | V45: =IFERROR(Q45+U45,"-") -> 0 | W45: =IFERROR(T45*V45,"-") -> 0
A46: =A45+1 -> 20 | B46: BRUNITO | C46: 1 | K46: =SUM(C46:J46) -> 1 | L46: =IFERROR(((C46+D46)*$Q$3)+((E46+F46)*$Q$4)+((G46+H46)*$Q$5)+((I46+J46)*$Q$6),"-") -> 35 | P46: TOTAL | T46: =SUM(T40:T45) -> 0 | W46: =SUM(W40:W45) -> 0
A47: =A46+1 -> 21 | B47: CANALES | E47: 1 | K47: =SUM(C47:J47) -> 1 | P47: Envio
A48: =A47+1 -> 22 | K48: =SUM(C48:J48) -> 0 | L48: =IFERROR(((C48+D48)*$Q$3)+((E48+F48)*$Q$4)+((G48+H48)*$Q$5)+((I48+J48)*$Q$6),"-") -> 0 | P48: Otros gastos
A49: =A48+1 -> 23 | K49: =SUM(C49:J49) -> 0 | L49: =IFERROR(((C49+D49)*$Q$3)+((E49+F49)*$Q$4)+((G49+H49)*$Q$5)+((I49+J49)*$Q$6),"-") -> 0 | P49: TOTAL EXTRAS | W49: =SUM(W47:W48) -> 0
A50: =A49+1 -> 24 | K50: =SUM(C50:J50) -> 0 | L50: =IFERROR(((C50+D50)*$Q$3)+((E50+F50)*$Q$4)+((G50+H50)*$Q$5)+((I50+J50)*$Q$6),"-") -> 0 | P50: BLANKS TOTAL | W50: =-W46 -> 0
A51: =A50+1 -> 25 | K51: =SUM(C51:J51) -> 0 | L51: =IFERROR(((C51+D51)*$Q$3)+((E51+F51)*$Q$4)+((G51+H51)*$Q$5)+((I51+J51)*$Q$6),"-") -> 0 | W51: =Q40*T40+Q41*T41+Q42*T42+Q43*T43+Q44*T44+Q45*T45+W49+W50 -> 0
A52: =A51+1 -> 26 | K52: =SUM(C52:J52) -> 0 | L52: =IFERROR(((C52+D52)*$Q$3)+((E52+F52)*$Q$4)+((G52+H52)*$Q$5)+((I52+J52)*$Q$6),"-") -> 0 | P52: COSTE TOTAL BLANKS | W52: =W37+W50 -> 578.11
A53: =A52+1 -> 27 | K53: =SUM(C53:J53) -> 0 | L53: =IFERROR(((C53+D53)*$Q$3)+((E53+F53)*$Q$4)+((G53+H53)*$Q$5)+((I53+J53)*$Q$6),"-") -> 0
